counter/counter.sv
`ifndef __COUNTER_SV__
`define __COUNTER_SV__

`default_nettype none


module CntSecMinHr(
    input wire clk, rst,
    output logic [5:0] sec,
    output logic [5:0] min,
    output logic [4:0] hr
);
    logic en1sec, en1min, en1hr;
    Counter #(10) cnt1sec (.clk(clk), .rst(rst), .en(  1'b1), .cnt(),    .co(en1sec));
    Counter #(60) cnt60sec(.clk(clk), .rst(rst), .en(en1sec), .cnt(sec), .co(en1min));
    Counter #(60) cnt60min(.clk(clk), .rst(rst), .en(en1min), .cnt(min), .co(en1hr ));
    Counter #(24) cnt24hr (.clk(clk), .rst(rst), .en(en1hr ), .cnt(hr ), .co());
endmodule

module Counter #(
    parameter M = 100
)(
    input wire clk, rst, en,
    output logic [$clog2(M) - 1 : 0] cnt,
    output logic co
);
    assign co = en & (cnt == M - 1);
    always_ff@(posedge clk) begin
        if(rst) cnt <= '0;
        else if(en) begin
            if(cnt < M - 1) cnt <= cnt + 1'b1;
            else cnt <= '0;
        end
    end
endmodule

module CounterMax #(
    parameter DW = 8
)(
    input wire clk, rst, en,
    input wire [DW - 1 : 0] max,
    output logic [DW - 1 : 0] cnt,
    output logic co
);
    assign co = en & (cnt == max);
    always_ff@(posedge clk) begin
        if(rst) cnt <= '0;
        else if(en) begin
            if(cnt < max) cnt <= cnt + 1'b1;
            else cnt <= '0;
        end
    end
endmodule

`endif

edge2en/edge2en.sv
`ifndef __EDEG2EN_SV__
`define __EDEG2EN_SV__
`default_nettype none

module Rising2En #( parameter SYNC_STG = 1 )(
    input wire clk, in,
    output logic en, out
);
    logic [SYNC_STG : 0] dly;
    always_ff@(posedge clk) begin
        dly <= {dly[SYNC_STG - 1 : 0], in};
    end
    assign en = (SYNC_STG ? dly[SYNC_STG -: 2] : {dly, in}) == 2'b01;
    assign out = dly[SYNC_STG];
endmodule

module Falling2En #( parameter SYNC_STG = 1 )(
    input wire clk, in,
    output logic en, out
);
    logic [SYNC_STG : 0] dly;
    always_ff@(posedge clk) begin
        dly <= {dly[SYNC_STG - 1 : 0], in};
    end
    assign en = (SYNC_STG ? dly[SYNC_STG -: 2] : {dly, in}) == 2'b10;
    assign out = dly[SYNC_STG];
endmodule

module Edge2En #( parameter SYNC_STG = 1 )(
    input wire clk, in,
    output logic rising, falling, out
);
    logic [SYNC_STG : 0] dly;
    always_ff@(posedge clk) begin
        dly <= {dly[SYNC_STG - 1 : 0], in};
    end
    assign rising = (SYNC_STG ? dly[SYNC_STG -: 2] : {dly, in}) == 2'b01;
    assign falling = (SYNC_STG ? dly[SYNC_STG -: 2] : {dly, in}) == 2'b10;
    assign out = dly[SYNC_STG];
endmodule

`endif

iis/iis.sv
`ifndef __IIS_SV__
`define __IIS_SV__
`include "../counter/counter.sv"
`include "../edge2en/edge2en.sv"


module IisClkGen #(
    parameter SCK_TO_WS = 64,
    parameter MCK_TO_SCK = 8
)(
    input wire mck,
    output logic sck,
    output logic ws,
    output logic sck_fall,
    output logic frame_sync
);
    localparam SCKW = $clog2(MCK_TO_SCK);
    localparam WSW = $clog2(SCK_TO_WS);
    logic [SCKW - 1 : 0] cnt_sck;
    logic cnt_sck_co;
    logic [WSW - 1 : 0] cnt_ws;
    always_ff@(posedge mck) sck <= cnt_sck >= SCKW'(MCK_TO_SCK / 2);
    always_ff@(posedge mck) ws <= cnt_ws >= WSW'(SCK_TO_WS / 2);
    always_ff@(posedge mck) sck_fall <= cnt_sck_co;
    Counter #(MCK_TO_SCK) cntSck(
        mck, 1'b0, 1'b1, cnt_sck, cnt_sck_co);
    Counter #(SCK_TO_WS) cntWs(
        mck, 1'b0, cnt_sck_co, cnt_ws, );
    assign frame_sync = (cnt_ws == 0) && cnt_sck_co;
endmodule

module IisTransmitter (
    input wire mck,
    input wire sck_fall,
    input wire frame_sync,
    input wire signed [31:0] data[2], //data[0]: left; data[1]: right
    output logic data_rd,
    output logic iis_sd
);
    assign data_rd = frame_sync;
    logic data_rd_dly;
    logic [63:0] shift_reg;
    always_ff@(posedge mck) data_rd_dly <= data_rd;
    always_ff@(posedge mck) begin
        if(data_rd_dly) shift_reg <= {data[0], data[1]};
        else if(sck_fall) shift_reg <= {shift_reg[62:0], 1'b0};
    end
    assign iis_sd = shift_reg[63];
endmodule

module IisReceiver (
    input wire mck, iis_sck, iis_ws, iis_sd,
    output logic signed [31:0] data[2],
    output logic data_valid
);
    logic sck_rising, sck_reg, ws_falling, sd_reg;
    Rising2En #(2) sckRising(mck, iis_sck, sck_rising, sck_reg);
    Falling2En #(2) wsFalling(mck, iis_ws, ws_falling, );
    Rising2En #(2) sdSync(mck, iis_sd, , sd_reg);
    logic [7:0] bit_cnt;
    Counter #(256) bitCnt(mck, ws_falling, sck_rising, bit_cnt, );
    logic frame_end;
    always_ff@(posedge mck) frame_end <= (bit_cnt == 8'd0) && sck_rising;
    always_ff@(posedge mck) data_valid <= frame_end;
    logic [63:0] shift_reg;
    always_ff@(posedge mck) begin
        if(frame_end) {data[0], data[1]} <= shift_reg;
        else if(sck_rising) shift_reg <= {shift_reg[62:0], sd_reg};
    end
endmodule

`endif

iis/tb_iis.sv
`timescale 1ns/100ps
`default_nettype none
module TestIis;
    logic clk;
    initial begin
        #10
            clk=1'b0;
        forever  #40.69ns  clk=~clk;
    end
    initial begin
        $dumpfile("wave.vcd");
        $dumpvars(0, TestIis );
    #100000 $finish;
    end
    // ==== transmitter side ====
    logic sck, ws, sd, sck_fall, f_sync, txdata_rd;
    // sck 3.072M, ws 48k
    IisClkGen #(64, 8) iisClk(clk, sck, ws, sck_fall, f_sync);
    logic signed [31:0] txdata[2];
    IisTransmitter iisTrans(clk, sck_fall, f_sync, txdata, txdata_rd, sd);
    // ==== receiver side ====
    logic signed [31:0] rxdata[2];
    logic rxdata_valid;
    IisReceiver iisRecv(clk, sck, ws, sd, rxdata, rxdata_valid);
    // ==== transmitter side data ====
    always_ff@(posedge clk) begin
        if(txdata_rd) begin
            txdata[0] <= $random() ;
            txdata[1] <= $random() ;
        end
    end

endmodule

iis/wave.vcd
$date
	Thu Mar 21 10:26:08 2024
$end
$version
	Icarus Verilog
$end
$timescale
	100ps
$end
$scope module TestIis $end
$var wire 1 ! ws $end
$var wire 1 " txdata_rd $end
$var wire 1 # sd $end
$var wire 1 $ sck_fall $end
$var wire 1 % sck $end
$var wire 1 & rxdata_valid $end
$var wire 1 ' f_sync $end
$var reg 1 ( clk $end
$scope module iisClk $end
$var wire 1 ' frame_sync $end
$var wire 1 ( mck $end
$var wire 6 ) cnt_ws [5:0] $end
$var wire 1 * cnt_sck_co $end
$var wire 3 + cnt_sck [2:0] $end
$var parameter 32 , MCK_TO_SCK $end
$var parameter 32 - SCKW $end
$var parameter 32 . SCK_TO_WS $end
$var parameter 32 / WSW $end
$var reg 1 % sck $end
$var reg 1 $ sck_fall $end
$var reg 1 ! ws $end
$scope module cntSck $end
$var wire 1 ( clk $end
$var wire 1 * co $end
$var wire 1 0 en $end
$var wire 1 1 rst $end
$var parameter 32 2 M $end
$var reg 3 3 cnt [2:0] $end
$upscope $end
$scope module cntWs $end
$var wire 1 ( clk $end
$var wire 1 4 co $end
$var wire 1 * en $end
$var wire 1 5 rst $end
$var parameter 32 6 M $end
$var reg 6 7 cnt [5:0] $end
$upscope $end
$upscope $end
$scope module iisRecv $end
$var wire 1 % iis_sck $end
$var wire 1 ! iis_ws $end
$var wire 1 ( mck $end
$var wire 1 8 ws_falling $end
$var wire 1 9 sd_reg $end
$var wire 1 : sck_rising $end
$var wire 1 ; sck_reg $end
$var wire 1 # iis_sd $end
$var wire 8 < bit_cnt [7:0] $end
$var reg 1 & data_valid $end
$var reg 1 = frame_end $end
$var reg 64 > shift_reg [63:0] $end
$scope module bitCnt $end
$var wire 1 ( clk $end
$var wire 1 ? co $end
$var wire 1 8 rst $end
$var wire 1 : en $end
$var parameter 32 @ M $end
$var reg 8 A cnt [7:0] $end
$upscope $end
$scope module sckRising $end
$var wire 1 ( clk $end
$var wire 1 % in $end
$var wire 1 ; out $end
$var wire 1 : en $end
$var parameter 32 B SYNC_STG $end
$var reg 3 C dly [2:0] $end
$upscope $end
$scope module sdSync $end
$var wire 1 ( clk $end
$var wire 1 9 out $end
$var wire 1 # in $end
$var wire 1 D en $end
$var parameter 32 E SYNC_STG $end
$var reg 3 F dly [2:0] $end
$upscope $end
$scope module wsFalling $end
$var wire 1 ( clk $end
$var wire 1 ! in $end
$var wire 1 G out $end
$var wire 1 8 en $end
$var parameter 32 H SYNC_STG $end
$var reg 3 I dly [2:0] $end
$upscope $end
$upscope $end
$scope module iisTrans $end
$var wire 1 " data_rd $end
$var wire 1 ' frame_sync $end
$var wire 1 ( mck $end
$var wire 1 $ sck_fall $end
$var wire 1 # iis_sd $end
$var reg 1 J data_rd_dly $end
$var reg 64 K shift_reg [63:0] $end
$upscope $end
$upscope $end
$enddefinitions $end
$comment Show the parameter values. $end
$dumpall
b10 H
b10 E
b10 B
b100000000 @
b1000000 6
b1000 2
b110 /
b1000000 .
b11 -
b1000 ,
$end
#0
$dumpvars
bx K
xJ
bx I
xG
bx F
xD
bx C
bx A
x?
bx >
x=
bx <
x;
x:
x9
x8
bx 7
05
x4
bx 3
01
10
bx +
x*
bx )
x(
x'
x&
x%
x$
x#
x"
x!
$end
#100
0(
#507
04
0"
0'
0*
b0 +
b0 3
1(
#914
0(
#1321
0J
0$
0%
b1 +
b1 3
1(
#1728
0(
#2135
b10 +
b10 3
bx0 C
1(
#2542
0(
#2949
0?
0:
bx00 C
b11 +
b11 3
1(
#3356
0(
#3763
0;
b100 +
b100 3
b0 C
0=
1(
#4170
0(
#4577
0&
1%
b101 +
b101 3
1(
#4984
0(
#5391
b110 +
b110 3
b1 C
1(
#5798
0(
#6205
x?
x4
x"
x'
1:
1*
b11 C
b111 +
b111 3
1(
#6612
0(
#7019
0*
04
0"
0'
0:
1;
0?
b0 +
b0 3
b0 )
b0 7
1$
xJ
b111 C
b0 <
b0 A
x=
1(
#7426
0(
#7833
x&
0=
bx0 K
0J
0$
0!
0%
b1 +
b1 3
1(
#8240
0(
#8647
b10 +
b10 3
b110 C
bx0 I
0&
1(
#9054
0(
#9461
bx00 I
b100 C
b11 +
b11 3
1(
#9868
0(
#10275
0;
08
0G
b100 +
b100 3
b0 C
b0 I
1(
#10682
0(
#11089
1%
b101 +
b101 3
1(
#11496
0(
#11903
b110 +
b110 3
b1 C
1(
#12310
0(
#12717
1"
1'
1:
1*
b11 C
b111 +
b111 3
1(
#13124
0(
#13531
0*
0"
0'
0:
1;
b0 +
b0 3
b1 )
b1 7
1$
1J
b111 C
b1 <
b1 A
1=
1(
#13938
0(
#14345
0#
1&
0=
b1001000010101001101010010010011000000100010010101111010000001 K
0J
0$
0%
b1 +
b1 3
1(
#14752
0(
#15159
b10 +
b10 3
b110 C
bx0 F
0&
1(
#15566
0(
#15973
0D
bx00 F
b100 C
b11 +
b11 3
1(
#16380
0(
#16787
0;
09
b100 +
b100 3
b0 C
b0 F
1(
#17194
0(
#17601
1%
b101 +
b101 3
1(
#18008
0(
#18415
b110 +
b110 3
b1 C
1(
#18822
0(
#19229
1:
1*
b11 C
b111 +
b111 3
1(
#19636
0(
#20043
0*
0:
1;
b0 +
b0 3
b10 )
b10 7
1$
b111 C
b10 <
b10 A
bx0 >
1(
#20450
0(
#20857
b10010000101010011010100100100110000001000100101011110100000010 K
0$
0%
b1 +
b1 3
1(
#21264
0(
#21671
b10 +
b10 3
b110 C
1(
#22078
0(
#22485
b100 C
b11 +
b11 3
1(
#22892
0(
#23299
0;
b100 +
b100 3
b0 C
1(
#23706
0(
#24113
1%
b101 +
b101 3
1(
#24520
0(
#24927
b110 +
b110 3
b1 C
1(
#25334
0(
#25741
1:
1*
b11 C
b111 +
b111 3
1(
#26148
0(
#26555
0*
0:
1;
b0 +
b0 3
b11 )
b11 7
1$
b111 C
b11 <
b11 A
bx00 >
1(
#26962
0(
#27369
b100100001010100110101001001001100000010001001010111101000000100 K
0$
0%
b1 +
b1 3
1(
#27776
0(
#28183
b10 +
b10 3
b110 C
1(
#28590
0(
#28997
b100 C
b11 +
b11 3
1(
#29404
0(
#29811
0;
b100 +
b100 3
b0 C
1(
#30218
0(
#30625
1%
b101 +
b101 3
1(
#31032
0(
#31439
b110 +
b110 3
b1 C
1(
#31846
0(
#32253
1:
1*
b11 C
b111 +
b111 3
1(
#32660
0(
#33067
0*
0:
1;
b0 +
b0 3
b100 )
b100 7
1$
b111 C
b100 <
b100 A
bx000 >
1(
#33474
0(
#33881
1#
b1001000010101001101010010010011000000100010010101111010000001000 K
0$
0%
b1 +
b1 3
1(
#34288
0(
#34695
b10 +
b10 3
b110 C
b1 F
1(
#35102
0(
#35509
1D
b11 F
b100 C
b11 +
b11 3
1(
#35916
0(
#36323
0;
0D
19
b100 +
b100 3
b0 C
b111 F
1(
#36730
0(
#37137
1%
b101 +
b101 3
1(
#37544
0(
#37951
b110 +
b110 3
b1 C
1(
#38358
0(
#38765
1:
1*
b11 C
b111 +
b111 3
1(
#39172
0(
#39579
0*
0:
1;
b0 +
b0 3
b101 )
b101 7
1$
b111 C
b101 <
b101 A
bx0001 >
1(
#39986
0(
#40393
0#
b10000101010011010100100100110000001000100101011110100000010000 K
0$
0%
b1 +
b1 3
1(
#40800
0(
#41207
b10 +
b10 3
b110 C
b110 F
1(
#41614
0(
#42021
b100 F
b100 C
b11 +
b11 3
1(
#42428
0(
#42835
0;
09
b100 +
b100 3
b0 C
b0 F
1(
#43242
0(
#43649
1%
b101 +
b101 3
1(
#44056
0(
#44463
b110 +
b110 3
b1 C
1(
#44870
0(
#45277
1:
1*
b11 C
b111 +
b111 3
1(
#45684
0(
#46091
0*
0:
1;
b0 +
b0 3
b110 )
b110 7
1$
b111 C
b110 <
b110 A
bx00010 >
1(
#46498
0(
#46905
b100001010100110101001001001100000010001001010111101000000100000 K
0$
0%
b1 +
b1 3
1(
#47312
0(
#47719
b10 +
b10 3
b110 C
1(
#48126
0(
#48533
b100 C
b11 +
b11 3
1(
#48940
0(
#49347
0;
b100 +
b100 3
b0 C
1(
#49754
0(
#50161
1%
b101 +
b101 3
1(
#50568
0(
#50975
b110 +
b110 3
b1 C
1(
#51382
0(
#51789
1:
1*
b11 C
b111 +
b111 3
1(
#52196
0(
#52603
0*
0:
1;
b0 +
b0 3
b111 )
b111 7
1$
b111 C
b111 <
b111 A
bx000100 >
1(
#53010
0(
#53417
1#
b1000010101001101010010010011000000100010010101111010000001000000 K
0$
0%
b1 +
b1 3
1(
#53824
0(
#54231
b10 +
b10 3
b110 C
b1 F
1(
#54638
0(
#55045
1D
b11 F
b100 C
b11 +
b11 3
1(
#55452
0(
#55859
0;
0D
19
b100 +
b100 3
b0 C
b111 F
1(
#56266
0(
#56673
1%
b101 +
b101 3
1(
#57080
0(
#57487
b110 +
b110 3
b1 C
1(
#57894
0(
#58301
1:
1*
b11 C
b111 +
b111 3
1(
#58708
0(
#59115
0*
0:
1;
b0 +
b0 3
b1000 )
b1000 7
1$
b111 C
b1000 <
b1000 A
bx0001001 >
1(
#59522
0(
#59929
0#
b101010011010100100100110000001000100101011110100000010000000 K
0$
0%
b1 +
b1 3
1(
#60336
0(
#60743
b10 +
b10 3
b110 C
b110 F
1(
#61150
0(
#61557
b100 F
b100 C
b11 +
b11 3
1(
#61964
0(
#62371
0;
09
b100 +
b100 3
b0 C
b0 F
1(
#62778
0(
#63185
1%
b101 +
b101 3
1(
#63592
0(
#63999
b110 +
b110 3
b1 C
1(
#64406
0(
#64813
1:
1*
b11 C
b111 +
b111 3
1(
#65220
0(
#65627
0*
0:
1;
b0 +
b0 3
b1001 )
b1001 7
1$
b111 C
b1001 <
b1001 A
bx00010010 >
1(
#66034
0(
#66441
b1010100110101001001001100000010001001010111101000000100000000 K
0$
0%
b1 +
b1 3
1(
#66848
0(
#67255
b10 +
b10 3
b110 C
1(
#67662
0(
#68069
b100 C
b11 +
b11 3
1(
#68476
0(
#68883
0;
b100 +
b100 3
b0 C
1(
#69290
0(
#69697
1%
b101 +
b101 3
1(
#70104
0(
#70511
b110 +
b110 3
b1 C
1(
#70918
0(
#71325
1:
1*
b11 C
b111 +
b111 3
1(
#71732
0(
#72139
0*
0:
1;
b0 +
b0 3
b1010 )
b1010 7
1$
b111 C
b1010 <
b1010 A
bx000100100 >
1(
#72546
0(
#72953
b10101001101010010010011000000100010010101111010000001000000000 K
0$
0%
b1 +
b1 3
1(
#73360
0(
#73767
b10 +
b10 3
b110 C
1(
#74174
0(
#74581
b100 C
b11 +
b11 3
1(
#74988
0(
#75395
0;
b100 +
b100 3
b0 C
1(
#75802
0(
#76209
1%
b101 +
b101 3
1(
#76616
0(
#77023
b110 +
b110 3
b1 C
1(
#77430
0(
#77837
1:
1*
b11 C
b111 +
b111 3
1(
#78244
0(
#78651
0*
0:
1;
b0 +
b0 3
b1011 )
b1011 7
1$
b111 C
b1011 <
b1011 A
bx0001001000 >
1(
#79058
0(
#79465
b101010011010100100100110000001000100101011110100000010000000000 K
0$
0%
b1 +
b1 3
1(
#79872
0(
#80279
b10 +
b10 3
b110 C
1(
#80686
0(
#81093
b100 C
b11 +
b11 3
1(
#81500
0(
#81907
0;
b100 +
b100 3
b0 C
1(
#82314
0(
#82721
1%
b101 +
b101 3
1(
#83128
0(
#83535
b110 +
b110 3
b1 C
1(
#83942
0(
#84349
1:
1*
b11 C
b111 +
b111 3
1(
#84756
0(
#85163
0*
0:
1;
b0 +
b0 3
b1100 )
b1100 7
1$
b111 C
b1100 <
b1100 A
bx00010010000 >
1(
#85570
0(
#85977
1#
b1010100110101001001001100000010001001010111101000000100000000000 K
0$
0%
b1 +
b1 3
1(
#86384
0(
#86791
b10 +
b10 3
b110 C
b1 F
1(
#87198
0(
#87605
1D
b11 F
b100 C
b11 +
b11 3
1(
#88012
0(
#88419
0;
0D
19
b100 +
b100 3
b0 C
b111 F
1(
#88826
0(
#89233
1%
b101 +
b101 3
1(
#89640
0(
#90047
b110 +
b110 3
b1 C
1(
#90454
0(
#90861
1:
1*
b11 C
b111 +
b111 3
1(
#91268
0(
#91675
0*
0:
1;
b0 +
b0 3
b1101 )
b1101 7
1$
b111 C
b1101 <
b1101 A
bx000100100001 >
1(
#92082
0(
#92489
0#
b101001101010010010011000000100010010101111010000001000000000000 K
0$
0%
b1 +
b1 3
1(
#92896
0(
#93303
b10 +
b10 3
b110 C
b110 F
1(
#93710
0(
#94117
b100 F
b100 C
b11 +
b11 3
1(
#94524
0(
#94931
0;
09
b100 +
b100 3
b0 C
b0 F
1(
#95338
0(
#95745
1%
b101 +
b101 3
1(
#96152
0(
#96559
b110 +
b110 3
b1 C
1(
#96966
0(
#97373
1:
1*
b11 C
b111 +
b111 3
1(
#97780
0(
#98187
0*
0:
1;
b0 +
b0 3
b1110 )
b1110 7
1$
b111 C
b1110 <
b1110 A
bx0001001000010 >
1(
#98594
0(
#99001
1#
b1010011010100100100110000001000100101011110100000010000000000000 K
0$
0%
b1 +
b1 3
1(
#99408
0(
#99815
b10 +
b10 3
b110 C
b1 F
1(
#100222
0(
#100629
1D
b11 F
b100 C
b11 +
b11 3
1(
#101036
0(
#101443
0;
0D
19
b100 +
b100 3
b0 C
b111 F
1(
#101850
0(
#102257
1%
b101 +
b101 3
1(
#102664
0(
#103071
b110 +
b110 3
b1 C
1(
#103478
0(
#103885
1:
1*
b11 C
b111 +
b111 3
1(
#104292
0(
#104699
0*
0:
1;
b0 +
b0 3
b1111 )
b1111 7
1$
b111 C
b1111 <
b1111 A
bx00010010000101 >
1(
#105106
0(
#105513
0#
b100110101001001001100000010001001010111101000000100000000000000 K
0$
0%
b1 +
b1 3
1(
#105920
0(
#106327
b10 +
b10 3
b110 C
b110 F
1(
#106734
0(
#107141
b100 F
b100 C
b11 +
b11 3
1(
#107548
0(
#107955
0;
09
b100 +
b100 3
b0 C
b0 F
1(
#108362
0(
#108769
1%
b101 +
b101 3
1(
#109176
0(
#109583
b110 +
b110 3
b1 C
1(
#109990
0(
#110397
1:
1*
b11 C
b111 +
b111 3
1(
#110804
0(
#111211
0*
0:
1;
b0 +
b0 3
b10000 )
b10000 7
1$
b111 C
b10000 <
b10000 A
bx000100100001010 >
1(
#111618
0(
#112025
1#
b1001101010010010011000000100010010101111010000001000000000000000 K
0$
0%
b1 +
b1 3
1(
#112432
0(
#112839
b10 +
b10 3
b110 C
b1 F
1(
#113246
0(
#113653
1D
b11 F
b100 C
b11 +
b11 3
1(
#114060
0(
#114467
0;
0D
19
b100 +
b100 3
b0 C
b111 F
1(
#114874
0(
#115281
1%
b101 +
b101 3
1(
#115688
0(
#116095
b110 +
b110 3
b1 C
1(
#116502
0(
#116909
1:
1*
b11 C
b111 +
b111 3
1(
#117316
0(
#117723
0*
0:
1;
b0 +
b0 3
b10001 )
b10001 7
1$
b111 C
b10001 <
b10001 A
bx0001001000010101 >
1(
#118130
0(
#118537
0#
b11010100100100110000001000100101011110100000010000000000000000 K
0$
0%
b1 +
b1 3
1(
#118944
0(
#119351
b10 +
b10 3
b110 C
b110 F
1(
#119758
0(
#120165
b100 F
b100 C
b11 +
b11 3
1(
#120572
0(
#120979
0;
09
b100 +
b100 3
b0 C
b0 F
1(
#121386
0(
#121793
1%
b101 +
b101 3
1(
#122200
0(
#122607
b110 +
b110 3
b1 C
1(
#123014
0(
#123421
1:
1*
b11 C
b111 +
b111 3
1(
#123828
0(
#124235
0*
0:
1;
b0 +
b0 3
b10010 )
b10010 7
1$
b111 C
b10010 <
b10010 A
bx00010010000101010 >
1(
#124642
0(
#125049
b110101001001001100000010001001010111101000000100000000000000000 K
0$
0%
b1 +
b1 3
1(
#125456
0(
#125863
b10 +
b10 3
b110 C
1(
#126270
0(
#126677
b100 C
b11 +
b11 3
1(
#127084
0(
#127491
0;
b100 +
b100 3
b0 C
1(
#127898
0(
#128305
1%
b101 +
b101 3
1(
#128712
0(
#129119
b110 +
b110 3
b1 C
1(
#129526
0(
#129933
1:
1*
b11 C
b111 +
b111 3
1(
#130340
0(
#130747
0*
0:
1;
b0 +
b0 3
b10011 )
b10011 7
1$
b111 C
b10011 <
b10011 A
bx000100100001010100 >
1(
#131154
0(
#131561
1#
b1101010010010011000000100010010101111010000001000000000000000000 K
0$
0%
b1 +
b1 3
1(
#131968
0(
#132375
b10 +
b10 3
b110 C
b1 F
1(
#132782
0(
#133189
1D
b11 F
b100 C
b11 +
b11 3
1(
#133596
0(
#134003
0;
0D
19
b100 +
b100 3
b0 C
b111 F
1(
#134410
0(
#134817
1%
b101 +
b101 3
1(
#135224
0(
#135631
b110 +
b110 3
b1 C
1(
#136038
0(
#136445
1:
1*
b11 C
b111 +
b111 3
1(
#136852
0(
#137259
0*
0:
1;
b0 +
b0 3
b10100 )
b10100 7
1$
b111 C
b10100 <
b10100 A
bx0001001000010101001 >
1(
#137666
0(
#138073
b1010100100100110000001000100101011110100000010000000000000000000 K
0$
0%
b1 +
b1 3
1(
#138480
0(
#138887
b10 +
b10 3
b110 C
1(
#139294
0(
#139701
b100 C
b11 +
b11 3
1(
#140108
0(
#140515
0;
b100 +
b100 3
b0 C
1(
#140922
0(
#141329
1%
b101 +
b101 3
1(
#141736
0(
#142143
b110 +
b110 3
b1 C
1(
#142550
0(
#142957
1:
1*
b11 C
b111 +
b111 3
1(
#143364
0(
#143771
0*
0:
1;
b0 +
b0 3
b10101 )
b10101 7
1$
b111 C
b10101 <
b10101 A
bx00010010000101010011 >
1(
#144178
0(
#144585
0#
b101001001001100000010001001010111101000000100000000000000000000 K
0$
0%
b1 +
b1 3
1(
#144992
0(
#145399
b10 +
b10 3
b110 C
b110 F
1(
#145806
0(
#146213
b100 F
b100 C
b11 +
b11 3
1(
#146620
0(
#147027
0;
09
b100 +
b100 3
b0 C
b0 F
1(
#147434
0(
#147841
1%
b101 +
b101 3
1(
#148248
0(
#148655
b110 +
b110 3
b1 C
1(
#149062
0(
#149469
1:
1*
b11 C
b111 +
b111 3
1(
#149876
0(
#150283
0*
0:
1;
b0 +
b0 3
b10110 )
b10110 7
1$
b111 C
b10110 <
b10110 A
bx000100100001010100110 >
1(
#150690
0(
#151097
1#
b1010010010011000000100010010101111010000001000000000000000000000 K
0$
0%
b1 +
b1 3
1(
#151504
0(
#151911
b10 +
b10 3
b110 C
b1 F
1(
#152318
0(
#152725
1D
b11 F
b100 C
b11 +
b11 3
1(
#153132
0(
#153539
0;
0D
19
b100 +
b100 3
b0 C
b111 F
1(
#153946
0(
#154353
1%
b101 +
b101 3
1(
#154760
0(
#155167
b110 +
b110 3
b1 C
1(
#155574
0(
#155981
1:
1*
b11 C
b111 +
b111 3
1(
#156388
0(
#156795
0*
0:
1;
b0 +
b0 3
b10111 )
b10111 7
1$
b111 C
b10111 <
b10111 A
bx0001001000010101001101 >
1(
#157202
0(
#157609
0#
b100100100110000001000100101011110100000010000000000000000000000 K
0$
0%
b1 +
b1 3
1(
#158016
0(
#158423
b10 +
b10 3
b110 C
b110 F
1(
#158830
0(
#159237
b100 F
b100 C
b11 +
b11 3
1(
#159644
0(
#160051
0;
09
b100 +
b100 3
b0 C
b0 F
1(
#160458
0(
#160865
1%
b101 +
b101 3
1(
#161272
0(
#161679
b110 +
b110 3
b1 C
1(
#162086
0(
#162493
1:
1*
b11 C
b111 +
b111 3
1(
#162900
0(
#163307
0*
0:
1;
b0 +
b0 3
b11000 )
b11000 7
1$
b111 C
b11000 <
b11000 A
bx00010010000101010011010 >
1(
#163714
0(
#164121
1#
b1001001001100000010001001010111101000000100000000000000000000000 K
0$
0%
b1 +
b1 3
1(
#164528
0(
#164935
b10 +
b10 3
b110 C
b1 F
1(
#165342
0(
#165749
1D
b11 F
b100 C
b11 +
b11 3
1(
#166156
0(
#166563
0;
0D
19
b100 +
b100 3
b0 C
b111 F
1(
#166970
0(
#167377
1%
b101 +
b101 3
1(
#167784
0(
#168191
b110 +
b110 3
b1 C
1(
#168598
0(
#169005
1:
1*
b11 C
b111 +
b111 3
1(
#169412
0(
#169819
0*
0:
1;
b0 +
b0 3
b11001 )
b11001 7
1$
b111 C
b11001 <
b11001 A
bx000100100001010100110101 >
1(
#170226
0(
#170633
0#
b10010011000000100010010101111010000001000000000000000000000000 K
0$
0%
b1 +
b1 3
1(
#171040
0(
#171447
b10 +
b10 3
b110 C
b110 F
1(
#171854
0(
#172261
b100 F
b100 C
b11 +
b11 3
1(
#172668
0(
#173075
0;
09
b100 +
b100 3
b0 C
b0 F
1(
#173482
0(
#173889
1%
b101 +
b101 3
1(
#174296
0(
#174703
b110 +
b110 3
b1 C
1(
#175110
0(
#175517
1:
1*
b11 C
b111 +
b111 3
1(
#175924
0(
#176331
0*
0:
1;
b0 +
b0 3
b11010 )
b11010 7
1$
b111 C
b11010 <
b11010 A
bx0001001000010101001101010 >
1(
#176738
0(
#177145
b100100110000001000100101011110100000010000000000000000000000000 K
0$
0%
b1 +
b1 3
1(
#177552
0(
#177959
b10 +
b10 3
b110 C
1(
#178366
0(
#178773
b100 C
b11 +
b11 3
1(
#179180
0(
#179587
0;
b100 +
b100 3
b0 C
1(
#179994
0(
#180401
1%
b101 +
b101 3
1(
#180808
0(
#181215
b110 +
b110 3
b1 C
1(
#181622
0(
#182029
1:
1*
b11 C
b111 +
b111 3
1(
#182436
0(
#182843
0*
0:
1;
b0 +
b0 3
b11011 )
b11011 7
1$
b111 C
b11011 <
b11011 A
bx00010010000101010011010100 >
1(
#183250
0(
#183657
1#
b1001001100000010001001010111101000000100000000000000000000000000 K
0$
0%
b1 +
b1 3
1(
#184064
0(
#184471
b10 +
b10 3
b110 C
b1 F
1(
#184878
0(
#185285
1D
b11 F
b100 C
b11 +
b11 3
1(
#185692
0(
#186099
0;
0D
19
b100 +
b100 3
b0 C
b111 F
1(
#186506
0(
#186913
1%
b101 +
b101 3
1(
#187320
0(
#187727
b110 +
b110 3
b1 C
1(
#188134
0(
#188541
1:
1*
b11 C
b111 +
b111 3
1(
#188948
0(
#189355
0*
0:
1;
b0 +
b0 3
b11100 )
b11100 7
1$
b111 C
b11100 <
b11100 A
bx000100100001010100110101001 >
1(
#189762
0(
#190169
0#
b10011000000100010010101111010000001000000000000000000000000000 K
0$
0%
b1 +
b1 3
1(
#190576
0(
#190983
b10 +
b10 3
b110 C
b110 F
1(
#191390
0(
#191797
b100 F
b100 C
b11 +
b11 3
1(
#192204
0(
#192611
0;
09
b100 +
b100 3
b0 C
b0 F
1(
#193018
0(
#193425
1%
b101 +
b101 3
1(
#193832
0(
#194239
b110 +
b110 3
b1 C
1(
#194646
0(
#195053
1:
1*
b11 C
b111 +
b111 3
1(
#195460
0(
#195867
0*
0:
1;
b0 +
b0 3
b11101 )
b11101 7
1$
b111 C
b11101 <
b11101 A
bx0001001000010101001101010010 >
1(
#196274
0(
#196681
b100110000001000100101011110100000010000000000000000000000000000 K
0$
0%
b1 +
b1 3
1(
#197088
0(
#197495
b10 +
b10 3
b110 C
1(
#197902
0(
#198309
b100 C
b11 +
b11 3
1(
#198716
0(
#199123
0;
b100 +
b100 3
b0 C
1(
#199530
0(
#199937
1%
b101 +
b101 3
1(
#200344
0(
#200751
b110 +
b110 3
b1 C
1(
#201158
0(
#201565
1:
1*
b11 C
b111 +
b111 3
1(
#201972
0(
#202379
0*
0:
1;
b0 +
b0 3
b11110 )
b11110 7
1$
b111 C
b11110 <
b11110 A
bx00010010000101010011010100100 >
1(
#202786
0(
#203193
1#
b1001100000010001001010111101000000100000000000000000000000000000 K
0$
0%
b1 +
b1 3
1(
#203600
0(
#204007
b10 +
b10 3
b110 C
b1 F
1(
#204414
0(
#204821
1D
b11 F
b100 C
b11 +
b11 3
1(
#205228
0(
