edge2en/edge2en.sv
`ifndef __EDEG2EN_SV__
`define __EDEG2EN_SV__
`default_nettype none

module Rising2En #( parameter SYNC_STG = 1 )(
    input wire clk, in,
    output logic en, out
);
    logic [SYNC_STG : 0] dly;
    always_ff@(posedge clk) begin
        dly <= {dly[SYNC_STG - 1 : 0], in};
    end
    assign en = (SYNC_STG ? dly[SYNC_STG -: 2] : {dly, in}) == 2'b01;
    assign out = dly[SYNC_STG];
endmodule

module Falling2En #( parameter SYNC_STG = 1 )(
    input wire clk, in,
    output logic en, out
);
    logic [SYNC_STG : 0] dly;
    always_ff@(posedge clk) begin
        dly <= {dly[SYNC_STG - 1 : 0], in};
    end
    assign en = (SYNC_STG ? dly[SYNC_STG -: 2] : {dly, in}) == 2'b10;
    assign out = dly[SYNC_STG];
endmodule

module Edge2En #( parameter SYNC_STG = 1 )(
    input wire clk, in,
    output logic rising, falling, out
);
    logic [SYNC_STG : 0] dly;
    always_ff@(posedge clk) begin
        dly <= {dly[SYNC_STG - 1 : 0], in};
    end
    assign rising = (SYNC_STG ? dly[SYNC_STG -: 2] : {dly, in}) == 2'b01;
    assign falling = (SYNC_STG ? dly[SYNC_STG -: 2] : {dly, in}) == 2'b10;
    assign out = dly[SYNC_STG];
endmodule

`endif

template/tb_template.sv
`timescale 1ns/1ns
`default_nettype none
module TestEdge2En;
    logic clk;
    initial begin
        #0
            clk=1'b0;
        forever  #5  clk=~clk;
    end
    logic in;
    initial begin
        in = 0;
        #44 in = 1;
        #56 in = 0;
    end
    initial begin
        $dumpfile("wave.vcd");
        $dumpvars(0, TestEdge2En );
    #150 $finish;
    end
    logic en1, en2, enR, enF;
    logic out1, out2, outRF;
    //Rising2En #(1) theR2E0(clk, in, en0, );
    Rising2En theR2E1(clk, in, en1, out1);
    Rising2En #(2) theR2E2(clk, in, en2, out2);
    Edge2En #(1) theEd2E(clk, in, enR, enF, outRF);
endmodule

edge2en/wave.vcd
$date
	Wed Feb 21 14:28:10 2024
$end
$version
	Icarus Verilog
$end
$timescale
	1ns
$end
$scope module TestEdge2En $end
$var wire 1 ! outRF $end
$var wire 1 " out2 $end
$var wire 1 # out1 $end
$var wire 1 $ enR $end
$var wire 1 % enF $end
$var wire 1 & en2 $end
$var wire 1 ' en1 $end
$var reg 1 ( clk $end
$var reg 1 ) in $end
$scope module theEd2E $end
$var wire 1 ( clk $end
$var wire 1 ) in $end
$var wire 1 $ rising $end
$var wire 1 ! out $end
$var wire 1 % falling $end
$var parameter 32 * SYNC_STG $end
$var reg 2 + dly [1:0] $end
$upscope $end
$scope module theR2E1 $end
$var wire 1 ( clk $end
$var wire 1 ) in $end
$var wire 1 # out $end
$var wire 1 ' en $end
$var parameter 32 , SYNC_STG $end
$var reg 2 - dly [1:0] $end
$upscope $end
$scope module theR2E2 $end
$var wire 1 ( clk $end
$var wire 1 ) in $end
$var wire 1 " out $end
$var wire 1 & en $end
$var parameter 32 . SYNC_STG $end
$var reg 3 / dly [2:0] $end
$upscope $end
$upscope $end
$enddefinitions $end
$comment Show the parameter values. $end
$dumpall
b10 .
b1 ,
b1 *
$end
#0
$dumpvars
bx /
bx -
bx +
0)
0(
x'
x&
x%
x$
x#
x"
x!
$end
#5
0'
0$
bx0 -
bx0 /
bx0 +
1(
#10
0(
#15
0%
0!
0&
0#
b0 +
bx00 /
b0 -
1(
#20
0(
#25
0"
b0 /
1(
#30
0(
#35
1(
#40
0(
#44
1)
#45
1'
1$
b1 -
b1 /
b1 +
1(
#50
0(
#55
0$
1!
1&
0'
1#
b11 +
b11 /
b11 -
1(
#60
0(
#65
0&
1"
b111 /
1(
#70
0(
#75
1(
#80
0(
#85
1(
#90
0(
#95
1(
#100
0(
0)
#105
1%
b10 -
b110 /
b10 +
1(
#110
0(
#115
0%
0!
0#
b0 +
b100 /
b0 -
1(
#120
0(
#125
0"
b0 /
1(
