memory/memory.sv
`ifndef __MEMORY_SV__
`define __MEMORY_SV__
`default_nettype none
module SpRamRf #(
    parameter DW = 8, WORDS = 256
)(
    input wire clk,
    input wire [$clog2(WORDS) - 1 : 0] addr,
    input wire we,
    input wire [DW - 1 : 0] din,
    output logic [DW - 1 : 0] qout
);
    logic [DW - 1 : 0] ram[WORDS];
    initial begin
        for(integer i = 0; i <WORDS; i = i + 1) begin
            ram[i] <= 0;
        end
    end
    always_ff@(posedge clk) begin
        if(we) ram[addr] <= din;
        qout <= ram[addr];
    end
endmodule

module SpRamRa #(   // asynchronous read
    parameter DW = 8, WORDS = 256
)(
    input wire clk,
    input wire [$clog2(WORDS) - 1 : 0] addr,
    input wire we,
    input wire [DW - 1 : 0] din,
    output logic [DW - 1 : 0] qout
);
    logic [DW - 1 : 0] ram[WORDS];
    always_ff@(posedge clk) begin
        if(we) ram[addr] <= din;
    end
    assign qout = ram[addr];
endmodule

module SpRamWf #(
    parameter DW = 8, WORDS = 256
)(
    input wire clk,
    input wire [$clog2(WORDS) - 1 : 0] addr,
    input wire we,
    input wire [DW - 1 : 0] din,
    output logic [DW - 1 : 0] qout
);
    logic [DW - 1 : 0] ram[WORDS];
    always_ff@(posedge clk) begin
        if(we) begin
            ram[addr] <= din;
            qout <= din;
        end
        else qout <= ram[addr];
    end
endmodule

module SdpRamRf #(
    parameter DW = 8, WORDS = 256
)(
    input wire clk,
    input wire [$clog2(WORDS) - 1 : 0] addr_a,
    input wire wr_a,
    input wire [DW - 1 : 0] din_a,
    input wire [$clog2(WORDS) - 1 : 0] addr_b,
    output logic [DW - 1 : 0] qout_b
);
    logic [DW - 1 : 0] ram[WORDS:0];
    always_ff@(posedge clk) begin
        if(wr_a) begin
            ram[addr_a] <= din_a;
        end
    end
    always_ff@(posedge clk) begin
        qout_b <= ram[addr_b];
    end
endmodule

module SdpRamRa #(
    parameter DW = 8, WORDS = 256
)(
    input wire clk,
    input wire [$clog2(WORDS) - 1 : 0] addr_a,
    input wire wr_a,
    input wire [DW - 1 : 0] din_a,
    input wire [$clog2(WORDS) - 1 : 0] addr_b,
    output logic [DW - 1 : 0] qout_b
);
    logic [DW - 1 : 0] ram[WORDS];
    always_ff@(posedge clk) begin
        if(wr_a) begin
            ram[addr_a] <= din_a;
        end
    end
    assign qout_b = ram[addr_b];
endmodule

module DpRam #(
    parameter DW = 8, WORDS = 256
)(
    input wire clk,
    input wire [$clog2(WORDS) - 1 : 0] addr_a,
    input wire wr_a,
    input wire [DW - 1 : 0] din_a,
    output logic [DW - 1 : 0] qout_a,
    input wire [$clog2(WORDS) - 1 : 0] addr_b,
    input wire wr_b,
    input wire [DW - 1 : 0] din_b,
    output logic [DW - 1 : 0] qout_b
);
    logic [DW - 1 : 0] ram[WORDS];
    always_ff@(posedge clk) begin
        if(wr_a) begin
            ram[addr_a] <= din_a;
            qout_a <= din_a;
        end
        else qout_a <= ram[addr_a];
    end
    always_ff@(posedge clk) begin
        if(wr_b) begin
            ram[addr_b] <= din_b;
            qout_b <= din_b;
        end
        else qout_b <= ram[addr_b];
    end
endmodule

module SdcRam #(
    parameter DW = 8, WORDS = 256
)(
    input wire clk_a,
    input wire [$clog2(WORDS) - 1 : 0] addr_a,
    input wire wr_a,
    input wire [DW - 1 : 0] din_a,
    input wire clk_b,
    input wire [$clog2(WORDS) - 1 : 0] addr_b,
    output logic [DW - 1 : 0] qout_b
);
    logic [DW - 1 : 0] ram[WORDS];
    always_ff@(posedge clk_a) begin
        if(wr_a) ram[addr_a] <= din_a;
    end
    always_ff@(posedge clk_b) begin
        qout_b <= ram[addr_b];
    end
endmodule

module DcRam #(
    parameter DW = 8, WORDS = 256
)(
    input wire clk_a,
    input wire [$clog2(WORDS) - 1 : 0] addr_a,
    input wire wr_a,
    input wire [DW - 1 : 0] din_a,
    output logic [DW - 1 : 0] qout_a,
    input wire clk_b,
    input wire [$clog2(WORDS) - 1 : 0] addr_b,
    input wire wr_b,
    input wire [DW - 1 : 0] din_b,
    output logic [DW - 1 : 0] qout_b
);
    logic [DW - 1 : 0] ram[WORDS];
    always_ff@(posedge clk_a) begin
        if(wr_a) ram[addr_a] <= din_a;
        qout_a <= ram[addr_a];
    end
    always_ff@(posedge clk_b) begin
        if(wr_b) ram[addr_b] <= din_b;
        qout_b <= ram[addr_b];
    end
endmodule

module SpRamRfSine #(
    parameter DW = 8, WORDS = 256
//    parameter string INIT_FILE = "sindata8b256.dat"
)(
    input wire clk,
    input wire [$clog2(WORDS) - 1 : 0] addr,
    input wire we,
    input wire signed [DW - 1 : 0] din,
    output logic signed [DW - 1 : 0] qout
);
    logic signed [DW - 1 : 0] ram[WORDS];

    localparam real PI = 3.1415926535897932;
    initial begin
        for(int i = 0; i < WORDS; i++) begin
            ram[i] = $sin(2.0 * PI * i / WORDS) * (2**(DW - 1) - 1);
        end
//        $readmemh(INIT_FILE, ram);
    end
    always@(posedge clk) begin
        if(we) ram[addr] <= din;
        qout <= ram[addr];
    end
endmodule

`default_nettype wire
`endif

memory/tb_memory.sv
`timescale 1ns/1ns
`default_nettype none
module TestMem;
    logic clk;
    initial begin
        #0
            clk=1'b0;
        forever  #5  clk=~clk;
    end
    logic [7:0] a = 0, d = 0, q;
    logic we = 0;
        initial begin
        $dumpfile("wave.vcd");
        $dumpvars(0, TestMem );
    #1000 $finish;
    end
    initial begin
        #10 {we, a, d} = {1'b1, 8'h01, 8'h10};
        #10 {we, a, d} = {1'b1, 8'h03, 8'h30};
        #10 {we, a, d} = {1'b1, 8'h06, 8'h60};
        #10 {we, a, d} = {1'b1, 8'h0a, 8'ha0};
        #10 {we, a, d} = {1'b1, 8'h0f, 8'hf0};
        #10 {we, a, d} = {1'b0, 8'h00, 8'h00};
        forever #10 a++;
    end
    SpRamRfSine theMem(clk, a, we, d, q);
endmodule

memory/wave.vcd
$date
	Sun Feb 25 13:55:59 2024
$end
$version
	Icarus Verilog
$end
$timescale
	1ns
$end
$scope module TestMem $end
$var wire 8 ! q [7:0] $end
$var reg 8 " a [7:0] $end
$var reg 1 # clk $end
$var reg 8 $ d [7:0] $end
$var reg 1 % we $end
$scope module theMem $end
$var wire 8 & addr [7:0] $end
$var wire 1 # clk $end
$var wire 8 ' din [7:0] $end
$var wire 1 % we $end
$var parameter 32 ( DW $end
$var real 1 ) PI $end
$var parameter 32 * WORDS $end
$var reg 8 + qout [7:0] $end
$scope begin $ivl_for_loop1 $end
$var integer 32 , i [31:0] $end
$upscope $end
$upscope $end
$upscope $end
$enddefinitions $end
$comment Show the parameter values. $end
$dumpall
b100000000 *
r3.141592653589793 )
b1000 (
$end
#0
$dumpvars
b100000000 ,
bx +
b0 '
b0 &
0%
b0 $
0#
b0 "
bx !
$end
#5
b0 !
b0 +
1#
#10
0#
1%
b1 "
b1 &
b10000 $
b10000 '
#15
b11 !
b11 +
1#
#20
0#
b11 "
b11 &
b110000 $
b110000 '
#25
b1001 !
b1001 +
1#
#30
0#
b110 "
b110 &
b1100000 $
b1100000 '
#35
b10011 !
b10011 +
1#
#40
0#
b1010 "
b1010 &
b10100000 $
b10100000 '
#45
b11111 !
b11111 +
1#
#50
0#
b1111 "
b1111 &
b11110000 $
b11110000 '
#55
b101110 !
b101110 +
1#
#60
0#
0%
b0 "
b0 &
b0 $
b0 '
#65
b0 !
b0 +
1#
#70
0#
b1 "
b1 &
#75
b10000 !
b10000 +
1#
#80
0#
b10 "
b10 &
#85
b110 !
b110 +
1#
#90
0#
b11 "
b11 &
#95
b110000 !
b110000 +
1#
#100
0#
b100 "
b100 &
#105
b1100 !
b1100 +
1#
#110
0#
b101 "
b101 &
#115
b10000 !
b10000 +
1#
#120
0#
b110 "
b110 &
#125
b1100000 !
b1100000 +
1#
#130
0#
b111 "
b111 &
#135
b10110 !
b10110 +
1#
#140
0#
b1000 "
b1000 &
#145
b11001 !
b11001 +
1#
#150
0#
b1001 "
b1001 &
#155
b11100 !
b11100 +
1#
#160
0#
b1010 "
b1010 &
#165
b10100000 !
b10100000 +
1#
#170
0#
b1011 "
b1011 &
#175
b100010 !
b100010 +
1#
#180
0#
b1100 "
b1100 &
#185
b100101 !
b100101 +
1#
#190
0#
b1101 "
b1101 &
#195
b101000 !
b101000 +
1#
#200
0#
b1110 "
b1110 &
#205
b101011 !
b101011 +
1#
#210
0#
b1111 "
b1111 &
#215
b11110000 !
b11110000 +
1#
#220
0#
b10000 "
b10000 &
#225
b110001 !
b110001 +
1#
#230
0#
b10001 "
b10001 &
#235
b110011 !
b110011 +
1#
#240
0#
b10010 "
b10010 &
#245
b110110 !
b110110 +
1#
#250
0#
b10011 "
b10011 &
#255
b111001 !
b111001 +
1#
#260
0#
b10100 "
b10100 &
#265
b111100 !
b111100 +
1#
#270
0#
b10101 "
b10101 &
#275
b111111 !
b111111 +
1#
#280
0#
b10110 "
b10110 &
#285
b1000001 !
b1000001 +
1#
#290
0#
b10111 "
b10111 &
#295
b1000100 !
b1000100 +
1#
#300
0#
b11000 "
b11000 &
#305
b1000111 !
b1000111 +
1#
#310
0#
b11001 "
b11001 &
#315
b1001001 !
b1001001 +
1#
#320
0#
b11010 "
b11010 &
#325
b1001100 !
b1001100 +
1#
#330
0#
b11011 "
b11011 &
#335
b1001110 !
b1001110 +
1#
#340
0#
b11100 "
b11100 &
#345
b1010001 !
b1010001 +
1#
#350
0#
b11101 "
b11101 &
#355
b1010011 !
b1010011 +
1#
#360
0#
b11110 "
b11110 &
#365
b1010101 !
b1010101 +
1#
#370
0#
b11111 "
b11111 &
#375
b1011000 !
b1011000 +
1#
#380
0#
b100000 "
b100000 &
#385
b1011010 !
b1011010 +
1#
#390
0#
b100001 "
b100001 &
#395
b1011100 !
b1011100 +
1#
#400
0#
b100010 "
b100010 &
#405
b1011110 !
b1011110 +
1#
#410
0#
b100011 "
b100011 &
#415
b1100000 !
b1100000 +
1#
#420
0#
b100100 "
b100100 &
#425
b1100010 !
b1100010 +
1#
#430
0#
b100101 "
b100101 &
#435
b1100100 !
b1100100 +
1#
#440
0#
b100110 "
b100110 &
#445
b1100110 !
b1100110 +
1#
#450
0#
b100111 "
b100111 &
#455
b1101000 !
b1101000 +
1#
#460
0#
b101000 "
b101000 &
#465
b1101010 !
b1101010 +
1#
#470
0#
b101001 "
b101001 &
#475
b1101011 !
b1101011 +
1#
#480
0#
b101010 "
b101010 &
#485
b1101101 !
b1101101 +
1#
#490
0#
b101011 "
b101011 &
#495
b1101111 !
b1101111 +
1#
#500
0#
b101100 "
b101100 &
#505
b1110000 !
b1110000 +
1#
#510
0#
b101101 "
b101101 &
#515
b1110001 !
b1110001 +
1#
#520
0#
b101110 "
b101110 &
#525
b1110011 !
b1110011 +
1#
#530
0#
b101111 "
b101111 &
#535
b1110100 !
b1110100 +
1#
#540
0#
b110000 "
b110000 &
#545
b1110101 !
b1110101 +
1#
#550
0#
b110001 "
b110001 &
#555
b1110110 !
b1110110 +
1#
#560
0#
b110010 "
b110010 &
#565
b1111000 !
b1111000 +
1#
#570
0#
b110011 "
b110011 &
#575
b1111001 !
b1111001 +
1#
#580
0#
b110100 "
b110100 &
#585
b1111010 !
b1111010 +
1#
#590
0#
b110101 "
b110101 &
#595
1#
#600
0#
b110110 "
b110110 &
#605
b1111011 !
b1111011 +
1#
#610
0#
b110111 "
b110111 &
#615
b1111100 !
b1111100 +
1#
#620
0#
b111000 "
b111000 &
#625
b1111101 !
b1111101 +
1#
#630
0#
b111001 "
b111001 &
#635
1#
#640
0#
b111010 "
b111010 &
#645
b1111110 !
b1111110 +
1#
#650
0#
b111011 "
b111011 &
#655
1#
#660
0#
b111100 "
b111100 &
#665
1#
#670
0#
b111101 "
b111101 &
#675
b1111111 !
b1111111 +
1#
#680
0#
b111110 "
b111110 &
#685
1#
#690
0#
b111111 "
b111111 &
#695
1#
#700
0#
b1000000 "
b1000000 &
#705
1#
#710
0#
b1000001 "
b1000001 &
#715
1#
#720
0#
b1000010 "
b1000010 &
#725
1#
#730
0#
b1000011 "
b1000011 &
#735
1#
#740
0#
b1000100 "
b1000100 &
#745
b1111110 !
b1111110 +
1#
#750
0#
b1000101 "
b1000101 &
#755
1#
#760
0#
b1000110 "
b1000110 &
#765
1#
#770
0#
b1000111 "
b1000111 &
#775
b1111101 !
b1111101 +
1#
#780
0#
b1001000 "
b1001000 &
#785
1#
#790
0#
b1001001 "
b1001001 &
#795
b1111100 !
b1111100 +
1#
#800
0#
b1001010 "
b1001010 &
#805
b1111011 !
b1111011 +
1#
#810
0#
b1001011 "
b1001011 &
#815
b1111010 !
b1111010 +
1#
#820
0#
b1001100 "
b1001100 &
#825
1#
#830
0#
b1001101 "
b1001101 &
#835
b1111001 !
b1111001 +
1#
#840
0#
b1001110 "
b1001110 &
#845
b1111000 !
b1111000 +
1#
#850
0#
b1001111 "
b1001111 &
#855
b1110110 !
b1110110 +
1#
#860
0#
b1010000 "
b1010000 &
#865
b1110101 !
b1110101 +
1#
#870
0#
b1010001 "
b1010001 &
#875
b1110100 !
b1110100 +
1#
#880
0#
b1010010 "
b1010010 &
#885
b1110011 !
b1110011 +
1#
#890
0#
b1010011 "
b1010011 &
#895
b1110001 !
b1110001 +
1#
#900
0#
b1010100 "
b1010100 &
#905
b1110000 !
b1110000 +
1#
#910
0#
b1010101 "
b1010101 &
#915
b1101111 !
b1101111 +
1#
#920
0#
b1010110 "
b1010110 &
#925
b1101101 !
b1101101 +
1#
#930
0#
b1010111 "
b1010111 &
#935
b1101011 !
b1101011 +
1#
#940
0#
b1011000 "
b1011000 &
#945
b1101010 !
b1101010 +
1#
#950
0#
b1011001 "
b1011001 &
#955
b1101000 !
b1101000 +
1#
#960
0#
b1011010 "
b1011010 &
#965
b1100110 !
b1100110 +
1#
#970
0#
b1011011 "
b1011011 &
#975
b1100100 !
b1100100 +
1#
#980
0#
b1011100 "
b1011100 &
#985
b1100010 !
b1100010 +
1#
#990
0#
b1011101 "
b1011101 &
#995
b1100000 !
b1100000 +
1#
#1000
0#
b1011110 "
b1011110 &
