mux/mux.sv
`default_nettype none
module Mux #(
	parameter DW = 8,
	parameter CH = 4
)(
	input wire [DW - 1 : 0] in[CH-1:0],
	input wire [$clog2(CH) - 1 : 0] sel,
	output logic [DW - 1 : 0] out
);
	assign out = in[sel];
endmodule

mux/tb_mux.sv
`timescale 1ps/1ps

module TestMux;
    //The original syntax is logic [7:0] a[4] = '{4{'0}};, which is not supported by iverilog.
    //So I wrote this initialization command in for form.
    logic [7:0] a[3:0];
    initial begin
        for(integer i = 0; i <4; i = i + 1) begin
            a[i] <= 0;
        end
    end
    logic [7:0] y;
	logic [1:0] sel = '0;
	always #10 a[0]++;
	always #20 a[1]++;
	always #40 a[2]++;
	always #80 a[3]++;
	always #160 sel++;
	Mux #(8, 4) theMux(a, sel, y);
    initial begin
        $dumpfile("wave.vcd");
        $dumpvars(0, TestMux);
    #10000 $finish;
    end
endmodule

mux/wave.vcd
$date
	Sun Feb 25 14:01:54 2024
$end
$version
	Icarus Verilog
$end
$timescale
	1ps
$end
$scope module TestMux $end
$var wire 8 ! y [7:0] $end
$var reg 2 " sel [1:0] $end
$scope module theMux $end
$var wire 8 # out [7:0] $end
$var wire 2 $ sel [1:0] $end
$var parameter 32 % CH $end
$var parameter 32 & DW $end
$upscope $end
$scope begin $ivl_for_loop0 $end
$var integer 32 ' i [31:0] $end
$upscope $end
$upscope $end
$enddefinitions $end
$comment Show the parameter values. $end
$dumpall
b1000 &
b100 %
$end
#0
$dumpvars
b100 '
b0 $
b0 #
b0 "
b0 !
$end
#10
b1 !
b1 #
#20
b10 !
b10 #
#30
b11 !
b11 #
#40
b100 !
b100 #
#50
b101 !
b101 #
#60
b110 !
b110 #
#70
b111 !
b111 #
#80
b1000 !
b1000 #
#90
b1001 !
b1001 #
#100
b1010 !
b1010 #
#110
b1011 !
b1011 #
#120
b1100 !
b1100 #
#130
b1101 !
b1101 #
#140
b1110 !
b1110 #
#150
b1111 !
b1111 #
#160
b1000 !
b1000 #
b1 "
b1 $
#180
b1001 !
b1001 #
#200
b1010 !
b1010 #
#220
b1011 !
b1011 #
#240
b1100 !
b1100 #
#260
b1101 !
b1101 #
#280
b1110 !
b1110 #
#300
b1111 !
b1111 #
#320
b1000 !
b1000 #
b10 "
b10 $
#360
b1001 !
b1001 #
#400
b1010 !
b1010 #
#440
b1011 !
b1011 #
#480
b110 !
b110 #
b11 "
b11 $
#560
b111 !
b111 #
#640
b1000000 !
b1000000 #
b0 "
b0 $
#650
b1000001 !
b1000001 #
#660
b1000010 !
b1000010 #
#670
b1000011 !
b1000011 #
#680
b1000100 !
b1000100 #
#690
b1000101 !
b1000101 #
#700
b1000110 !
b1000110 #
#710
b1000111 !
b1000111 #
#720
b1001000 !
b1001000 #
#730
b1001001 !
b1001001 #
#740
b1001010 !
b1001010 #
#750
b1001011 !
b1001011 #
#760
b1001100 !
b1001100 #
#770
b1001101 !
b1001101 #
#780
b1001110 !
b1001110 #
#790
b1001111 !
b1001111 #
#800
b101000 !
b101000 #
b1 "
b1 $
#820
b101001 !
b101001 #
#840
b101010 !
b101010 #
#860
b101011 !
b101011 #
#880
b101100 !
b101100 #
#900
b101101 !
b101101 #
#920
b101110 !
b101110 #
#940
b101111 !
b101111 #
#960
b11000 !
b11000 #
b10 "
b10 $
#1000
b11001 !
b11001 #
#1040
b11010 !
b11010 #
#1080
b11011 !
b11011 #
#1120
b1110 !
b1110 #
b11 "
b11 $
#1200
b1111 !
b1111 #
#1280
b10000000 !
b10000000 #
b0 "
b0 $
#1290
b10000001 !
b10000001 #
#1300
b10000010 !
b10000010 #
#1310
b10000011 !
b10000011 #
#1320
b10000100 !
b10000100 #
#1330
b10000101 !
b10000101 #
#1340
b10000110 !
b10000110 #
#1350
b10000111 !
b10000111 #
#1360
b10001000 !
b10001000 #
#1370
b10001001 !
b10001001 #
#1380
b10001010 !
b10001010 #
#1390
b10001011 !
b10001011 #
#1400
b10001100 !
b10001100 #
#1410
b10001101 !
b10001101 #
#1420
b10001110 !
b10001110 #
#1430
b10001111 !
b10001111 #
#1440
b1001000 !
b1001000 #
b1 "
b1 $
#1460
b1001001 !
b1001001 #
#1480
b1001010 !
b1001010 #
#1500
b1001011 !
b1001011 #
#1520
b1001100 !
b1001100 #
#1540
b1001101 !
b1001101 #
#1560
b1001110 !
b1001110 #
#1580
b1001111 !
b1001111 #
#1600
b101000 !
b101000 #
b10 "
b10 $
#1640
b101001 !
b101001 #
#1680
b101010 !
b101010 #
#1720
b101011 !
b101011 #
#1760
b10110 !
b10110 #
b11 "
b11 $
#1840
b10111 !
b10111 #
#1920
b11000000 !
b11000000 #
b0 "
b0 $
#1930
b11000001 !
b11000001 #
#1940
b11000010 !
b11000010 #
#1950
b11000011 !
b11000011 #
#1960
b11000100 !
b11000100 #
#1970
b11000101 !
b11000101 #
#1980
b11000110 !
b11000110 #
#1990
b11000111 !
b11000111 #
#2000
b11001000 !
b11001000 #
#2010
b11001001 !
b11001001 #
#2020
b11001010 !
b11001010 #
#2030
b11001011 !
b11001011 #
#2040
b11001100 !
b11001100 #
#2050
b11001101 !
b11001101 #
#2060
b11001110 !
b11001110 #
#2070
b11001111 !
b11001111 #
#2080
b1101000 !
b1101000 #
b1 "
b1 $
#2100
b1101001 !
b1101001 #
#2120
b1101010 !
b1101010 #
#2140
b1101011 !
b1101011 #
#2160
b1101100 !
b1101100 #
#2180
b1101101 !
b1101101 #
#2200
b1101110 !
b1101110 #
#2220
b1101111 !
b1101111 #
#2240
b111000 !
b111000 #
b10 "
b10 $
#2280
b111001 !
b111001 #
#2320
b111010 !
b111010 #
#2360
b111011 !
b111011 #
#2400
b11110 !
b11110 #
b11 "
b11 $
#2480
b11111 !
b11111 #
#2560
b0 !
b0 #
b0 "
b0 $
#2570
b1 !
b1 #
#2580
b10 !
b10 #
#2590
b11 !
b11 #
#2600
b100 !
b100 #
#2610
b101 !
b101 #
#2620
b110 !
b110 #
#2630
b111 !
b111 #
#2640
b1000 !
b1000 #
#2650
b1001 !
b1001 #
#2660
b1010 !
b1010 #
#2670
b1011 !
b1011 #
#2680
b1100 !
b1100 #
#2690
b1101 !
b1101 #
#2700
b1110 !
b1110 #
#2710
b1111 !
b1111 #
#2720
b10001000 !
b10001000 #
b1 "
b1 $
#2740
b10001001 !
b10001001 #
#2760
b10001010 !
b10001010 #
#2780
b10001011 !
b10001011 #
#2800
b10001100 !
b10001100 #
#2820
b10001101 !
b10001101 #
#2840
b10001110 !
b10001110 #
#2860
b10001111 !
b10001111 #
#2880
b1001000 !
b1001000 #
b10 "
b10 $
#2920
b1001001 !
b1001001 #
#2960
b1001010 !
b1001010 #
#3000
b1001011 !
b1001011 #
#3040
b100110 !
b100110 #
b11 "
b11 $
#3120
b100111 !
b100111 #
#3200
b1000000 !
b1000000 #
b0 "
b0 $
#3210
b1000001 !
b1000001 #
#3220
b1000010 !
b1000010 #
#3230
b1000011 !
b1000011 #
#3240
b1000100 !
b1000100 #
#3250
b1000101 !
b1000101 #
#3260
b1000110 !
b1000110 #
#3270
b1000111 !
b1000111 #
#3280
b1001000 !
b1001000 #
#3290
b1001001 !
b1001001 #
#3300
b1001010 !
b1001010 #
#3310
b1001011 !
b1001011 #
#3320
b1001100 !
b1001100 #
#3330
b1001101 !
b1001101 #
#3340
b1001110 !
b1001110 #
#3350
b1001111 !
b1001111 #
#3360
b10101000 !
b10101000 #
b1 "
b1 $
#3380
b10101001 !
b10101001 #
#3400
b10101010 !
b10101010 #
#3420
b10101011 !
b10101011 #
#3440
b10101100 !
b10101100 #
#3460
b10101101 !
b10101101 #
#3480
b10101110 !
b10101110 #
#3500
b10101111 !
b10101111 #
#3520
b1011000 !
b1011000 #
b10 "
b10 $
#3560
b1011001 !
b1011001 #
#3600
b1011010 !
b1011010 #
#3640
b1011011 !
b1011011 #
#3680
b101110 !
b101110 #
b11 "
b11 $
#3760
b101111 !
b101111 #
#3840
b10000000 !
b10000000 #
b0 "
b0 $
#3850
b10000001 !
b10000001 #
#3860
b10000010 !
b10000010 #
#3870
b10000011 !
b10000011 #
#3880
b10000100 !
b10000100 #
#3890
b10000101 !
b10000101 #
#3900
b10000110 !
b10000110 #
#3910
b10000111 !
b10000111 #
#3920
b10001000 !
b10001000 #
#3930
b10001001 !
b10001001 #
#3940
b10001010 !
b10001010 #
#3950
b10001011 !
b10001011 #
#3960
b10001100 !
b10001100 #
#3970
b10001101 !
b10001101 #
#3980
b10001110 !
b10001110 #
#3990
b10001111 !
b10001111 #
#4000
b11001000 !
b11001000 #
b1 "
b1 $
#4020
b11001001 !
b11001001 #
#4040
b11001010 !
b11001010 #
#4060
b11001011 !
b11001011 #
#4080
b11001100 !
b11001100 #
#4100
b11001101 !
b11001101 #
#4120
b11001110 !
b11001110 #
#4140
b11001111 !
b11001111 #
#4160
b1101000 !
b1101000 #
b10 "
b10 $
#4200
b1101001 !
b1101001 #
#4240
b1101010 !
b1101010 #
#4280
b1101011 !
b1101011 #
#4320
b110110 !
b110110 #
b11 "
b11 $
#4400
b110111 !
b110111 #
#4480
b11000000 !
b11000000 #
b0 "
b0 $
#4490
b11000001 !
b11000001 #
#4500
b11000010 !
b11000010 #
#4510
b11000011 !
b11000011 #
#4520
b11000100 !
b11000100 #
#4530
b11000101 !
b11000101 #
#4540
b11000110 !
b11000110 #
#4550
b11000111 !
b11000111 #
#4560
b11001000 !
b11001000 #
#4570
b11001001 !
b11001001 #
#4580
b11001010 !
b11001010 #
#4590
b11001011 !
b11001011 #
#4600
b11001100 !
b11001100 #
#4610
b11001101 !
b11001101 #
#4620
b11001110 !
b11001110 #
#4630
b11001111 !
b11001111 #
#4640
b11101000 !
b11101000 #
b1 "
b1 $
#4660
b11101001 !
b11101001 #
#4680
b11101010 !
b11101010 #
#4700
b11101011 !
b11101011 #
#4720
b11101100 !
b11101100 #
#4740
b11101101 !
b11101101 #
#4760
b11101110 !
b11101110 #
#4780
b11101111 !
b11101111 #
#4800
b1111000 !
b1111000 #
b10 "
b10 $
#4840
b1111001 !
b1111001 #
#4880
b1111010 !
b1111010 #
#4920
b1111011 !
b1111011 #
#4960
b111110 !
b111110 #
b11 "
b11 $
#5040
b111111 !
b111111 #
#5120
b0 !
b0 #
b0 "
b0 $
#5130
b1 !
b1 #
#5140
b10 !
b10 #
#5150
b11 !
b11 #
#5160
b100 !
b100 #
#5170
b101 !
b101 #
#5180
b110 !
b110 #
#5190
b111 !
b111 #
#5200
b1000 !
b1000 #
#5210
b1001 !
b1001 #
#5220
b1010 !
b1010 #
#5230
b1011 !
b1011 #
#5240
b1100 !
b1100 #
#5250
b1101 !
b1101 #
#5260
b1110 !
b1110 #
#5270
b1111 !
b1111 #
#5280
b1000 !
b1000 #
b1 "
b1 $
#5300
b1001 !
b1001 #
#5320
b1010 !
b1010 #
#5340
b1011 !
b1011 #
#5360
b1100 !
b1100 #
#5380
b1101 !
b1101 #
#5400
b1110 !
b1110 #
#5420
b1111 !
b1111 #
#5440
b10001000 !
b10001000 #
b10 "
b10 $
#5480
b10001001 !
b10001001 #
#5520
b10001010 !
b10001010 #
#5560
b10001011 !
b10001011 #
#5600
b1000110 !
b1000110 #
b11 "
b11 $
#5680
b1000111 !
b1000111 #
#5760
b1000000 !
b1000000 #
b0 "
b0 $
#5770
b1000001 !
b1000001 #
#5780
b1000010 !
b1000010 #
#5790
b1000011 !
b1000011 #
#5800
b1000100 !
b1000100 #
#5810
b1000101 !
b1000101 #
#5820
b1000110 !
b1000110 #
#5830
b1000111 !
b1000111 #
#5840
b1001000 !
b1001000 #
#5850
b1001001 !
b1001001 #
#5860
b1001010 !
b1001010 #
#5870
b1001011 !
b1001011 #
#5880
b1001100 !
b1001100 #
#5890
b1001101 !
b1001101 #
#5900
b1001110 !
b1001110 #
#5910
b1001111 !
b1001111 #
#5920
b101000 !
b101000 #
b1 "
b1 $
#5940
b101001 !
b101001 #
#5960
b101010 !
b101010 #
#5980
b101011 !
b101011 #
#6000
b101100 !
b101100 #
#6020
b101101 !
b101101 #
#6040
b101110 !
b101110 #
#6060
b101111 !
b101111 #
#6080
b10011000 !
b10011000 #
b10 "
b10 $
#6120
b10011001 !
b10011001 #
#6160
b10011010 !
b10011010 #
#6200
b10011011 !
b10011011 #
#6240
b1001110 !
b1001110 #
b11 "
b11 $
#6320
b1001111 !
b1001111 #
#6400
b10000000 !
b10000000 #
b0 "
b0 $
#6410
b10000001 !
b10000001 #
#6420
b10000010 !
b10000010 #
#6430
b10000011 !
b10000011 #
#6440
b10000100 !
b10000100 #
#6450
b10000101 !
b10000101 #
#6460
b10000110 !
b10000110 #
#6470
b10000111 !
b10000111 #
#6480
b10001000 !
b10001000 #
#6490
b10001001 !
b10001001 #
#6500
b10001010 !
b10001010 #
#6510
b10001011 !
b10001011 #
#6520
b10001100 !
b10001100 #
#6530
b10001101 !
b10001101 #
#6540
b10001110 !
b10001110 #
#6550
b10001111 !
b10001111 #
#6560
b1001000 !
b1001000 #
b1 "
b1 $
#6580
b1001001 !
b1001001 #
#6600
b1001010 !
b1001010 #
#6620
b1001011 !
b1001011 #
#6640
b1001100 !
b1001100 #
#6660
b1001101 !
b1001101 #
#6680
b1001110 !
b1001110 #
#6700
b1001111 !
b1001111 #
#6720
b10101000 !
b10101000 #
b10 "
b10 $
#6760
b10101001 !
b10101001 #
#6800
b10101010 !
b10101010 #
#6840
b10101011 !
b10101011 #
#6880
b1010110 !
b1010110 #
b11 "
b11 $
#6960
b1010111 !
b1010111 #
#7040
b11000000 !
b11000000 #
b0 "
b0 $
#7050
b11000001 !
b11000001 #
#7060
b11000010 !
b11000010 #
#7070
b11000011 !
b11000011 #
#7080
b11000100 !
b11000100 #
#7090
b11000101 !
b11000101 #
#7100
b11000110 !
b11000110 #
#7110
b11000111 !
b11000111 #
#7120
b11001000 !
b11001000 #
#7130
b11001001 !
b11001001 #
#7140
b11001010 !
b11001010 #
#7150
b11001011 !
b11001011 #
#7160
b11001100 !
b11001100 #
#7170
b11001101 !
b11001101 #
#7180
b11001110 !
b11001110 #
#7190
b11001111 !
b11001111 #
#7200
b1101000 !
b1101000 #
b1 "
b1 $
#7220
b1101001 !
b1101001 #
#7240
b1101010 !
b1101010 #
#7260
b1101011 !
b1101011 #
#7280
b1101100 !
b1101100 #
#7300
b1101101 !
b1101101 #
#7320
b1101110 !
b1101110 #
#7340
b1101111 !
b1101111 #
#7360
b10111000 !
b10111000 #
b10 "
b10 $
#7400
b10111001 !
b10111001 #
#7440
b10111010 !
b10111010 #
#7480
b10111011 !
b10111011 #
#7520
b1011110 !
b1011110 #
b11 "
b11 $
#7600
b1011111 !
b1011111 #
#7680
b0 !
b0 #
b0 "
b0 $
#7690
b1 !
b1 #
#7700
b10 !
b10 #
#7710
b11 !
b11 #
#7720
b100 !
b100 #
#7730
b101 !
b101 #
#7740
b110 !
b110 #
#7750
b111 !
b111 #
#7760
b1000 !
b1000 #
#7770
b1001 !
b1001 #
#7780
b1010 !
b1010 #
#7790
b1011 !
b1011 #
#7800
b1100 !
b1100 #
#7810
b1101 !
b1101 #
#7820
b1110 !
b1110 #
#7830
b1111 !
b1111 #
#7840
b10001000 !
b10001000 #
b1 "
b1 $
#7860
b10001001 !
b10001001 #
#7880
b10001010 !
b10001010 #
#7900
b10001011 !
b10001011 #
#7920
b10001100 !
b10001100 #
#7940
b10001101 !
b10001101 #
#7960
b10001110 !
b10001110 #
#7980
b10001111 !
b10001111 #
#8000
b11001000 !
b11001000 #
b10 "
b10 $
#8040
b11001001 !
b11001001 #
#8080
b11001010 !
b11001010 #
#8120
b11001011 !
b11001011 #
#8160
b1100110 !
b1100110 #
b11 "
b11 $
#8240
b1100111 !
b1100111 #
#8320
b1000000 !
b1000000 #
b0 "
b0 $
#8330
b1000001 !
b1000001 #
#8340
b1000010 !
b1000010 #
#8350
b1000011 !
b1000011 #
#8360
b1000100 !
b1000100 #
#8370
b1000101 !
b1000101 #
#8380
b1000110 !
b1000110 #
#8390
b1000111 !
b1000111 #
#8400
b1001000 !
b1001000 #
#8410
b1001001 !
b1001001 #
#8420
b1001010 !
b1001010 #
#8430
b1001011 !
b1001011 #
#8440
b1001100 !
b1001100 #
#8450
b1001101 !
b1001101 #
#8460
b1001110 !
b1001110 #
#8470
b1001111 !
b1001111 #
#8480
b10101000 !
b10101000 #
b1 "
b1 $
#8500
b10101001 !
b10101001 #
#8520
b10101010 !
b10101010 #
#8540
b10101011 !
b10101011 #
#8560
b10101100 !
b10101100 #
#8580
b10101101 !
b10101101 #
#8600
b10101110 !
b10101110 #
#8620
b10101111 !
b10101111 #
#8640
b11011000 !
b11011000 #
b10 "
b10 $
#8680
b11011001 !
b11011001 #
#8720
b11011010 !
b11011010 #
#8760
b11011011 !
b11011011 #
#8800
b1101110 !
b1101110 #
b11 "
b11 $
#8880
b1101111 !
b1101111 #
#8960
b10000000 !
b10000000 #
b0 "
b0 $
#8970
b10000001 !
b10000001 #
#8980
b10000010 !
b10000010 #
#8990
b10000011 !
b10000011 #
#9000
b10000100 !
b10000100 #
#9010
b10000101 !
b10000101 #
#9020
b10000110 !
b10000110 #
#9030
b10000111 !
b10000111 #
#9040
b10001000 !
b10001000 #
#9050
b10001001 !
b10001001 #
#9060
b10001010 !
b10001010 #
#9070
b10001011 !
b10001011 #
#9080
b10001100 !
b10001100 #
#9090
b10001101 !
b10001101 #
#9100
b10001110 !
b10001110 #
#9110
b10001111 !
b10001111 #
#9120
b11001000 !
b11001000 #
b1 "
b1 $
#9140
b11001001 !
b11001001 #
#9160
b11001010 !
b11001010 #
#9180
b11001011 !
b11001011 #
#9200
b11001100 !
b11001100 #
#9220
b11001101 !
b11001101 #
#9240
b11001110 !
b11001110 #
#9260
b11001111 !
b11001111 #
#9280
b11101000 !
b11101000 #
b10 "
b10 $
#9320
b11101001 !
b11101001 #
#9360
b11101010 !
b11101010 #
#9400
b11101011 !
b11101011 #
#9440
b1110110 !
b1110110 #
b11 "
b11 $
#9520
b1110111 !
b1110111 #
#9600
b11000000 !
b11000000 #
b0 "
b0 $
#9610
b11000001 !
b11000001 #
#9620
b11000010 !
b11000010 #
#9630
b11000011 !
b11000011 #
#9640
b11000100 !
b11000100 #
#9650
b11000101 !
b11000101 #
#9660
b11000110 !
b11000110 #
#9670
b11000111 !
b11000111 #
#9680
b11001000 !
b11001000 #
#9690
b11001001 !
b11001001 #
#9700
b11001010 !
b11001010 #
#9710
b11001011 !
b11001011 #
#9720
b11001100 !
b11001100 #
#9730
b11001101 !
b11001101 #
#9740
b11001110 !
b11001110 #
#9750
b11001111 !
b11001111 #
#9760
b11101000 !
b11101000 #
b1 "
b1 $
#9780
b11101001 !
b11101001 #
#9800
b11101010 !
b11101010 #
#9820
b11101011 !
b11101011 #
#9840
b11101100 !
b11101100 #
#9860
b11101101 !
b11101101 #
#9880
b11101110 !
b11101110 #
#9900
b11101111 !
b11101111 #
#9920
b11111000 !
b11111000 #
b10 "
b10 $
#9960
b11111001 !
b11111001 #
#10000
b11111010 !
b11111010 #
