dds/dds.sv
`ifndef __DDS_SV__
`define __DDS_SV__
module DDS #(
    parameter PW = 32, DW = 10, AW = 13
)(
    input wire clk, rst, en,
    input wire signed [PW - 1 : 0] freq, phase,
    output logic signed [DW - 1 : 0] out
);
    localparam LEN = 2**AW;
    localparam real PI = 3.1415926535897932;
    logic signed [DW-1 : 0] sine[LEN];
    initial begin
        for(int i = 0; i < LEN; i++) begin
            sine[i] = $sin(2.0 * PI * i / LEN) * (2.0**(DW-1) - 1.0);
        end
    end
    logic [PW-1 : 0] phaseAcc;
    always_ff@(posedge clk) begin
        if(rst) phaseAcc <= '0;
        else if(en) phaseAcc <= phaseAcc + freq;
    end
    wire [PW-1 : 0] phaseSum = phaseAcc + phase;
    always_ff@(posedge clk) begin
        if(rst) out <= '0;
        else if(en) out <= sine[phaseSum[PW-1 -: AW]];
    end
endmodule

module OrthDDS #(
    parameter PW = 32, DW = 10, AW = 13
)(
    input wire clk, rst, en,
    input wire signed [PW - 1 : 0] freq, phase,
    output logic signed [DW - 1 : 0] sin, cos
);
    localparam LEN = 2**AW;
    localparam real PI = 3.1415926535897932;
    logic signed [DW-1 : 0] sine[LEN];
    initial begin
        for(int i = 0; i < LEN; i++) begin
            sine[i] = $sin(2.0 * PI * i / LEN) * (2.0**(DW-1) - 1.0);
        end
    end
    logic [PW-1 : 0] phaseAcc, phSum0, phSum1;
    always_ff@(posedge clk) begin
        if(rst) phaseAcc <= '0;
        else if(en) phaseAcc <= phaseAcc + freq;
    end
    always_ff@(posedge clk) begin
        if(rst) begin
            phSum0 <= '0;
            phSum1 <= PW'(1) <<< (PW-2); // 90deg
        end
        else if(en) begin
            phSum0 <= phaseAcc + phase;
            phSum1 <= phaseAcc + phase + (PW'(1) <<< (PW-2));
        end
    end
    always_ff@(posedge clk) begin
        if(rst) sin <= '0;
        else if(en) sin <= sine[phSum0[PW-1 -: AW]];
    end
    always_ff@(posedge clk) begin
        if(rst) cos <= '0;
        else if(en) cos <= sine[phSum1[PW-1 -: AW]];
    end
endmodule

`endif

dds/tb_dds.sv
`timescale 1ns/1ns
`default_nettype none
module TestDDS;
    logic clk, rst;
    initial begin
        #0
            clk=1'b0;
        forever  #50  clk=~clk;
    end
    initial begin
        rst = 1;
        #60 rst =0;
    end
    initial begin
        $dumpfile("wave.vcd");
        $dumpvars(0, TestDDS );
    #1000000 $finish;
    end
    real freqr = 1e6, fstepr = 49e6/(1e-3*100e6); // from 1MHz to 50MHz in 1ms
    always@(posedge clk) begin
        if(rst) freqr = 1e6;
        else freqr += fstepr;
    end
    logic signed [31:0] freq;
    always@(posedge clk) begin
        freq <= 2.0**32 * freqr / 100e6; // frequency to freq control word
    end
    logic signed [31:0] phase = '0;
    logic signed [9:0] swave;
    DDS #(32, 10, 13) theDDS(clk, rst, 1'b1, freq, phase, swave);
endmodule

dds/wave.vcd
$date
	Wed Mar 27 10:16:46 2024
$end
$version
	Icarus Verilog
$end
$timescale
	1ns
$end
$scope module TestDDS $end
$var wire 10 ! swave [9:0] $end
$var reg 1 " clk $end
$var reg 32 # freq [31:0] $end
$var reg 32 $ phase [31:0] $end
$var reg 1 % rst $end
$var real 1 & freqr $end
$var real 1 ' fstepr $end
$scope module theDDS $end
$var wire 1 " clk $end
$var wire 1 ( en $end
$var wire 32 ) freq [31:0] $end
$var wire 32 * phase [31:0] $end
$var wire 1 % rst $end
$var wire 32 + phaseSum [31:0] $end
$var parameter 32 , AW $end
$var parameter 32 - DW $end
$var parameter 32 . LEN $end
$var real 1 / PI $end
$var parameter 32 0 PW $end
$var reg 10 1 out [9:0] $end
$var reg 32 2 phaseAcc [31:0] $end
$scope begin $ivl_for_loop0 $end
$var integer 32 3 i [31:0] $end
$upscope $end
$upscope $end
$upscope $end
$enddefinitions $end
$comment Show the parameter values. $end
$dumpall
b100000 0
r3.141592653589793 /
b10000000000000 .
b1010 -
b1101 ,
$end
#0
$dumpvars
b10000000000000 3
bx 2
bx 1
bx +
b0 *
bx )
1(
r490 '
r1000000 &
1%
b0 $
bx #
0"
bx !
$end
#50
b0 +
b0 2
b0 !
b0 1
b10100011110101110000101001 #
b10100011110101110000101001 )
1"
#60
0%
#100
0"
#150
b10100011111010111001011110 #
b10100011111010111001011110 )
b10100011110101110000101001 +
b10100011110101110000101001 2
r1000490 &
1"
#200
0"
#250
b101000111110000101010000111 +
b101000111110000101010000111 2
b100000 !
b100000 1
r1000980 &
1"
#300
0"
#350
b10100100000101001011001001 #
b10100100000101001011001001 )
b1000000 !
b1000000 1
b111101011101011100011100101 +
b111101011101011100011100101 2
r1001470 &
1"
#400
0"
#450
b1010001111110000101110101110 +
b1010001111110000101110101110 2
b1011111 !
b1011111 1
r1001960 &
1"
#500
0"
#550
b10100100001111011100110100 #
b10100100001111011100110100 )
b1111111 !
b1111111 1
b1100110011110101111001110111 +
b1100110011110101111001110111 2
r1002450 &
1"
#600
0"
#650
b1111011000000101010110101011 +
b1111011000000101010110101011 2
b10011110 !
b10011110 1
r1002940 &
1"
#700
0"
#750
b10100100011001101110011110 #
b10100100011001101110011110 )
b10111100 !
b10111100 1
b10001111100010100110011011111 +
b10001111100010100110011011111 2
r1003430 &
1"
#800
0"
#850
b10100100000101110100001111101 +
b10100100000101110100001111101 2
b11011010 !
b11011010 1
r1003920 &
1"
#900
0"
#950
b10100100100100000000001001 #
b10100100100100000000001001 )
b11110110 !
b11110110 1
b10111000101001000010000011011 +
b10111000101001000010000011011 2
r1004410 &
1"
#1000
0"
#1050
b11001101001101100010000100100 +
b11001101001101100010000100100 2
b100010010 !
b100010010 1
r1004900 &
1"
#1100
0"
#1150
b10100100101110010001110100 #
b10100100101110010001110100 )
b100101101 !
b100101101 1
b11100001110010000010000101101 +
b11100001110010000010000101101 2
r1005390 &
1"
#1200
0"
#1250
b11110110010111110100010100001 +
b11110110010111110100010100001 2
b101000110 !
b101000110 1
r1005880 &
1"
#1300
0"
#1350
b10100100111000100011011110 #
b10100100111000100011011110 )
b101011110 !
b101011110 1
b100001010111101100110100010101 +
b100001010111101100110100010101 2
r1006370 &
1"
#1400
0"
#1450
b100011111100100101010111110011 +
b100011111100100101010111110011 2
b101110101 !
b101110101 1
r1006860 &
1"
#1500
0"
#1550
b10100101000010110101001001 #
b10100101000010110101001001 )
b110001011 !
b110001011 1
b100110100001011101111011010001 +
b100110100001011101111011010001 2
r1007350 &
1"
#1600
0"
#1650
b101001000110100000110000011010 +
b101001000110100000110000011010 2
b110011110 !
b110011110 1
r1007840 &
1"
#1700
0"
#1750
b10100101001101000110110100 #
b10100101001101000110110100 )
b110110000 !
b110110000 1
b101011101011100011100101100011 +
b101011101011100011100101100011 2
r1008330 &
1"
#1800
0"
#1850
b101110010000110000101100010111 +
b101110010000110000101100010111 2
b111000001 !
b111000001 1
r1008820 &
1"
#1900
0"
#1950
b10100101010111011000011110 #
b10100101010111011000011110 )
b111001111 !
b111001111 1
b110000110101111101110011001011 +
b110000110101111101110011001011 2
r1009310 &
1"
#2000
0"
#2050
b110011011011010101001011101001 +
b110011011011010101001011101001 2
b111011100 !
b111011100 1
r1009800 &
1"
#2100
0"
#2150
b10100101100001101010001001 #
b10100101100001101010001001 )
b111100111 !
b111100111 1
b110110000000101100100100000111 +
b110110000000101100100100000111 2
r1010290 &
1"
#2200
0"
#2250
b111000100110001110001110010000 +
b111000100110001110001110010000 2
b111110000 !
b111110000 1
r1010780 &
1"
#2300
0"
#2350
b10100101101011111011110100 #
b10100101101011111011110100 )
b111110111 !
b111110111 1
b111011001011101111111000011001 +
b111011001011101111111000011001 2
r1011270 &
1"
#2400
0"
#2450
b111101110001011011110100001101 +
b111101110001011011110100001101 2
b111111011 !
b111111011 1
r1011760 &
1"
#2500
0"
#2550
b10100101110110001101011110 #
b10100101110110001101011110 )
b111111110 !
b111111110 1
b1000000010111000111110000000001 +
b1000000010111000111110000000001 2
r1012250 &
1"
#2600
0"
#2650
b1000010111100111101111101011111 +
b1000010111100111101111101011111 2
b111111111 !
b111111111 1
r1012740 &
1"
#2700
0"
#2750
b10100110000000011111001001 #
b10100110000000011111001001 )
b111111110 !
b111111110 1
b1000101100010110100001010111101 +
b1000101100010110100001010111101 2
r1013230 &
1"
#2800
0"
#2850
b1001000001000110100101010000110 +
b1001000001000110100101010000110 2
b111111010 !
b111111010 1
r1013720 &
1"
#2900
0"
#2950
b10100110001010110000110100 #
b10100110001010110000110100 )
b111110101 !
b111110101 1
b1001010101110110101001001001111 +
b1001010101110110101001001001111 2
r1014210 &
1"
#3000
0"
#3050
b1001101010100111111111010000011 +
b1001101010100111111111010000011 2
b111101101 !
b111101101 1
r1014700 &
1"
#3100
0"
#3150
b10100110010101000010011110 #
b10100110010101000010011110 )
b111100100 !
b111100100 1
b1001111111011001010101010110111 +
b1001111111011001010101010110111 2
r1015190 &
1"
#3200
0"
#3250
b1010010100001011111101101010101 +
b1010010100001011111101101010101 2
b111011001 !
b111011001 1
r1015680 &
1"
#3300
0"
#3350
b10100110011111010100001001 #
b10100110011111010100001001 )
b111001011 !
b111001011 1
b1010101000111110100101111110011 +
b1010101000111110100101111110011 2
r1016170 &
1"
#3400
0"
#3450
b1010111101110010100000011111100 +
b1010111101110010100000011111100 2
b110111100 !
b110111100 1
r1016660 &
1"
#3500
0"
#3550
b10100110101001100101110100 #
b10100110101001100101110100 )
b110101011 !
b110101011 1
b1011010010100110011011000000101 +
b1011010010100110011011000000101 2
r1017150 &
1"
#3600
0"
#3650
b1011100111011011100111101111001 +
b1011100111011011100111101111001 2
b110011000 !
b110011000 1
r1017640 &
1"
#3700
0"
#3750
b10100110110011110111011111 #
b10100110110011110111011111 )
b110000100 !
b110000100 1
b1011111100010000110100011101101 +
b1011111100010000110100011101101 2
r1018130 &
1"
#3800
0"
#3850
b1100010001000111010011011001100 +
b1100010001000111010011011001100 2
b101101101 !
b101101101 1
r1018620 &
1"
#3900
0"
#3950
b10100110111110001001001001 #
b10100110111110001001001001 )
b101010110 !
b101010110 1
b1100100101111101110010010101011 +
b1100100101111101110010010101011 2
r1019110 &
1"
#4000
0"
#4050
b1100111010110101100011011110100 +
b1100111010110101100011011110100 2
b100111101 !
b100111101 1
r1019600 &
1"
#4100
0"
#4150
b10100111001000011010110100 #
b10100111001000011010110100 )
b100100011 !
b100100011 1
b1101001111101101010100100111101 +
b1101001111101101010100100111101 2
r1020090 &
1"
#4200
0"
#4250
b1101100100100110010111111110001 +
b1101100100100110010111111110001 2
b100000111 !
b100000111 1
r1020580 &
1"
#4300
0"
#4350
b10100111010010101100011111 #
b10100111010010101100011111 )
b11101011 !
b11101011 1
b1101111001011111011011010100101 +
b1101111001011111011011010100101 2
r1021070 &
1"
#4400
0"
#4450
b1110001110011001110000111000100 +
b1110001110011001110000111000100 2
b11001101 !
b11001101 1
r1021560 &
1"
#4500
0"
#4550
b10100111011100111110001001 #
b10100111011100111110001001 )
b10101111 !
b10101111 1
b1110100011010100000110011100011 +
b1110100011010100000110011100011 2
r1022050 &
1"
#4600
0"
#4650
b1110111000001111101110001101100 +
b1110111000001111101110001101100 2
b10001111 !
b10001111 1
r1022540 &
1"
#4700
0"
#4750
b10100111100111001111110100 #
b10100111100111001111110100 )
b1110000 !
b1110000 1
b1111001101001011010101111110101 +
b1111001101001011010101111110101 2
r1023030 &
1"
#4800
0"
#4850
b1111100010001000001111111101001 +
b1111100010001000001111111101001 2
b1010000 !
b1010000 1
r1023520 &
1"
#4900
0"
#4950
b10100111110001100001011111 #
b10100111110001100001011111 )
b101111 !
b101111 1
b1111110111000101001001111011101 +
b1111110111000101001001111011101 2
r1024010 &
1"
#5000
0"
#5050
b10000001100000011010110000111100 +
b10000001100000011010110000111100 2
b1110 !
b1110 1
r1024500 &
1"
#5100
0"
#5150
b10100111111011110011001001 #
b10100111111011110011001001 )
b1111101101 !
b1111101101 1
b10000100001000001100010010011011 +
b10000100001000001100010010011011 2
r1024990 &
1"
#5200
0"
#5250
b10000110110000001000000101100100 +
b10000110110000001000000101100100 2
b1111001100 !
b1111001100 1
r1025480 &
1"
#5300
0"
#5350
b10101000000110000100110100 #
b10101000000110000100110100 )
b1110101100 !
b1110101100 1
b10001001011000000011111000101101 +
b10001001011000000011111000101101 2
r1025970 &
1"
#5400
0"
#5450
b10001100000000001001111101100001 +
b10001100000000001001111101100001 2
b1110001011 !
b1110001011 1
r1026460 &
1"
#5500
0"
#5550
b10101000010000010110011111 #
b10101000010000010110011111 )
b1101101100 !
b1101101100 1
b10001110101000010000000010010101 +
b10001110101000010000000010010101 2
r1026950 &
1"
#5600
0"
#5650
b10010001010000100000011000110100 +
b10010001010000100000011000110100 2
b1101001100 !
b1101001100 1
r1027440 &
1"
#5700
0"
#5750
b10101000011010101000001001 #
b10101000011010101000001001 )
b1100101110 !
b1100101110 1
b10010011111000110000101111010011 +
b10010011111000110000101111010011 2
r1027930 &
1"
#5800
0"
#5850
b10010110100001001011010111011100 +
b10010110100001001011010111011100 2
b1100010001 !
b1100010001 1
r1028420 &
1"
#5900
0"
#5950
b10101000100100111001110100 #
b10101000100100111001110100 )
b1011110100 !
b1011110100 1
b10011001001001100101111111100101 +
b10011001001001100101111111100101 2
r1028910 &
1"
#6000
0"
#6050
b10011011110010001010111001011001 +
b10011011110010001010111001011001 2
b1011011000 !
b1011011000 1
r1029400 &
1"
#6100
0"
#6150
b10101000101111001011011111 #
b10101000101111001011011111 )
b1010111110 !
b1010111110 1
b10011110011010101111110011001101 +
b10011110011010101111110011001101 2
r1029890 &
1"
#6200
0"
#6250
b10100001000011011110111110101100 +
b10100001000011011110111110101100 2
b1010100101 !
b1010100101 1
r1030380 &
1"
#6300
0"
#6350
b10101000111001011101001001 #
b10101000111001011101001001 )
b1010001110 !
b1010001110 1
b10100011101100001110001010001011 +
b10100011101100001110001010001011 2
r1030870 &
1"
#6400
0"
#6450
b10100110010101000111100111010100 +
b10100110010101000111100111010100 2
b1001110111 !
b1001110111 1
r1031360 &
1"
#6500
0"
#6550
b10101001000011101110110100 #
b10101001000011101110110100 )
b1001100011 !
b1001100011 1
b10101000111110000001000100011101 +
b10101000111110000001000100011101 2
r1031850 &
1"
#6600
0"
#6650
b10101011100111000100110011010001 +
b10101011100111000100110011010001 2
b1001010000 !
b1001010000 1
r1032340 &
1"
#6700
0"
#6750
b10101001001110000000011111 #
b10101001001110000000011111 )
b1001000000 !
b1001000000 1
b10101110010000001000100010000101 +
b10101110010000001000100010000101 2
r1032830 &
1"
#6800
0"
#6850
b10110000111001010110100010100100 +
b10110000111001010110100010100100 2
b1000110001 !
b1000110001 1
r1033320 &
1"
#6900
0"
#6950
b10101001011000010010001001 #
b10101001011000010010001001 )
b1000100100 !
b1000100100 1
b10110011100010100100100011000011 +
b10110011100010100100100011000011 2
r1033810 &
1"
#7000
0"
#7050
b10110110001011111100110101001100 +
b10110110001011111100110101001100 2
b1000011001 !
b1000011001 1
r1034300 &
1"
#7100
0"
#7150
b10101001100010100011110100 #
b10101001100010100011110100 )
b1000010000 !
b1000010000 1
b10111000110101010101000111010101 +
b10111000110101010101000111010101 2
r1034790 &
1"
#7200
0"
#7250
b10111011011110110111101011001001 +
b10111011011110110111101011001001 2
b1000001001 !
b1000001001 1
r1035280 &
1"
#7300
0"
#7350
b10101001101100110101011111 #
b10101001101100110101011111 )
b1000000100 !
b1000000100 1
b10111110001000011010001110111101 +
b10111110001000011010001110111101 2
r1035770 &
1"
#7400
0"
#7450
b11000000110010000111000100011100 +
b11000000110010000111000100011100 2
b1000000010 !
b1000000010 1
r1036260 &
1"
#7500
0"
#7550
b10101001110111000111001001 #
b10101001110111000111001001 )
b1000000001 !
b1000000001 1
b11000011011011110011111001111011 +
b11000011011011110011111001111011 2
r1036750 &
1"
#7600
0"
#7650
b11000110000101101011000001000100 +
b11000110000101101011000001000100 2
b1000000011 !
b1000000011 1
r1037240 &
1"
#7700
0"
#7750
b10101010000001011000110100 #
b10101010000001011000110100 )
b1000000111 !
b1000000111 1
b11001000101111100010001000001101 +
b11001000101111100010001000001101 2
r1037730 &
1"
#7800
0"
#7850
b11001011011001100011100001000001 +
b11001011011001100011100001000001 2
b1000001101 !
b1000001101 1
r1038220 &
1"
#7900
0"
#7950
b10101010001011101010011111 #
b10101010001011101010011111 )
b1000010101 !
b1000010101 1
b11001110000011100100111001110101 +
b11001110000011100100111001110101 2
r1038710 &
1"
#8000
0"
#8050
b11010000101101110000100100010100 +
b11010000101101110000100100010100 2
b1000011111 !
b1000011111 1
r1039200 &
1"
#8100
0"
#8150
b10101010010101111100001001 #
b10101010010101111100001001 )
b1000101011 !
b1000101011 1
b11010011010111111100001110110011 +
b11010011010111111100001110110011 2
r1039690 &
1"
#8200
0"
#8250
b11010110000010010010001010111100 +
b11010110000010010010001010111100 2
b1000111010 !
b1000111010 1
r1040180 &
1"
#8300
0"
#8350
b10101010100000001101110100 #
b10101010100000001101110100 )
b1001001010 !
b1001001010 1
b11011000101100101000000111000101 +
b11011000101100101000000111000101 2
r1040670 &
1"
#8400
0"
#8450
b11011011010111001000010100111001 +
b11011011010111001000010100111001 2
b1001011100 !
b1001011100 1
r1041160 &
1"
#8500
0"
#8550
b10101010101010011111011111 #
b10101010101010011111011111 )
b1001110000 !
b1001110000 1
b11011110000001101000100010101101 +
b11011110000001101000100010101101 2
r1041650 &
1"
#8600
0"
#8650
b11100000101100010011000010001100 +
b11100000101100010011000010001100 2
b1010000101 !
b1010000101 1
r1042140 &
1"
#8700
0"
#8750
b10101010110100110001001010 #
b10101010110100110001001010 )
b1010011101 !
b1010011101 1
b11100011010110111101100001101011 +
b11100011010110111101100001101011 2
r1042630 &
1"
#8800
0"
#8850
b11100110000001110010010010110101 +
b11100110000001110010010010110101 2
b1010110110 !
b1010110110 1
r1043120 &
1"
#8900
0"
#8950
b10101010111111000010110100 #
b10101010111111000010110100 )
b1011010000 !
b1011010000 1
b11101000101100100111000011111111 +
b11101000101100100111000011111111 2
r1043610 &
1"
#9000
0"
#9050
b11101011010111100110000110110011 +
b11101011010111100110000110110011 2
b1011101011 !
b1011101011 1
r1044100 &
1"
#9100
0"
#9150
b10101011001001010100011111 #
b10101011001001010100011111 )
b1100001000 !
b1100001000 1
b11101110000010100101001001100111 +
b11101110000010100101001001100111 2
r1044590 &
1"
#9200
0"
#9250
b11110000101101101110011110000110 +
b11110000101101101110011110000110 2
b1100100110 !
b1100100110 1
r1045080 &
1"
#9300
0"
#9350
b10101011010011100110001010 #
b10101011010011100110001010 )
b1101000100 !
b1101000100 1
b11110011011000110111110010100101 +
b11110011011000110111110010100101 2
r1045570 &
1"
#9400
0"
#9450
b11110110000100001011011000101111 +
b11110110000100001011011000101111 2
b1101100100 !
b1101100100 1
r1046060 &
1"
#9500
0"
#9550
b10101011011101110111110100 #
b10101011011101110111110100 )
b1110000101 !
b1110000101 1
b11111000101111011110111110111001 +
b11111000101111011110111110111001 2
r1046550 &
1"
#9600
0"
#9650
b11111011011010111100110110101101 +
b11111011011010111100110110101101 2
b1110100101 !
b1110100101 1
r1047040 &
1"
#9700
0"
#9750
b10101011101000001001011111 #
b10101011101000001001011111 )
b1111000111 !
b1111000111 1
b11111110000110011010101110100001 +
b11111110000110011010101110100001 2
r1047530 &
1"
#9800
0"
#9850
b110010000010111000000000 +
b110010000010111000000000 2
b1111101000 !
b1111101000 1
r1048020 &
1"
#9900
0"
#9950
b10101011110010011011001010 #
b10101011110010011011001010 )
b1010 !
b1010 1
b11011101101011000001011111 +
b11011101101011000001011111 2
r1048510 &
1"
#10000
0"
#10050
b110001001011101011100101001 +
b110001001011101011100101001 2
b101011 !
b101011 1
r1049000 &
1"
#10100
0"
#10150
b10101011111100101100110100 #
b10101011111100101100110100 )
b1001101 !
b1001101 1
b1000110101001111110111110011 +
b1000110101001111110111110011 2
r1049490 &
1"
#10200
0"
#10250
b1011100001001100100100100111 +
b1011100001001100100100100111 2
b1101110 !
b1101110 1
r1049980 &
1"
#10300
0"
#10350
b10101100000110111110011111 #
b10101100000110111110011111 )
b10001110 !
b10001110 1
b1110001101001001010001011011 +
b1110001101001001010001011011 2
r1050470 &
1"
#10400
0"
#10450
b10000111001010000001111111010 +
b10000111001010000001111111010 2
b10101110 !
b10101110 1
r1050960 &
1"
#10500
0"
#10550
b10101100010001010000001010 #
b10101100010001010000001010 )
b11001110 !
b11001110 1
b10011100101010111001110011001 +
b10011100101010111001110011001 2
r1051450 &
1"
#10600
0"
#10650
b10110010001101000011110100011 +
b10110010001101000011110100011 2
b11101100 !
b11101100 1
r1051940 &
1"
#10700
0"
#10750
b10101100011011100001110100 #
b10101100011011100001110100 )
b100001001 !
b100001001 1
b11000111101111001101110101101 +
b11000111101111001101110101101 2
r1052430 &
1"
#10800
0"
#10850
b11011101010010101010000100001 +
b11011101010010101010000100001 2
b100100110 !
b100100110 1
r1052920 &
1"
#10900
0"
#10950
b10101100100101110011011111 #
b10101100100101110011011111 )
b101000001 !
b101000001 1
b11110010110110000110010010101 +
b11110010110110000110010010101 2
r1053410 &
1"
#11000
0"
#11050
b100001000011010110100101110100 +
b100001000011010110100101110100 2
b101011010 !
b101011010 1
r1053900 &
1"
#11100
0"
#11150
b10101100110000000101001010 #
b10101100110000000101001010 )
b101110010 !
b101110010 1
b100011101111111100011001010011 +
b100011101111111100011001010011 2
r1054390 &
1"
#11200
0"
#11250
b100110011100101100011110011101 +
b100110011100101100011110011101 2
b110001001 !
b110001001 1
r1054880 &
1"
#11300
0"
#11350
b10101100111010010110110100 #
b10101100111010010110110100 )
b110011110 !
b110011110 1
b101001001001011100100011100111 +
b101001001001011100100011100111 2
r1055370 &
1"
#11400
0"
#11450
b101011110110010110111010011011 +
b101011110110010110111010011011 2
b110110001 !
b110110001 1
r1055860 &
1"
#11500
0"
#11550
b10101101000100101000011111 #
b10101101000100101000011111 )
b111000010 !
b111000010 1
b101110100011010001010001001111 +
b101110100011010001010001001111 2
r1056350 &
1"
#11600
0"
#11650
b110001010000010101111001101110 +
b110001010000010101111001101110 2
b111010001 !
b111010001 1
r1056840 &
1"
#11700
0"
#11750
b10101101001110111010001010 #
b10101101001110111010001010 )
b111011110 !
b111011110 1
b110011111101011010100010001101 +
b110011111101011010100010001101 2
r1057330 &
1"
#11800
0"
#11850
b110110101010101001011100010111 +
b110110101010101001011100010111 2
b111101001 !
b111101001 1
r1057820 &
1"
#11900
0"
#11950
b10101101011001001011110100 #
b10101101011001001011110100 )
b111110010 !
b111110010 1
b111001010111111000010110100001 +
b111001010111111000010110100001 2
r1058310 &
1"
#12000
0"
#12050
b111100000101010001100010010101 +
b111100000101010001100010010101 2
b111111000 !
b111111000 1
r1058800 &
1"
#12100
0"
#12150
b10101101100011011101011111 #
b10101101100011011101011111 )
b111111101 !
b111111101 1
b111110110010101010101110001001 +
b111110110010101010101110001001 2
r1059290 &
1"
#12200
0"
#12250
b1000001100000001110001011101000 +
b1000001100000001110001011101000 2
b111111111 !
b111111111 1
r1059780 &
1"
#12300
0"
#12350
b10101101101101101111001010 #
b10101101101101101111001010 )
b1000100001101110001101001000111 +
b1000100001101110001101001000111 2
r1060270 &
1"
#12400
0"
#12450
b1000110111011011111011000010001 +
b1000110111011011111011000010001 2
b111111100 !
b111111100 1
r1060760 &
1"
#12500
0"
#12550
b10101101111000000000110100 #
b10101101111000000000110100 )
b111111000 !
b111111000 1
b1001001101001001101000111011011 +
b1001001101001001101000111011011 2
r1061250 &
1"
#12600
0"
#12650
b1001100010111000101001000001111 +
b1001100010111000101001000001111 2
b111110001 !
b111110001 1
r1061740 &
1"
#12700
0"
#12750
b10101110000010010010011111 #
b10101110000010010010011111 )
b111101000 !
b111101000 1
b1001111000100111101001001000011 +
b1001111000100111101001001000011 2
r1062230 &
1"
#12800
0"
#12850
b1010001110010111111011011100010 +
b1010001110010111111011011100010 2
b111011100 !
b111011100 1
r1062720 &
1"
#12900
0"
#12950
b10101110001100100100001010 #
b10101110001100100100001010 )
b111001111 !
b111001111 1
b1010100100001000001101110000001 +
b1010100100001000001101110000001 2
r1063210 &
1"
#13000
0"
#13050
b1010111001111001110010010001011 +
b1010111001111001110010010001011 2
b111000000 !
b111000000 1
r1063700 &
1"
#13100
0"
#13150
b10101110010110110101110100 #
b10101110010110110101110100 )
b110101110 !
b110101110 1
b1011001111101011010110110010101 +
b1011001111101011010110110010101 2
r1064190 &
1"
#13200
0"
#13250
b1011100101011110001101100001001 +
b1011100101011110001101100001001 2
b110011011 !
b110011011 1
r1064680 &
1"
#13300
0"
#13350
b10101110100001000111011111 #
b10101110100001000111011111 )
b110000110 !
b110000110 1
b1011111011010001000100001111101 +
b1011111011010001000100001111101 2
r1065170 &
1"
#13400
0"
#13450
b1100010001000101001101001011100 +
b1100010001000101001101001011100 2
b101101111 !
b101101111 1
r1065660 &
1"
#13500
0"
#13550
b10101110101011011001001010 #
b10101110101011011001001010 )
b101010110 !
b101010110 1
b1100100110111001010110000111011 +
b1100100110111001010110000111011 2
r1066150 &
1"
#13600
0"
#13650
b1100111100101110110001010000101 +
b1100111100101110110001010000101 2
b100111100 !
b100111100 1
r1066640 &
1"
#13700
0"
#13750
b10101110110101101010110101 #
b10101110110101101010110101 )
b100100000 !
b100100000 1
b1101010010100100001100011001111 +
b1101010010100100001100011001111 2
r1067130 &
1"
#13800
0"
#13850
b1101101000011010111001110000100 +
b1101101000011010111001110000100 2
b100000011 !
b100000011 1
r1067620 &
1"
#13900
0"
#13950
b10101110111111111100011111 #
b10101110111111111100011111 )
b11100101 !
b11100101 1
b1101111110010001100111000111001 +
b1101111110010001100111000111001 2
r1068110 &
1"
#14000
0"
#14050
b1110010100001001100110101011000 +
b1110010100001001100110101011000 2
b11000110 !
b11000110 1
r1068600 &
1"
#14100
0"
#14150
b10101111001010001110001010 #
b10101111001010001110001010 )
b10100110 !
b10100110 1
b1110101010000001100110001110111 +
b1110101010000001100110001110111 2
r1069090 &
1"
#14200
0"
#14250
b1110111111111010111000000000001 +
b1110111111111010111000000000001 2
b10000101 !
b10000101 1
r1069580 &
1"
#14300
0"
#14350
b10101111010100011111110101 #
b10101111010100011111110101 )
b1100100 !
b1100100 1
b1111010101110100001001110001011 +
b1111010101110100001001110001011 2
r1070070 &
1"
#14400
0"
#14450
b1111101011101110101101110000000 +
b1111101011101110101101110000000 2
b1000010 !
b1000010 1
r1070560 &
1"
#14500
0"
#14550
b10101111011110110001011111 #
b10101111011110110001011111 )
b100000 !
b100000 1
b10000000001101001010001101110101 +
b10000000001101001010001101110101 2
r1071050 &
1"
#14600
0"
#14650
b10000010111100101000111111010100 +
b10000010111100101000111111010100 2
b1111111110 !
b1111111110 1
r1071540 &
1"
#14700
0"
#14750
b10101111101001000011001010 #
b10101111101001000011001010 )
b1111011011 !
b1111011011 1
b10000101101100000111110000110011 +
b10000101101100000111110000110011 2
r1072030 &
1"
#14800
0"
#14850
b10001000011011110000110011111101 +
b10001000011011110000110011111101 2
b1110111001 !
b1110111001 1
r1072520 &
1"
#14900
0"
#14950
b10101111110011010100110101 #
b10101111110011010100110101 )
b1110010111 !
b1110010111 1
b10001011001011011001110111000111 +
b10001011001011011001110111000111 2
r1073010 &
1"
#15000
0"
#15050
b10001101111011001101001011111100 +
b10001101111011001101001011111100 2
b1101110110 !
b1101110110 1
r1073500 &
1"
#15100
0"
#15150
b10101111111101100110011111 #
b10101111111101100110011111 )
b1101010101 !
b1101010101 1
b10010000101011000000100000110001 +
b10010000101011000000100000110001 2
r1073990 &
1"
#15200
0"
#15250
b10010011011010111110000111010000 +
b10010011011010111110000111010000 2
b1100110101 !
b1100110101 1
r1074480 &
1"
#15300
0"
#15350
b10110000000111111000001010 #
b10110000000111111000001010 )
b1100010110 !
b1100010110 1
b10010110001010111011101101101111 +
b10010110001010111011101101101111 2
r1074970 &
1"
#15400
0"
#15450
b10011000111011000011100101111001 +
b10011000111011000011100101111001 2
b1011111000 !
b1011111000 1
r1075460 &
1"
#15500
0"
#15550
b10110000010010001001110101 #
b10110000010010001001110101 )
b1011011011 !
b1011011011 1
b10011011101011001011011110000011 +
b10011011101011001011011110000011 2
r1075950 &
1"
#15600
0"
#15650
b10011110011011011101100111111000 +
b10011110011011011101100111111000 2
b1010111111 !
b1010111111 1
r1076440 &
1"
#15700
0"
#15750
b10110000011100011011011111 #
b10110000011100011011011111 )
b1010100101 !
b1010100101 1
b10100001001011101111110001101101 +
b10100001001011101111110001101101 2
r1076930 &
1"
#15800
0"
#15850
b10100011111100001100001101001100 +
b10100011111100001100001101001100 2
b1010001101 !
b1010001101 1
r1077420 &
1"
#15900
0"
#15950
b10110000100110101101001010 #
b10110000100110101101001010 )
b1001110101 !
b1001110101 1
b10100110101100101000101000101011 +
b10100110101100101000101000101011 2
r1077910 &
1"
#16000
0"
#16050
b10101001011101001111010101110101 +
b10101001011101001111010101110101 2
b1001100000 !
b1001100000 1
r1078400 &
1"
#16100
0"
#16150
b10110000110000111110110101 #
b10110000110000111110110101 )
b1001001101 !
b1001001101 1
b10101100001101110110000010111111 +
b10101100001101110110000010111111 2
r1078890 &
1"
#16200
0"
#16250
b10101110111110100111000001110100 +
b10101110111110100111000001110100 2
b1000111100 !
b1000111100 1
r1079380 &
1"
#16300
0"
#16350
b10110000111011010000011111 #
b10110000111011010000011111 )
b1000101101 !
b1000101101 1
b10110001101111011000000000101001 +
b10110001101111011000000000101001 2
r1079870 &
1"
#16400
0"
#16450
b10110100100000010011010001001000 +
b10110100100000010011010001001000 2
b1000100000 !
b1000100000 1
r1080360 &
1"
#16500
0"
#16550
b10110001000101100010001010 #
b10110001000101100010001010 )
b1000010101 !
b1000010101 1
b10110111010001001110100001100111 +
b10110111010001001110100001100111 2
r1080850 &
1"
#16600
0"
