cc_event_handshake/cc_event_handshake.sv
module CrossClkEvent (
	input wire clk_a, clk_b,
	input wire in,     // domain a
	output logic busy, // domain a
	output logic out   // domain b
);
	logic ra0 = '0, ra1 = '0, ra2 = '0;
	logic rb0 = '0, rb1 = '0, rb2 = '0;
	// === clk_a domain ===
	always_ff@(posedge clk_a) begin
		if(in) ra0 <= 1'b1;
		else if(ra2) ra0 <= 1'b0;
	end
	always_ff@(posedge clk_a) begin
		{ra2, ra1} <= {ra1, rb1};
	end
	assign busy = ra0 | ra2;
	// === clk_b domain ===
	always_ff@(posedge clk_b) begin
		{rb2, rb1, rb0} <= {rb1, rb0, ra0};
	end
	assign out = rb1 & ~rb2;
endmodule

cc_event_handshake/tb_cc_event_handshake.sv
`timescale 1ns/1ns
`default_nettype none
module TestCCEvent;
    logic clk_a, clk_b;
    initial begin
        #2
            clk_a=1'b0;
        forever  #5  clk_a=~clk_a;
    end
    initial begin
        #1
            clk_b=1'b0;
        forever  #6  clk_b=~clk_b;
    end
    initial begin
        $dumpfile("wave.vcd");
        $dumpvars(0, TestCCEvent );
    #500 $finish;
    end
    logic in = 0;
	initial begin
		#100 in = 1;
		#10 in = 0;
		#80 in = 1;
		#10 in = 0;
	end
	logic busy, out;
    CrossClkEvent theCCEvent(clk_a, clk_b, in, busy, out);
endmodule

cc_event_handshake/wave.vcd
$date
	Sat Mar 16 14:11:07 2024
$end
$version
	Icarus Verilog
$end
$timescale
	1ns
$end
$scope module TestCCEvent $end
$var wire 1 ! out $end
$var wire 1 " busy $end
$var reg 1 # clk_a $end
$var reg 1 $ clk_b $end
$var reg 1 % in $end
$scope module theCCEvent $end
$var wire 1 " busy $end
$var wire 1 # clk_a $end
$var wire 1 $ clk_b $end
$var wire 1 % in $end
$var wire 1 ! out $end
$var reg 1 & ra0 $end
$var reg 1 ' ra1 $end
$var reg 1 ( ra2 $end
$var reg 1 ) rb0 $end
$var reg 1 * rb1 $end
$var reg 1 + rb2 $end
$upscope $end
$upscope $end
$enddefinitions $end
$comment Show the parameter values. $end
$dumpall
$end
#0
$dumpvars
0+
0*
0)
0(
0'
0&
0%
x$
x#
0"
0!
$end
#1
0$
#2
0#
#7
1#
1$
#12
0#
#13
0$
#17
1#
#19
1$
#22
0#
#25
0$
#27
1#
#31
1$
#32
0#
#37
1#
0$
#42
0#
#43
1$
#47
1#
#49
0$
#52
0#
#55
1$
#57
1#
#61
0$
#62
0#
#67
1#
1$
#72
0#
#73
0$
#77
1#
#79
1$
#82
0#
#85
0$
#87
1#
#91
1$
#92
0#
#97
1#
0$
#100
1%
#102
0#
#103
1$
#107
1"
1&
1#
#109
0$
#110
0%
#112
0#
#115
1)
1$
#117
1#
#121
0$
#122
0#
#127
1!
1*
1#
1$
#132
0#
#133
0$
#137
1'
1#
#139
0!
1+
1$
#142
0#
#145
0$
#147
1(
1#
#151
1$
#152
0#
#157
0&
1#
0$
#162
0#
#163
0)
1$
#167
1#
#169
0$
#172
0#
#175
0*
1$
#177
0'
1#
#181
0$
#182
0#
#187
0"
0(
0+
1#
1$
#190
1%
#192
0#
#193
0$
#197
1"
1&
1#
#199
1)
1$
#200
0%
#202
0#
#205
0$
#207
1#
#211
1!
1*
1$
#212
0#
#217
1'
1#
0$
#222
0#
#223
0!
1+
1$
#227
1(
1#
#229
0$
#232
0#
#235
1$
#237
0&
1#
#241
0$
#242
0#
#247
0)
1#
1$
#252
0#
#253
0$
#257
1#
#259
0*
1$
#262
0#
#265
0$
#267
0'
1#
#271
0+
1$
#272
0#
#277
0"
0(
1#
0$
