cross_cd_cnt_state/cross_cd_cnt_state.sv
module CrossClkCnt #( parameter W = 8 )(
	input wire clk_a, clk_b, inc,
	output logic [W - 1 : 0] cnt_a = '0,output reg [W - 1 : 0] cnt_b
);
	// === clk_a domain ===
	logic [W - 1 : 0] bin_next;
	logic [W - 1 : 0] gray, gray_next;
	always_comb begin
		bin_next = cnt_a + inc;
		gray_next = bin_next ^ (bin_next >> 1);
	end
	always_ff@(posedge clk_a) begin
		cnt_a <= bin_next;
		gray <= gray_next;
	end
	// === clk_b domain ===
	logic [W - 1 : 0] gray_sync[2];
	always_ff@(posedge clk_b) begin
		gray_sync[1] <= gray_sync[0];
		gray_sync[0] <= gray;
	end
	always_comb begin
		for(int i = 0; i < W; i++)
			cnt_b[i] = ^(gray_sync[1] >> i);
	end
endmodule

cross_cd_cnt_state/tb_cross_cd_cnt_state.sv
`timescale 1ns/1ns
`default_nettype none
module TestCCCnt;
    logic clk_a, clk_b;
    initial begin
        #2
            clk_a=1'b0;
        forever  #5  clk_a=~clk_a;
    end
    initial begin
        #1
            clk_b=1'b0;
        forever  #4.5  clk_b=~clk_b;
    end
    initial begin
        $dumpfile("wave.vcd");
        $dumpvars(0, TestCCCnt );
    #200 $finish;
    end
    logic inc = 0;
    always #10 inc = $random();
	logic [7:0] cnt_a, cnt_b;
    CrossClkCnt theCCCnt(clk_a, clk_b, inc, cnt_a, cnt_b);
endmodule

cross_cd_cnt_state/wave.vcd
$date
	Sun Mar 17 15:28:43 2024
$end
$version
	Icarus Verilog
$end
$timescale
	1ns
$end
$scope module TestCCCnt $end
$var wire 8 ! cnt_b [7:0] $end
$var wire 8 " cnt_a [7:0] $end
$var reg 1 # clk_a $end
$var reg 1 $ clk_b $end
$var reg 1 % inc $end
$scope module theCCCnt $end
$var wire 1 # clk_a $end
$var wire 1 $ clk_b $end
$var wire 1 % inc $end
$var parameter 32 & W $end
$var reg 8 ' bin_next [7:0] $end
$var reg 8 ( cnt_a [7:0] $end
$var reg 8 ) cnt_b [7:0] $end
$var reg 8 * gray [7:0] $end
$var reg 8 + gray_next [7:0] $end
$scope begin $ivl_for_loop0 $end
$var integer 32 , i [31:0] $end
$upscope $end
$upscope $end
$upscope $end
$enddefinitions $end
$comment Show the parameter values. $end
$dumpall
b1000 &
$end
#0
$dumpvars
b1000 ,
b0 +
bx *
bx )
b0 (
b0 '
0%
x$
x#
b0 "
bx !
$end
#1
0$
#2
0#
#6
1$
#7
b0 *
1#
#11
0$
#12
0#
#16
1$
#17
1#
#20
b1 +
b1 '
1%
#21
0$
#22
0#
#26
b0 !
b0 )
b1000 ,
1$
#27
b11 +
b10 '
b1 *
b1 "
b1 (
1#
#31
0$
#32
0#
#36
1$
#37
b10 +
b11 '
b11 *
b10 "
b10 (
1#
#41
0$
#42
0#
#46
b1 !
b1 )
b1000 ,
1$
#47
b110 +
b100 '
b10 *
b11 "
b11 (
1#
#51
0$
#52
0#
#56
b10 !
b10 )
b1000 ,
1$
#57
b111 +
b101 '
b110 *
b100 "
b100 (
1#
#61
0$
#62
0#
#66
b11 !
b11 )
b1000 ,
1$
#67
b101 +
b110 '
b111 *
b101 "
b101 (
1#
#71
0$
#72
0#
#76
b100 !
b100 )
b1000 ,
1$
#77
b100 +
b111 '
b101 *
b110 "
b110 (
1#
#80
b101 +
b110 '
0%
#81
0$
#82
0#
#86
b101 !
b101 )
b1000 ,
1$
#87
1#
#90
b100 +
b111 '
1%
#91
0$
#92
0#
#96
b110 !
b110 )
b1000 ,
1$
#97
b1100 +
b1000 '
b100 *
b111 "
b111 (
1#
#101
0$
#102
0#
#106
1$
#107
b1101 +
b1001 '
b1100 *
b1000 "
b1000 (
1#
#110
b1100 +
b1000 '
0%
#111
0$
#112
0#
#116
b111 !
b111 )
b1000 ,
1$
#117
1#
#120
b1101 +
b1001 '
1%
#121
0$
#122
0#
#126
b1000 !
b1000 )
b1000 ,
1$
#127
b1111 +
b1010 '
b1101 *
b1001 "
b1001 (
1#
#131
0$
#132
0#
#136
1$
#137
b1110 +
b1011 '
b1111 *
b1010 "
b1010 (
1#
#140
b1111 +
b1010 '
0%
#141
0$
#142
0#
#146
b1001 !
b1001 )
b1000 ,
1$
#147
1#
#150
b1110 +
b1011 '
1%
#151
0$
#152
0#
#156
b1010 !
b1010 )
b1000 ,
1$
#157
b1010 +
b1100 '
b1110 *
b1011 "
b1011 (
1#
#160
b1110 +
b1011 '
0%
#161
0$
#162
0#
#166
1$
#167
1#
#170
b1010 +
b1100 '
1%
#171
0$
#172
0#
#176
b1011 !
b1011 )
b1000 ,
1$
#177
b1011 +
b1101 '
b1010 *
b1100 "
b1100 (
1#
#180
b1010 +
b1100 '
0%
#181
0$
#182
0#
#186
1$
#187
1#
#190
b1011 +
b1101 '
1%
#191
0$
#192
0#
#196
b1100 !
b1100 )
b1000 ,
1$
#197
b1001 +
b1110 '
b1011 *
b1101 "
b1101 (
1#
