frequency_conter/frequency_conter.sv
//等精度测量法(低频)
module frequency_conter (
        input                 clk_fs ,
        input                 rst_n  ,
        input                 clk_fx ,

        output   reg [63:0]   fre
);

parameter	CLK_FS    = 26'd50_000_000;
parameter   GATE_TIME = 16'd100;    		//门控时间，越大误差越小，但测量时间也会变长

//reg define
reg                	gate_fx		;   		//门控信号，被测信号域下
reg                	gate_fs     ;           //同步到基准时钟的门控信号
reg                	gate_fs_r   ;          	//用于同步gate信号的寄存器
reg                	gate_fs_d0  ;           //用于采集基准时钟下gate下降沿
reg                	gate_fs_d1  ;           //用于采集基准时钟下gate下降沿
reg                	gate_fx_d0  ;          	//用于采集被测时钟下gate下降沿
reg                	gate_fx_d1  ;           //用于采集被测时钟下gate下降沿
reg    [15:0]   	gate_cnt    ;          	//门控计数
reg    [31:0]   	fs_cnt      ;           //门控时间内基准时钟的计数值
reg    [31:0]   	fs_cnt_temp ;           //fs_cnt 临时值
reg    [31:0]   	fx_cnt      ;           //门控时间内被测时钟的计数值
reg    [31:0]   	fx_cnt_temp ;           //fx_cnt 临时值

//wire define
wire               neg_gate_fs;            	//基准时钟下门控信号下降沿=
wire               neg_gate_fx;            	//被测时钟下门控信号下降沿

//捕捉信号下降沿
assign neg_gate_fs = gate_fs_d1 & (~gate_fs_d0);
assign neg_gate_fx = gate_fx_d1 & (~gate_fx_d0);

//检测gate_fx下降沿
always @(posedge clk_fx or negedge rst_n) begin
    if(!rst_n) begin
        gate_fx_d0 <= 1'b0;
        gate_fx_d1 <= 1'b0;
    end
    else begin
        gate_fx_d0 <= gate_fx;
        gate_fx_d1 <= gate_fx_d0;
    end
end
//检测gate_fs下降沿
always @(posedge clk_fs or negedge rst_n) begin
    if(!rst_n) begin
        gate_fs_d0 <= 1'b0;
        gate_fs_d1 <= 1'b0;
    end
    else begin
        gate_fs_d0 <= gate_fs;
        gate_fs_d1 <= gate_fs_d0;
    end
end
//被测时钟闸门计数器
always @(posedge clk_fx or negedge rst_n) begin
    if(!rst_n)
        gate_cnt <= 16'd0;
    else if(gate_cnt == GATE_TIME*2)
        gate_cnt <= 16'd0;
    else
        gate_cnt <= gate_cnt + 1'b1;
end
//被测时钟闸门生成
always @(posedge clk_fx or negedge rst_n) begin
    if(!rst_n)
        gate_fx <= 1'b0;
    else if(gate_cnt == GATE_TIME)
        gate_fx <= 1'b1;
    else if(gate_cnt == GATE_TIME*2)
        gate_fx <= 1'b0;
    else
        gate_fx <= gate_fx;
end
//把闸门从被测时钟域同步到基准时钟域
always @(posedge clk_fs or negedge rst_n) begin
    if(!rst_n) begin
        gate_fs_r <= 1'b0;
        gate_fs   <= 1'b0;
    end
    else begin
        gate_fs_r <= gate_fx;
        gate_fs   <= gate_fs_r;
    end
end
//在被测时钟域对被测信号计数
always @(posedge clk_fx or negedge rst_n) begin
    if(!rst_n) begin
        fx_cnt_temp <= 0;
        fx_cnt <= 0;
    end
    else if(gate_fx)
        fx_cnt_temp <= fx_cnt_temp + 1'b1;
    else if(neg_gate_fx) begin
        fx_cnt_temp <= 0;
        fx_cnt <= fx_cnt_temp;
    end
end
//在基准时钟域对基准时钟计数
always @(posedge clk_fs or negedge rst_n) begin
    if(!rst_n) begin
        fs_cnt_temp <= 0;
        fs_cnt <= 0;
    end
    else if(gate_fs)
        fs_cnt_temp <= fs_cnt_temp + 1'b1;
    else if(neg_gate_fs) begin
        fs_cnt_temp <= 0;
        fs_cnt <= fs_cnt_temp;
    end
end
//在基准时钟域输出结果
always @(posedge clk_fs or negedge rst_n) begin
    if(!rst_n) begin
        fre <= 0;
    end
    else if(gate_fs == 1'b0)
        fre <= (CLK_FS * fx_cnt ) / fs_cnt;
end
endmodule

frequency_conter/frequency_conter_test.sv
`timescale 1 ns/ 1 ns
//------------<模块及端口声明>----------------------------------------
module frequency_conter_test();

reg clk_fs;
reg clk_fx;
reg rst_n;

wire [63:0]  fre;

//------------<例化被测试模块>----------------------------------------
frequency_conter frequency_conter_inst (
	.clk_fs		(clk_fs	)	,
	.clk_fx		(clk_fx	)	,
	.fre		(fre	)	,
	.rst_n		(rst_n	)
);
//------------<设置初始测试条件>----------------------------------------
initial	begin
	clk_fs = 1'b0;
	clk_fx <= 1'b0;
	rst_n <= 1'b0;
	#116
	rst_n <= 1'b1;

end
//------------<设置时钟>----------------------------------------------
always	#10 clk_fs <= ~clk_fs;
always  #489 clk_fx <= ~clk_fx;

initial begin
    $dumpfile("wave.vcd");
    $dumpvars(0, frequency_conter_test);
#1000000 $finish;
end

endmodule

frequency_conter/wave.vcd
$date
	Thu May 30 14:48:02 2024
$end
$version
	Icarus Verilog
$end
$timescale
	1ns
$end
$scope module frequency_conter_test $end
$var wire 64 ! fre [63:0] $end
$var reg 1 " clk_fs $end
$var reg 1 # clk_fx $end
$var reg 1 $ rst_n $end
$scope module frequency_conter_inst $end
$var wire 1 " clk_fs $end
$var wire 1 # clk_fx $end
$var wire 1 % neg_gate_fs $end
$var wire 1 & neg_gate_fx $end
$var wire 1 $ rst_n $end
$var parameter 26 ' CLK_FS $end
$var parameter 16 ( GATE_TIME $end
$var reg 64 ) fre [63:0] $end
$var reg 32 * fs_cnt [31:0] $end
$var reg 32 + fs_cnt_temp [31:0] $end
$var reg 32 , fx_cnt [31:0] $end
$var reg 32 - fx_cnt_temp [31:0] $end
$var reg 16 . gate_cnt [15:0] $end
$var reg 1 / gate_fs $end
$var reg 1 0 gate_fs_d0 $end
$var reg 1 1 gate_fs_d1 $end
$var reg 1 2 gate_fs_r $end
$var reg 1 3 gate_fx $end
$var reg 1 4 gate_fx_d0 $end
$var reg 1 5 gate_fx_d1 $end
$upscope $end
$upscope $end
$enddefinitions $end
$comment Show the parameter values. $end
$dumpall
b1100100 (
b10111110101111000010000000 '
$end
#0
$dumpvars
05
04
03
02
01
00
0/
b0 .
b0 -
b0 ,
b0 +
b0 *
b0 )
0&
0%
0$
0#
0"
b0 !
$end
#10
1"
#20
0"
#30
1"
#40
0"
#50
1"
#60
0"
#70
1"
#80
0"
#90
1"
#100
0"
#110
1"
#116
1$
#120
0"
#130
bx !
bx )
1"
#140
0"
#150
1"
#160
0"
#170
1"
#180
0"
#190
1"
#200
0"
#210
1"
#220
0"
#230
1"
#240
0"
#250
1"
#260
0"
#270
1"
#280
0"
#290
1"
#300
0"
#310
1"
#320
0"
#330
1"
#340
0"
#350
1"
#360
0"
#370
1"
#380
0"
#390
1"
#400
0"
#410
1"
#420
0"
#430
1"
#440
0"
#450
1"
#460
0"
#470
1"
#480
0"
#489
b1 .
1#
#490
1"
#500
0"
#510
1"
#520
0"
#530
1"
#540
0"
#550
1"
#560
0"
#570
1"
#580
0"
#590
1"
#600
0"
#610
1"
#620
0"
#630
1"
#640
0"
#650
1"
#660
0"
#670
1"
#680
0"
#690
1"
#700
0"
#710
1"
#720
0"
#730
1"
#740
0"
#750
1"
#760
0"
#770
1"
#780
0"
#790
1"
#800
0"
#810
1"
#820
0"
#830
1"
#840
0"
#850
1"
#860
0"
#870
1"
#880
0"
#890
1"
#900
0"
#910
1"
#920
0"
#930
1"
#940
0"
#950
1"
#960
0"
#970
1"
#978
0#
#980
0"
#990
1"
#1000
0"
#1010
1"
#1020
0"
#1030
1"
#1040
0"
#1050
1"
#1060
0"
#1070
1"
#1080
0"
#1090
1"
#1100
0"
#1110
1"
#1120
0"
#1130
1"
#1140
0"
#1150
1"
#1160
0"
#1170
1"
#1180
0"
#1190
1"
#1200
0"
#1210
1"
#1220
0"
#1230
1"
#1240
0"
#1250
1"
#1260
0"
#1270
1"
#1280
0"
#1290
1"
#1300
0"
#1310
1"
#1320
0"
#1330
1"
#1340
0"
#1350
1"
#1360
0"
#1370
1"
#1380
0"
#1390
1"
#1400
0"
#1410
1"
#1420
0"
#1430
1"
#1440
0"
#1450
1"
#1460
0"
#1467
b10 .
1#
#1470
1"
#1480
0"
#1490
1"
#1500
0"
#1510
1"
#1520
0"
#1530
1"
#1540
0"
#1550
1"
#1560
0"
#1570
1"
#1580
0"
#1590
1"
#1600
0"
#1610
1"
#1620
0"
#1630
1"
#1640
0"
#1650
1"
#1660
0"
#1670
1"
#1680
0"
#1690
1"
#1700
0"
#1710
1"
#1720
0"
#1730
1"
#1740
0"
#1750
1"
#1760
0"
#1770
1"
#1780
0"
#1790
1"
#1800
0"
#1810
1"
#1820
0"
#1830
1"
#1840
0"
#1850
1"
#1860
0"
#1870
1"
#1880
0"
#1890
1"
#1900
0"
#1910
1"
#1920
0"
#1930
1"
#1940
0"
#1950
1"
#1956
0#
#1960
0"
#1970
1"
#1980
0"
#1990
1"
#2000
0"
#2010
1"
#2020
0"
#2030
1"
#2040
0"
#2050
1"
#2060
0"
#2070
1"
#2080
0"
#2090
1"
#2100
0"
#2110
1"
#2120
0"
#2130
1"
#2140
0"
#2150
1"
#2160
0"
#2170
1"
#2180
0"
#2190
1"
#2200
0"
#2210
1"
#2220
0"
#2230
1"
#2240
0"
#2250
1"
#2260
0"
#2270
1"
#2280
0"
#2290
1"
#2300
0"
#2310
1"
#2320
0"
#2330
1"
#2340
0"
#2350
1"
#2360
0"
#2370
1"
#2380
0"
#2390
1"
#2400
0"
#2410
1"
#2420
0"
#2430
1"
#2440
0"
#2445
b11 .
1#
#2450
1"
#2460
0"
#2470
1"
#2480
0"
#2490
1"
#2500
0"
#2510
1"
#2520
0"
#2530
1"
#2540
0"
#2550
1"
#2560
0"
#2570
1"
#2580
0"
#2590
1"
#2600
0"
#2610
1"
#2620
0"
#2630
1"
#2640
0"
#2650
1"
#2660
0"
#2670
1"
#2680
0"
#2690
1"
#2700
0"
#2710
1"
#2720
0"
#2730
1"
#2740
0"
#2750
1"
#2760
0"
#2770
1"
#2780
0"
#2790
1"
#2800
0"
#2810
1"
#2820
0"
#2830
1"
#2840
0"
#2850
1"
#2860
0"
#2870
1"
#2880
0"
#2890
1"
#2900
0"
#2910
1"
#2920
0"
#2930
1"
#2934
0#
#2940
0"
#2950
1"
#2960
0"
#2970
1"
#2980
0"
#2990
1"
#3000
0"
#3010
1"
#3020
0"
#3030
1"
#3040
0"
#3050
1"
#3060
0"
#3070
1"
#3080
0"
#3090
1"
#3100
0"
#3110
1"
#3120
0"
#3130
1"
#3140
0"
#3150
1"
#3160
0"
#3170
1"
#3180
0"
#3190
1"
#3200
0"
#3210
1"
#3220
0"
#3230
1"
#3240
0"
#3250
1"
#3260
0"
#3270
1"
#3280
0"
#3290
1"
#3300
0"
#3310
1"
#3320
0"
#3330
1"
#3340
0"
#3350
1"
#3360
0"
#3370
1"
#3380
0"
#3390
1"
#3400
0"
#3410
1"
#3420
0"
#3423
b100 .
1#
#3430
1"
#3440
0"
#3450
1"
#3460
0"
#3470
1"
#3480
0"
#3490
1"
#3500
0"
#3510
1"
#3520
0"
#3530
1"
#3540
0"
#3550
1"
#3560
0"
#3570
1"
#3580
0"
#3590
1"
#3600
0"
#3610
1"
#3620
0"
#3630
1"
#3640
0"
#3650
1"
#3660
0"
#3670
1"
#3680
0"
#3690
1"
#3700
0"
#3710
1"
#3720
0"
#3730
1"
#3740
0"
#3750
1"
#3760
0"
#3770
1"
#3780
0"
#3790
1"
#3800
0"
#3810
1"
#3820
0"
#3830
1"
#3840
0"
#3850
1"
#3860
0"
#3870
1"
#3880
0"
#3890
1"
#3900
0"
#3910
1"
#3912
0#
#3920
0"
#3930
1"
#3940
0"
#3950
1"
#3960
0"
#3970
1"
#3980
0"
#3990
1"
#4000
0"
#4010
1"
#4020
0"
#4030
1"
#4040
0"
#4050
1"
#4060
0"
#4070
1"
#4080
0"
#4090
1"
#4100
0"
#4110
1"
#4120
0"
#4130
1"
#4140
0"
#4150
1"
#4160
0"
#4170
1"
#4180
0"
#4190
1"
#4200
0"
#4210
1"
#4220
0"
#4230
1"
#4240
0"
#4250
1"
#4260
0"
#4270
1"
#4280
0"
#4290
1"
#4300
0"
#4310
1"
#4320
0"
#4330
1"
#4340
0"
#4350
1"
#4360
0"
#4370
1"
#4380
0"
#4390
1"
#4400
0"
#4401
b101 .
1#
