pulse_widen/pulse_widen.sv
`default_nettype none
module PulseWiden #( parameter RATIO = 1 )(
	input wire clk, in,
	output logic out
);
	logic [$clog2(RATIO + 1) - 1 : 0] cnt = '0;
	always_ff@(posedge clk) begin
		if(in) cnt <= RATIO;
		else if(cnt > 0) cnt <= cnt - 1'b1;
	end
	assign out = cnt > 0;
endmodule

pulse_widen/tb_pulse_widen.sv
`timescale 1ns/1ns
`default_nettype none
module TestPulseWiden;
	logic clk;
    initial begin
        #0
            clk=1'b0;
        forever  #5  clk=~clk;
    end
	logic in;
	initial begin
		in = 0;
		#44 in = 1;
		#56 in = 0;
		#100 in = 1;
		#10 in = 0;
	end
    initial begin
        $dumpfile("wave.vcd");
        $dumpvars(0, TestPulseWiden );
    #400 $finish;
    end
	logic out, out2, out3;
	PulseWiden #(4) pw1(clk, in, out);
	PulseWiden #(2) pw2(clk, in, out2);
	PulseWiden #(3) pw3(clk, in, out3);
endmodule

pulse_widen/wave.vcd
$date
	Thu Feb 22 20:33:27 2024
$end
$version
	Icarus Verilog
$end
$timescale
	1ns
$end
$scope module TestPulseWiden $end
$var wire 1 ! out3 $end
$var wire 1 " out2 $end
$var wire 1 # out $end
$var reg 1 $ clk $end
$var reg 1 % in $end
$scope module pw1 $end
$var wire 1 $ clk $end
$var wire 1 % in $end
$var wire 1 # out $end
$var parameter 32 & RATIO $end
$var reg 3 ' cnt [2:0] $end
$upscope $end
$scope module pw2 $end
$var wire 1 $ clk $end
$var wire 1 % in $end
$var wire 1 " out $end
$var parameter 32 ( RATIO $end
$var reg 2 ) cnt [1:0] $end
$upscope $end
$scope module pw3 $end
$var wire 1 $ clk $end
$var wire 1 % in $end
$var wire 1 ! out $end
$var parameter 32 * RATIO $end
$var reg 2 + cnt [1:0] $end
$upscope $end
$upscope $end
$enddefinitions $end
$comment Show the parameter values. $end
$dumpall
b11 *
b10 (
b100 &
$end
#0
$dumpvars
b0 +
b0 )
b0 '
0%
0$
0#
0"
0!
$end
#5
1$
#10
0$
#15
1$
#20
0$
#25
1$
#30
0$
#35
1$
#40
0$
#44
1%
#45
1#
b100 '
1"
b10 )
1!
b11 +
1$
#50
0$
#55
1$
#60
0$
#65
1$
#70
0$
#75
1$
#80
0$
#85
1$
#90
0$
#95
1$
#100
0$
0%
#105
b11 '
b1 )
b10 +
1$
#110
0$
#115
b1 +
0"
b0 )
b10 '
1$
#120
0$
#125
b1 '
0!
b0 +
1$
#130
0$
#135
0#
b0 '
1$
#140
0$
#145
1$
#150
0$
#155
1$
#160
0$
#165
1$
#170
0$
#175
1$
#180
0$
#185
1$
#190
0$
#195
1$
#200
0$
1%
#205
1#
b100 '
1"
b10 )
1!
b11 +
1$
#210
0$
0%
#215
b10 +
b1 )
b11 '
1$
#220
0$
#225
b10 '
0"
b0 )
b1 +
1$
#230
0$
#235
0!
b0 +
b1 '
1$
#240
0$
#245
0#
b0 '
1$
