counter/counter.sv
`ifndef __COUNTER_SV__
`define __COUNTER_SV__

`default_nettype none


module CntSecMinHr(
    input wire clk, rst,
    output logic [5:0] sec,
    output logic [5:0] min,
    output logic [4:0] hr
);
    logic en1sec, en1min, en1hr;
    Counter #(10) cnt1sec (.clk(clk), .rst(rst), .en(  1'b1), .cnt(),    .co(en1sec));
    Counter #(60) cnt60sec(.clk(clk), .rst(rst), .en(en1sec), .cnt(sec), .co(en1min));
    Counter #(60) cnt60min(.clk(clk), .rst(rst), .en(en1min), .cnt(min), .co(en1hr ));
    Counter #(24) cnt24hr (.clk(clk), .rst(rst), .en(en1hr ), .cnt(hr ), .co());
endmodule

module Counter #(
    parameter M = 100
)(
    input wire clk, rst, en,
    output logic [$clog2(M) - 1 : 0] cnt,
    output logic co
);
    assign co = en & (cnt == M - 1);
    always_ff@(posedge clk) begin
        if(rst) cnt <= '0;
        else if(en) begin
            if(cnt < M - 1) cnt <= cnt + 1'b1;
            else cnt <= '0;
        end
    end
endmodule

module CounterMax #(
    parameter DW = 8
)(
    input wire clk, rst, en,
    input wire [DW - 1 : 0] max,
    output logic [DW - 1 : 0] cnt,
    output logic co
);
    assign co = en & (cnt == max);
    always_ff@(posedge clk) begin
        if(rst) cnt <= '0;
        else if(en) begin
            if(cnt < max) cnt <= cnt + 1'b1;
            else cnt <= '0;
        end
    end
endmodule

`endif

counter/tb_counter.sv
`timescale 1ps/1ps
`default_nettype none

module TestCounter;
    logic clk;
    logic rst;
    logic en;
    initial begin
        #0
            rst=1'b1;
        #20
            rst=1'b0;
    end
    initial begin
        #0
            clk=1'b0;
        forever  #5  clk=~clk;
    end
    initial begin
        en = 1'b1;
        #100 en = 1'b0;
        #100 en = 1'b1;
    end
    initial begin
        $dumpfile("wave.vcd");
        $dumpvars(0, TestCounter );
    #20000 $finish;
    end
    logic [6:0] cnt;
    logic co;
    Counter #(128) theCnt(clk, rst, en, cnt, co);
endmodule

counter/wave.vcd
$date
	Wed Feb 21 13:24:48 2024
$end
$version
	Icarus Verilog
$end
$timescale
	1ps
$end
$scope module TestCounter $end
$var wire 1 ! co $end
$var wire 7 " cnt [6:0] $end
$var reg 1 # clk $end
$var reg 1 $ en $end
$var reg 1 % rst $end
$scope module theCnt $end
$var wire 1 # clk $end
$var wire 1 ! co $end
$var wire 1 $ en $end
$var wire 1 % rst $end
$var parameter 32 & M $end
$var reg 7 ' cnt [6:0] $end
$upscope $end
$upscope $end
$enddefinitions $end
$comment Show the parameter values. $end
$dumpall
b10000000 &
$end
#0
$dumpvars
bx '
1%
1$
0#
bx "
x!
$end
#5
0!
b0 "
b0 '
1#
#10
0#
#15
1#
#20
0#
0%
#25
b1 "
b1 '
1#
#30
0#
#35
b10 "
b10 '
1#
#40
0#
#45
b11 "
b11 '
1#
#50
0#
#55
b100 "
b100 '
1#
#60
0#
#65
b101 "
b101 '
1#
#70
0#
#75
b110 "
b110 '
1#
#80
0#
#85
b111 "
b111 '
1#
#90
0#
#95
b1000 "
b1000 '
1#
#100
0#
0$
#105
1#
#110
0#
#115
1#
#120
0#
#125
1#
#130
0#
#135
1#
#140
0#
#145
1#
#150
0#
#155
1#
#160
0#
#165
1#
#170
0#
#175
1#
#180
0#
#185
1#
#190
0#
#195
1#
#200
0#
1$
#205
b1001 "
b1001 '
1#
#210
0#
#215
b1010 "
b1010 '
1#
#220
0#
#225
b1011 "
b1011 '
1#
#230
0#
#235
b1100 "
b1100 '
1#
#240
0#
#245
b1101 "
b1101 '
1#
#250
0#
#255
b1110 "
b1110 '
1#
#260
0#
#265
b1111 "
b1111 '
1#
#270
0#
#275
b10000 "
b10000 '
1#
#280
0#
#285
b10001 "
b10001 '
1#
#290
0#
#295
b10010 "
b10010 '
1#
#300
0#
#305
b10011 "
b10011 '
1#
#310
0#
#315
b10100 "
b10100 '
1#
#320
0#
#325
b10101 "
b10101 '
1#
#330
0#
#335
b10110 "
b10110 '
1#
#340
0#
#345
b10111 "
b10111 '
1#
#350
0#
#355
b11000 "
b11000 '
1#
#360
0#
#365
b11001 "
b11001 '
1#
#370
0#
#375
b11010 "
b11010 '
1#
#380
0#
#385
b11011 "
b11011 '
1#
#390
0#
#395
b11100 "
b11100 '
1#
#400
0#
#405
b11101 "
b11101 '
1#
#410
0#
#415
b11110 "
b11110 '
1#
#420
0#
#425
b11111 "
b11111 '
1#
#430
0#
#435
b100000 "
b100000 '
1#
#440
0#
#445
b100001 "
b100001 '
1#
#450
0#
#455
b100010 "
b100010 '
1#
#460
0#
#465
b100011 "
b100011 '
1#
#470
0#
#475
b100100 "
b100100 '
1#
#480
0#
#485
b100101 "
b100101 '
1#
#490
0#
#495
b100110 "
b100110 '
1#
#500
0#
#505
b100111 "
b100111 '
1#
#510
0#
#515
b101000 "
b101000 '
1#
#520
0#
#525
b101001 "
b101001 '
1#
#530
0#
#535
b101010 "
b101010 '
1#
#540
0#
#545
b101011 "
b101011 '
1#
#550
0#
#555
b101100 "
b101100 '
1#
#560
0#
#565
b101101 "
b101101 '
1#
#570
0#
#575
b101110 "
b101110 '
1#
#580
0#
#585
b101111 "
b101111 '
1#
#590
0#
#595
b110000 "
b110000 '
1#
#600
0#
#605
b110001 "
b110001 '
1#
#610
0#
#615
b110010 "
b110010 '
1#
#620
0#
#625
b110011 "
b110011 '
1#
#630
0#
#635
b110100 "
b110100 '
1#
#640
0#
#645
b110101 "
b110101 '
1#
#650
0#
#655
b110110 "
b110110 '
1#
#660
0#
#665
b110111 "
b110111 '
1#
#670
0#
#675
b111000 "
b111000 '
1#
#680
0#
#685
b111001 "
b111001 '
1#
#690
0#
#695
b111010 "
b111010 '
1#
#700
0#
#705
b111011 "
b111011 '
1#
#710
0#
#715
b111100 "
b111100 '
1#
#720
0#
#725
b111101 "
b111101 '
1#
#730
0#
#735
b111110 "
b111110 '
1#
#740
0#
#745
b111111 "
b111111 '
1#
#750
0#
#755
b1000000 "
b1000000 '
1#
#760
0#
#765
b1000001 "
b1000001 '
1#
#770
0#
#775
b1000010 "
b1000010 '
1#
#780
0#
#785
b1000011 "
b1000011 '
1#
#790
0#
#795
b1000100 "
b1000100 '
1#
#800
0#
#805
b1000101 "
b1000101 '
1#
#810
0#
#815
b1000110 "
b1000110 '
1#
#820
0#
#825
b1000111 "
b1000111 '
1#
#830
0#
#835
b1001000 "
b1001000 '
1#
#840
0#
#845
b1001001 "
b1001001 '
1#
#850
0#
#855
b1001010 "
b1001010 '
1#
#860
0#
#865
b1001011 "
b1001011 '
1#
#870
0#
#875
b1001100 "
b1001100 '
1#
#880
0#
#885
b1001101 "
b1001101 '
1#
#890
0#
#895
b1001110 "
b1001110 '
1#
#900
0#
#905
b1001111 "
b1001111 '
1#
#910
0#
#915
b1010000 "
b1010000 '
1#
#920
0#
#925
b1010001 "
b1010001 '
1#
#930
0#
#935
b1010010 "
b1010010 '
1#
#940
0#
#945
b1010011 "
b1010011 '
1#
#950
0#
#955
b1010100 "
b1010100 '
1#
#960
0#
#965
b1010101 "
b1010101 '
1#
#970
0#
#975
b1010110 "
b1010110 '
1#
#980
0#
#985
b1010111 "
b1010111 '
1#
#990
0#
#995
b1011000 "
b1011000 '
1#
#1000
0#
#1005
b1011001 "
b1011001 '
1#
#1010
0#
#1015
b1011010 "
b1011010 '
1#
#1020
0#
#1025
b1011011 "
b1011011 '
1#
#1030
0#
#1035
b1011100 "
b1011100 '
1#
#1040
0#
#1045
b1011101 "
b1011101 '
1#
#1050
0#
#1055
b1011110 "
b1011110 '
1#
#1060
0#
#1065
b1011111 "
b1011111 '
1#
#1070
0#
#1075
b1100000 "
b1100000 '
1#
#1080
0#
#1085
b1100001 "
b1100001 '
1#
#1090
0#
#1095
b1100010 "
b1100010 '
1#
#1100
0#
#1105
b1100011 "
b1100011 '
1#
#1110
0#
#1115
b1100100 "
b1100100 '
1#
#1120
0#
#1125
b1100101 "
b1100101 '
1#
#1130
0#
#1135
b1100110 "
b1100110 '
1#
#1140
0#
#1145
b1100111 "
b1100111 '
1#
#1150
0#
#1155
b1101000 "
b1101000 '
1#
#1160
0#
#1165
b1101001 "
b1101001 '
1#
#1170
0#
#1175
b1101010 "
b1101010 '
1#
#1180
0#
#1185
b1101011 "
b1101011 '
1#
#1190
0#
#1195
b1101100 "
b1101100 '
1#
#1200
0#
#1205
b1101101 "
b1101101 '
1#
#1210
0#
#1215
b1101110 "
b1101110 '
1#
#1220
0#
#1225
b1101111 "
b1101111 '
1#
#1230
0#
#1235
b1110000 "
b1110000 '
1#
#1240
0#
#1245
b1110001 "
b1110001 '
1#
#1250
0#
#1255
b1110010 "
b1110010 '
1#
#1260
0#
#1265
b1110011 "
b1110011 '
1#
#1270
0#
#1275
b1110100 "
b1110100 '
1#
#1280
0#
#1285
b1110101 "
b1110101 '
1#
#1290
0#
#1295
b1110110 "
b1110110 '
1#
#1300
0#
#1305
b1110111 "
b1110111 '
1#
#1310
0#
#1315
b1111000 "
b1111000 '
1#
#1320
0#
#1325
b1111001 "
b1111001 '
1#
#1330
0#
#1335
b1111010 "
b1111010 '
1#
#1340
0#
#1345
b1111011 "
b1111011 '
1#
#1350
0#
#1355
b1111100 "
b1111100 '
1#
#1360
0#
#1365
b1111101 "
b1111101 '
1#
#1370
0#
#1375
b1111110 "
b1111110 '
1#
#1380
0#
#1385
1!
b1111111 "
b1111111 '
1#
#1390
0#
#1395
0!
b0 "
b0 '
1#
#1400
0#
#1405
b1 "
b1 '
1#
#1410
0#
#1415
b10 "
b10 '
1#
#1420
0#
#1425
b11 "
b11 '
1#
#1430
0#
#1435
b100 "
b100 '
1#
#1440
0#
#1445
b101 "
b101 '
1#
#1450
0#
#1455
b110 "
b110 '
1#
#1460
0#
#1465
b111 "
b111 '
1#
#1470
0#
#1475
b1000 "
b1000 '
1#
#1480
0#
#1485
b1001 "
b1001 '
1#
#1490
0#
#1495
b1010 "
b1010 '
1#
#1500
0#
#1505
b1011 "
b1011 '
1#
#1510
0#
#1515
b1100 "
b1100 '
1#
#1520
0#
#1525
b1101 "
b1101 '
1#
#1530
0#
#1535
b1110 "
b1110 '
1#
#1540
0#
#1545
b1111 "
b1111 '
1#
#1550
0#
#1555
b10000 "
b10000 '
1#
#1560
0#
#1565
b10001 "
b10001 '
1#
#1570
0#
#1575
b10010 "
b10010 '
1#
#1580
0#
#1585
b10011 "
b10011 '
1#
#1590
0#
#1595
b10100 "
b10100 '
1#
#1600
0#
#1605
b10101 "
b10101 '
1#
#1610
0#
#1615
b10110 "
b10110 '
1#
#1620
0#
#1625
b10111 "
b10111 '
1#
#1630
0#
#1635
b11000 "
b11000 '
1#
#1640
0#
#1645
b11001 "
b11001 '
1#
#1650
0#
#1655
b11010 "
b11010 '
1#
#1660
0#
#1665
b11011 "
b11011 '
1#
#1670
0#
#1675
b11100 "
b11100 '
1#
#1680
0#
#1685
b11101 "
b11101 '
1#
#1690
0#
#1695
b11110 "
b11110 '
1#
#1700
0#
#1705
b11111 "
b11111 '
1#
#1710
0#
#1715
b100000 "
b100000 '
1#
#1720
0#
#1725
b100001 "
b100001 '
1#
#1730
0#
#1735
b100010 "
b100010 '
1#
#1740
0#
#1745
b100011 "
b100011 '
1#
#1750
0#
#1755
b100100 "
b100100 '
1#
#1760
0#
#1765
b100101 "
b100101 '
1#
#1770
0#
#1775
b100110 "
b100110 '
1#
#1780
0#
#1785
b100111 "
b100111 '
1#
#1790
0#
#1795
b101000 "
b101000 '
1#
#1800
0#
#1805
b101001 "
b101001 '
1#
#1810
0#
#1815
b101010 "
b101010 '
1#
#1820
0#
#1825
b101011 "
b101011 '
1#
#1830
0#
#1835
b101100 "
b101100 '
1#
#1840
0#
#1845
b101101 "
b101101 '
1#
#1850
0#
#1855
b101110 "
b101110 '
1#
#1860
0#
#1865
b101111 "
b101111 '
1#
#1870
0#
#1875
b110000 "
b110000 '
1#
#1880
0#
#1885
b110001 "
b110001 '
1#
#1890
0#
#1895
b110010 "
b110010 '
1#
#1900
0#
#1905
b110011 "
b110011 '
1#
#1910
0#
#1915
b110100 "
b110100 '
1#
#1920
0#
#1925
b110101 "
b110101 '
1#
#1930
0#
#1935
b110110 "
b110110 '
1#
#1940
0#
#1945
b110111 "
b110111 '
1#
#1950
0#
#1955
b111000 "
b111000 '
1#
#1960
0#
#1965
b111001 "
b111001 '
1#
#1970
0#
#1975
b111010 "
b111010 '
1#
#1980
0#
#1985
b111011 "
b111011 '
1#
#1990
0#
#1995
b111100 "
b111100 '
1#
#2000
0#
#2005
b111101 "
b111101 '
1#
#2010
0#
#2015
b111110 "
b111110 '
1#
#2020
0#
#2025
b111111 "
b111111 '
1#
#2030
0#
#2035
b1000000 "
b1000000 '
1#
#2040
0#
#2045
b1000001 "
b1000001 '
1#
#2050
0#
#2055
b1000010 "
b1000010 '
1#
#2060
0#
#2065
b1000011 "
b1000011 '
1#
#2070
0#
#2075
b1000100 "
b1000100 '
1#
#2080
0#
#2085
b1000101 "
b1000101 '
1#
#2090
0#
#2095
b1000110 "
b1000110 '
1#
#2100
0#
#2105
b1000111 "
b1000111 '
1#
#2110
0#
#2115
b1001000 "
b1001000 '
1#
#2120
0#
#2125
b1001001 "
b1001001 '
1#
#2130
0#
#2135
b1001010 "
b1001010 '
1#
#2140
0#
#2145
b1001011 "
b1001011 '
1#
#2150
0#
#2155
b1001100 "
b1001100 '
1#
#2160
0#
#2165
b1001101 "
b1001101 '
1#
#2170
0#
#2175
b1001110 "
b1001110 '
1#
#2180
0#
#2185
b1001111 "
b1001111 '
1#
#2190
0#
#2195
b1010000 "
b1010000 '
1#
#2200
0#
#2205
b1010001 "
b1010001 '
1#
#2210
0#
#2215
b1010010 "
b1010010 '
1#
#2220
0#
#2225
b1010011 "
b1010011 '
1#
#2230
0#
#2235
b1010100 "
b1010100 '
1#
#2240
0#
#2245
b1010101 "
b1010101 '
1#
#2250
0#
#2255
b1010110 "
b1010110 '
1#
#2260
0#
#2265
b1010111 "
b1010111 '
1#
#2270
0#
#2275
b1011000 "
b1011000 '
1#
#2280
0#
#2285
b1011001 "
b1011001 '
1#
#2290
0#
#2295
b1011010 "
b1011010 '
1#
#2300
0#
#2305
b1011011 "
b1011011 '
1#
#2310
0#
#2315
b1011100 "
b1011100 '
1#
#2320
0#
#2325
b1011101 "
b1011101 '
1#
#2330
0#
#2335
b1011110 "
b1011110 '
1#
#2340
0#
#2345
b1011111 "
b1011111 '
1#
#2350
0#
#2355
b1100000 "
b1100000 '
1#
#2360
0#
#2365
b1100001 "
b1100001 '
1#
#2370
0#
#2375
b1100010 "
b1100010 '
1#
#2380
0#
#2385
b1100011 "
b1100011 '
1#
#2390
0#
#2395
b1100100 "
b1100100 '
1#
#2400
0#
#2405
b1100101 "
b1100101 '
1#
#2410
0#
#2415
b1100110 "
b1100110 '
1#
#2420
0#
#2425
b1100111 "
b1100111 '
1#
#2430
0#
#2435
b1101000 "
b1101000 '
1#
#2440
0#
#2445
b1101001 "
b1101001 '
1#
#2450
0#
#2455
b1101010 "
b1101010 '
1#
#2460
0#
#2465
b1101011 "
b1101011 '
1#
#2470
0#
#2475
b1101100 "
b1101100 '
1#
#2480
0#
#2485
b1101101 "
b1101101 '
1#
#2490
0#
#2495
b1101110 "
b1101110 '
1#
#2500
0#
#2505
b1101111 "
b1101111 '
1#
#2510
0#
#2515
b1110000 "
b1110000 '
1#
#2520
0#
#2525
b1110001 "
b1110001 '
1#
#2530
0#
#2535
b1110010 "
b1110010 '
1#
#2540
0#
#2545
b1110011 "
b1110011 '
1#
#2550
0#
#2555
b1110100 "
b1110100 '
1#
#2560
0#
#2565
b1110101 "
b1110101 '
1#
#2570
0#
#2575
b1110110 "
b1110110 '
1#
#2580
0#
#2585
b1110111 "
b1110111 '
1#
#2590
0#
#2595
b1111000 "
b1111000 '
1#
#2600
0#
#2605
b1111001 "
b1111001 '
1#
#2610
0#
#2615
b1111010 "
b1111010 '
1#
#2620
0#
#2625
b1111011 "
b1111011 '
1#
#2630
0#
#2635
b1111100 "
b1111100 '
1#
#2640
0#
#2645
b1111101 "
b1111101 '
1#
#2650
0#
#2655
b1111110 "
b1111110 '
1#
#2660
0#
#2665
1!
b1111111 "
b1111111 '
1#
#2670
0#
#2675
0!
b0 "
b0 '
1#
#2680
0#
#2685
b1 "
b1 '
1#
#2690
0#
#2695
b10 "
b10 '
1#
#2700
0#
#2705
b11 "
b11 '
1#
#2710
0#
#2715
b100 "
b100 '
1#
#2720
0#
#2725
b101 "
b101 '
1#
#2730
0#
#2735
b110 "
b110 '
1#
#2740
0#
#2745
b111 "
b111 '
1#
#2750
0#
#2755
b1000 "
b1000 '
1#
#2760
0#
#2765
b1001 "
b1001 '
1#
#2770
0#
#2775
b1010 "
b1010 '
1#
#2780
0#
#2785
b1011 "
b1011 '
1#
#2790
0#
#2795
b1100 "
b1100 '
1#
#2800
0#
#2805
b1101 "
b1101 '
1#
#2810
0#
#2815
b1110 "
b1110 '
1#
#2820
0#
#2825
b1111 "
b1111 '
1#
#2830
0#
#2835
b10000 "
b10000 '
1#
#2840
0#
#2845
b10001 "
b10001 '
1#
#2850
0#
#2855
b10010 "
b10010 '
1#
#2860
0#
#2865
b10011 "
b10011 '
1#
#2870
0#
#2875
b10100 "
b10100 '
1#
#2880
0#
#2885
b10101 "
b10101 '
1#
#2890
0#
#2895
b10110 "
b10110 '
1#
#2900
0#
#2905
b10111 "
b10111 '
1#
#2910
0#
#2915
b11000 "
b11000 '
1#
#2920
0#
#2925
b11001 "
b11001 '
1#
#2930
0#
#2935
b11010 "
b11010 '
1#
#2940
0#
#2945
b11011 "
b11011 '
1#
#2950
0#
#2955
b11100 "
b11100 '
1#
#2960
0#
#2965
b11101 "
b11101 '
1#
#2970
0#
#2975
b11110 "
b11110 '
1#
#2980
0#
#2985
b11111 "
b11111 '
1#
#2990
0#
#2995
b100000 "
b100000 '
1#
#3000
0#
#3005
b100001 "
b100001 '
1#
#3010
0#
#3015
b100010 "
b100010 '
1#
#3020
0#
#3025
b100011 "
b100011 '
1#
#3030
0#
#3035
b100100 "
b100100 '
1#
#3040
0#
#3045
b100101 "
b100101 '
1#
#3050
0#
#3055
b100110 "
b100110 '
1#
#3060
0#
#3065
b100111 "
b100111 '
1#
#3070
0#
#3075
b101000 "
b101000 '
1#
#3080
0#
#3085
b101001 "
b101001 '
1#
#3090
0#
#3095
b101010 "
b101010 '
1#
#3100
0#
#3105
b101011 "
b101011 '
1#
#3110
0#
#3115
b101100 "
b101100 '
1#
#3120
0#
#3125
b101101 "
b101101 '
1#
#3130
0#
#3135
b101110 "
b101110 '
1#
#3140
0#
#3145
b101111 "
b101111 '
1#
#3150
0#
#3155
b110000 "
b110000 '
1#
#3160
0#
#3165
b110001 "
b110001 '
1#
#3170
0#
#3175
b110010 "
b110010 '
1#
#3180
0#
#3185
b110011 "
b110011 '
1#
#3190
0#
#3195
b110100 "
b110100 '
1#
#3200
0#
#3205
b110101 "
b110101 '
1#
#3210
0#
#3215
b110110 "
b110110 '
1#
#3220
0#
#3225
b110111 "
b110111 '
1#
#3230
0#
#3235
b111000 "
b111000 '
1#
#3240
0#
#3245
b111001 "
b111001 '
1#
#3250
0#
#3255
b111010 "
b111010 '
1#
#3260
0#
#3265
b111011 "
b111011 '
1#
#3270
0#
#3275
b111100 "
b111100 '
1#
#3280
0#
#3285
b111101 "
b111101 '
1#
#3290
0#
#3295
b111110 "
b111110 '
1#
#3300
0#
#3305
b111111 "
b111111 '
1#
#3310
0#
#3315
b1000000 "
b1000000 '
1#
#3320
0#
#3325
b1000001 "
b1000001 '
1#
#3330
0#
#3335
b1000010 "
b1000010 '
1#
#3340
0#
#3345
b1000011 "
b1000011 '
1#
#3350
0#
#3355
b1000100 "
b1000100 '
1#
#3360
0#
#3365
b1000101 "
b1000101 '
1#
#3370
0#
#3375
b1000110 "
b1000110 '
1#
#3380
0#
#3385
b1000111 "
b1000111 '
1#
#3390
0#
#3395
b1001000 "
b1001000 '
1#
#3400
0#
#3405
b1001001 "
b1001001 '
1#
#3410
0#
#3415
b1001010 "
b1001010 '
1#
#3420
0#
#3425
b1001011 "
b1001011 '
1#
#3430
0#
#3435
b1001100 "
b1001100 '
1#
#3440
0#
#3445
b1001101 "
b1001101 '
1#
#3450
0#
#3455
b1001110 "
b1001110 '
1#
#3460
0#
#3465
b1001111 "
b1001111 '
1#
#3470
0#
#3475
b1010000 "
b1010000 '
1#
#3480
0#
#3485
b1010001 "
b1010001 '
1#
#3490
0#
#3495
b1010010 "
b1010010 '
1#
#3500
0#
#3505
b1010011 "
b1010011 '
1#
#3510
0#
#3515
b1010100 "
b1010100 '
1#
#3520
0#
#3525
b1010101 "
b1010101 '
1#
#3530
0#
#3535
b1010110 "
b1010110 '
1#
#3540
0#
#3545
b1010111 "
b1010111 '
1#
#3550
0#
#3555
b1011000 "
b1011000 '
1#
#3560
0#
#3565
b1011001 "
b1011001 '
1#
#3570
0#
#3575
b1011010 "
b1011010 '
1#
#3580
0#
#3585
b1011011 "
b1011011 '
1#
#3590
0#
#3595
b1011100 "
b1011100 '
1#
#3600
0#
#3605
b1011101 "
b1011101 '
1#
#3610
0#
#3615
b1011110 "
b1011110 '
1#
#3620
0#
#3625
b1011111 "
b1011111 '
1#
#3630
0#
#3635
b1100000 "
b1100000 '
1#
#3640
0#
#3645
b1100001 "
b1100001 '
1#
#3650
0#
#3655
b1100010 "
b1100010 '
1#
#3660
0#
#3665
b1100011 "
b1100011 '
1#
#3670
0#
#3675
b1100100 "
b1100100 '
1#
#3680
0#
#3685
b1100101 "
b1100101 '
1#
#3690
0#
#3695
b1100110 "
b1100110 '
1#
#3700
0#
#3705
b1100111 "
b1100111 '
1#
#3710
0#
#3715
b1101000 "
b1101000 '
1#
#3720
0#
#3725
b1101001 "
b1101001 '
1#
#3730
0#
#3735
b1101010 "
b1101010 '
1#
#3740
0#
#3745
b1101011 "
b1101011 '
1#
#3750
0#
#3755
b1101100 "
b1101100 '
1#
#3760
0#
#3765
b1101101 "
b1101101 '
1#
#3770
0#
#3775
b1101110 "
b1101110 '
1#
#3780
0#
#3785
b1101111 "
b1101111 '
1#
#3790
0#
#3795
b1110000 "
b1110000 '
1#
#3800
0#
#3805
b1110001 "
b1110001 '
1#
#3810
0#
#3815
b1110010 "
b1110010 '
1#
#3820
0#
#3825
b1110011 "
b1110011 '
1#
#3830
0#
#3835
b1110100 "
b1110100 '
1#
#3840
0#
#3845
b1110101 "
b1110101 '
1#
#3850
0#
#3855
b1110110 "
b1110110 '
1#
#3860
0#
#3865
b1110111 "
b1110111 '
1#
#3870
0#
#3875
b1111000 "
b1111000 '
1#
#3880
0#
#3885
b1111001 "
b1111001 '
1#
#3890
0#
#3895
b1111010 "
b1111010 '
1#
#3900
0#
#3905
b1111011 "
b1111011 '
1#
#3910
0#
#3915
b1111100 "
b1111100 '
1#
#3920
0#
#3925
b1111101 "
b1111101 '
1#
#3930
0#
#3935
b1111110 "
b1111110 '
1#
#3940
0#
#3945
1!
b1111111 "
b1111111 '
1#
#3950
0#
#3955
0!
b0 "
b0 '
1#
#3960
0#
#3965
b1 "
b1 '
1#
#3970
0#
#3975
b10 "
b10 '
1#
#3980
0#
#3985
b11 "
b11 '
1#
#3990
0#
#3995
b100 "
b100 '
1#
#4000
0#
#4005
b101 "
b101 '
1#
#4010
0#
#4015
b110 "
b110 '
1#
#4020
0#
#4025
b111 "
b111 '
1#
#4030
0#
#4035
b1000 "
b1000 '
1#
#4040
0#
#4045
b1001 "
b1001 '
1#
#4050
0#
#4055
b1010 "
b1010 '
1#
#4060
0#
#4065
b1011 "
b1011 '
1#
#4070
0#
#4075
b1100 "
b1100 '
1#
#4080
0#
#4085
b1101 "
b1101 '
1#
#4090
0#
#4095
b1110 "
b1110 '
1#
#4100
0#
#4105
b1111 "
b1111 '
1#
#4110
0#
#4115
b10000 "
b10000 '
1#
#4120
0#
#4125
b10001 "
b10001 '
1#
#4130
0#
#4135
b10010 "
b10010 '
1#
#4140
0#
#4145
b10011 "
b10011 '
1#
#4150
0#
#4155
b10100 "
b10100 '
1#
#4160
0#
#4165
b10101 "
b10101 '
1#
#4170
0#
#4175
b10110 "
b10110 '
1#
#4180
0#
#4185
b10111 "
b10111 '
1#
#4190
0#
#4195
b11000 "
b11000 '
1#
#4200
0#
#4205
b11001 "
b11001 '
1#
#4210
0#
#4215
b11010 "
b11010 '
1#
#4220
0#
#4225
b11011 "
b11011 '
1#
#4230
0#
#4235
b11100 "
b11100 '
1#
#4240
0#
#4245
b11101 "
b11101 '
1#
#4250
0#
#4255
b11110 "
b11110 '
1#
#4260
0#
#4265
b11111 "
b11111 '
1#
#4270
0#
#4275
b100000 "
b100000 '
1#
#4280
0#
#4285
b100001 "
b100001 '
1#
#4290
0#
#4295
b100010 "
b100010 '
1#
#4300
0#
#4305
b100011 "
b100011 '
1#
#4310
0#
#4315
b100100 "
b100100 '
1#
#4320
0#
#4325
b100101 "
b100101 '
1#
#4330
0#
#4335
b100110 "
b100110 '
1#
#4340
0#
#4345
b100111 "
b100111 '
1#
#4350
0#
#4355
b101000 "
b101000 '
1#
#4360
0#
#4365
b101001 "
b101001 '
1#
#4370
0#
#4375
b101010 "
b101010 '
1#
#4380
0#
#4385
b101011 "
b101011 '
1#
#4390
0#
#4395
b101100 "
b101100 '
1#
#4400
0#
#4405
b101101 "
b101101 '
1#
#4410
0#
#4415
b101110 "
b101110 '
1#
#4420
0#
#4425
b101111 "
b101111 '
1#
#4430
0#
#4435
b110000 "
b110000 '
1#
#4440
0#
#4445
b110001 "
b110001 '
1#
#4450
0#
#4455
b110010 "
b110010 '
1#
#4460
0#
#4465
b110011 "
b110011 '
1#
#4470
0#
#4475
b110100 "
b110100 '
1#
#4480
0#
#4485
b110101 "
b110101 '
1#
#4490
0#
#4495
b110110 "
b110110 '
1#
#4500
0#
#4505
b110111 "
b110111 '
1#
#4510
0#
#4515
b111000 "
b111000 '
1#
#4520
0#
#4525
b111001 "
b111001 '
1#
#4530
0#
#4535
b111010 "
b111010 '
1#
#4540
0#
#4545
b111011 "
b111011 '
1#
#4550
0#
#4555
b111100 "
b111100 '
1#
#4560
0#
#4565
b111101 "
b111101 '
1#
#4570
0#
#4575
b111110 "
b111110 '
1#
#4580
0#
#4585
b111111 "
b111111 '
1#
#4590
0#
#4595
b1000000 "
b1000000 '
1#
#4600
0#
#4605
b1000001 "
b1000001 '
1#
#4610
0#
#4615
b1000010 "
b1000010 '
1#
#4620
0#
#4625
b1000011 "
b1000011 '
1#
#4630
0#
#4635
b1000100 "
b1000100 '
1#
#4640
0#
#4645
b1000101 "
b1000101 '
1#
#4650
0#
#4655
b1000110 "
b1000110 '
1#
#4660
0#
#4665
b1000111 "
b1000111 '
1#
#4670
0#
#4675
b1001000 "
b1001000 '
1#
#4680
0#
#4685
b1001001 "
b1001001 '
1#
#4690
0#
#4695
b1001010 "
b1001010 '
1#
#4700
0#
#4705
b1001011 "
b1001011 '
1#
#4710
0#
#4715
b1001100 "
b1001100 '
1#
#4720
0#
#4725
b1001101 "
b1001101 '
1#
#4730
0#
#4735
b1001110 "
b1001110 '
1#
#4740
0#
#4745
b1001111 "
b1001111 '
1#
#4750
0#
#4755
b1010000 "
b1010000 '
1#
#4760
0#
#4765
b1010001 "
b1010001 '
1#
#4770
0#
#4775
b1010010 "
b1010010 '
1#
#4780
0#
#4785
b1010011 "
b1010011 '
1#
#4790
0#
#4795
b1010100 "
b1010100 '
1#
#4800
0#
#4805
b1010101 "
b1010101 '
1#
#4810
0#
#4815
b1010110 "
b1010110 '
1#
#4820
0#
#4825
b1010111 "
b1010111 '
1#
#4830
0#
#4835
b1011000 "
b1011000 '
1#
#4840
0#
#4845
b1011001 "
b1011001 '
1#
#4850
0#
#4855
b1011010 "
b1011010 '
1#
#4860
0#
#4865
b1011011 "
b1011011 '
1#
#4870
0#
#4875
b1011100 "
b1011100 '
1#
#4880
0#
#4885
b1011101 "
b1011101 '
1#
#4890
0#
#4895
b1011110 "
b1011110 '
1#
#4900
0#
#4905
b1011111 "
b1011111 '
1#
#4910
0#
#4915
b1100000 "
b1100000 '
1#
#4920
0#
#4925
b1100001 "
b1100001 '
1#
#4930
0#
#4935
b1100010 "
b1100010 '
1#
#4940
0#
#4945
b1100011 "
b1100011 '
1#
#4950
0#
#4955
b1100100 "
b1100100 '
1#
#4960
0#
#4965
b1100101 "
b1100101 '
1#
#4970
0#
#4975
b1100110 "
b1100110 '
1#
#4980
0#
#4985
b1100111 "
b1100111 '
1#
#4990
0#
#4995
b1101000 "
b1101000 '
1#
#5000
0#
#5005
b1101001 "
b1101001 '
1#
#5010
0#
#5015
b1101010 "
b1101010 '
1#
#5020
0#
#5025
b1101011 "
b1101011 '
1#
#5030
0#
#5035
b1101100 "
b1101100 '
1#
#5040
0#
#5045
b1101101 "
b1101101 '
1#
#5050
0#
#5055
b1101110 "
b1101110 '
1#
#5060
0#
#5065
b1101111 "
b1101111 '
1#
#5070
0#
#5075
b1110000 "
b1110000 '
1#
#5080
0#
#5085
b1110001 "
b1110001 '
1#
#5090
0#
#5095
b1110010 "
b1110010 '
1#
#5100
0#
#5105
b1110011 "
b1110011 '
1#
#5110
0#
#5115
b1110100 "
b1110100 '
1#
#5120
0#
#5125
b1110101 "
b1110101 '
1#
#5130
0#
#5135
b1110110 "
b1110110 '
1#
#5140
0#
#5145
b1110111 "
b1110111 '
1#
#5150
0#
#5155
b1111000 "
b1111000 '
1#
#5160
0#
#5165
b1111001 "
b1111001 '
1#
#5170
0#
#5175
b1111010 "
b1111010 '
1#
#5180
0#
#5185
b1111011 "
b1111011 '
1#
#5190
0#
#5195
b1111100 "
b1111100 '
1#
#5200
0#
#5205
b1111101 "
b1111101 '
1#
