spi_by_IC2ICU/defines.sv
`define CPOL 0      //clock polarity
`define CPHA 0      //clock phase
`define CLK_FREQ 50_000_000  // input clk frequency
`define SCLK_FREQ  5_000_000  // sclk frequency
`define DATA_WIDTH 8            // a word width
`define CLK_CYCLE 20

spi_by_IC2ICU/spi.sv
`include "defines.sv"

module SPI_MASTER(
    input   wire                        clk     ,
    input   wire                        rst_n   ,
    input   wire                        miso    ,
    input   wire    [`DATA_WIDTH-1:0]   data_i  ,
    input   wire                        start   ,

    output  wire                        mosi    ,
    output  reg                         sclk    ,
    output  reg                         ss_n    ,
    output  wire                        finish
);
    parameter       IDLE    =   5'b00001  ,
                    //CHOOSE  =   5'b00010  ,
                    DATA    =   5'b00100  ,
                    EXTRA   =   5'b01000  ,
                    FINISH  =   5'b10000  ;

    parameter       CNT_MAX =   `CLK_FREQ / `SCLK_FREQ - 1;

    reg     [31:0]      cnt                     ;   //sclk的时钟周期的计数器
    reg     [4:0]       state                   ;
    reg     [4:0]       nx_state                ;
    wire    [3:0]       cnt_data                ;   //输出的数据计数器
    reg                 sclk_dly                ;   //sclk的打一拍信号
    reg     [3:0]       cnt_sclk_pos            ;   //sclk的上升沿计数器信号
    reg     [3:0]       cnt_sclk_neg            ;   //sclk的下降沿计数器信号
    reg                 start_dly               ;   //start的打一拍信号
    reg     [3:0]       cnt_data_dly            ;

    wire                cnt_max_flag            ;   //计数器cnt达到最大值的信号
    wire                dec_pos_or_neg_sample   ;   //1 posedge sample, 0 negedge sample
    wire                sclk_posedge            ;   //sclk的上升沿
    wire                sclk_negedge            ;   //sclk的下降沿


    assign  dec_pos_or_neg_sample = (`CPOL == `CPHA) ? 1'b1 : 1'b0;

    assign cnt_max_flag = (cnt == CNT_MAX ) ? 1'b1 : 1'b0;
    assign sclk_posedge = ((sclk == 1'b1) && (sclk_dly == 1'b0)) ? 1'b1 : 1'b0;
    assign sclk_negedge = ((sclk == 1'b0) && (sclk_dly == 1'b1)) ? 1'b1 : 1'b0;
    assign cnt_data = dec_pos_or_neg_sample ? cnt_sclk_pos : cnt_sclk_neg;

    always @(posedge clk or negedge rst_n) begin
        sclk_dly <= sclk;
        start_dly <= start;
    end

    always @(posedge clk or negedge rst_n) begin
        if(!rst_n) begin
            cnt_sclk_pos <= 4'd0;
        end
        else if(state == FINISH) begin
            cnt_sclk_pos <= 4'd0;
        end
        //else if((sclk_posedge) && (cnt_sclk_pos == `DATA_WIDTH - 1)) begin
        //    cnt_sclk_pos <= `DATA_WIDTH - 1;
        //end
        else if(sclk_posedge) begin
            cnt_sclk_pos <= cnt_sclk_pos + 1'b1;
        end
        else begin
            cnt_sclk_pos <= cnt_sclk_pos;
        end
    end

    always @(posedge clk or negedge rst_n) begin
        if(!rst_n) begin
            cnt_sclk_neg <= 4'd0;
        end
        else if(state == FINISH) begin
            cnt_sclk_neg <= 4'd0;
        end
        //else if((sclk_negedge) && (cnt_sclk_neg == `DATA_WIDTH - 1)) begin
        //    cnt_sclk_neg <= `DATA_WIDTH - 1;
        //end
        else if(sclk_negedge) begin
            cnt_sclk_neg <= cnt_sclk_neg + 1'b1;
        end
        else begin
            cnt_sclk_neg <= cnt_sclk_neg;
        end
    end
    always @(posedge clk or negedge rst_n) begin
        if(!rst_n) begin
            state <= IDLE;
        end
        else begin
            state <= nx_state;
        end
    end

    always @(*) begin
        nx_state <= IDLE;
        case(state)
            IDLE:   nx_state <= start_dly ? DATA : IDLE;
            DATA:   nx_state <= (cnt_data == `DATA_WIDTH) ? (`CPHA == 0) ? EXTRA : FINISH : DATA;
            EXTRA:  nx_state <= cnt_max_flag ? FINISH : EXTRA ;
            FINISH: nx_state <= IDLE;
            default:nx_state <= IDLE;
        endcase
    end

    always @(posedge clk or negedge rst_n) begin
        if(!rst_n) begin
            cnt <= 'd0;
        end
        else if((state == DATA) && (nx_state == FINISH) && (cnt == CNT_MAX)) begin
            cnt <= 'd0;
        end
        else if((state == DATA) && (nx_state == EXTRA) && (cnt == CNT_MAX)) begin
            cnt <= 'd0;
        end
        else if((state == DATA) && (cnt == CNT_MAX)) begin
            cnt <= 'd0;
        end
        else if((state == EXTRA) && (cnt == CNT_MAX)) begin
            cnt <= 'd0;
        end
        else if(state == DATA) begin
            cnt <= cnt + 1'b1;
        end
        else if(state == EXTRA) begin
            cnt <= cnt + 1'b1;
        end
        else begin
            cnt <= 'd0;
        end
    end

    always @(posedge clk or negedge rst_n) begin
        if(!rst_n) begin
            sclk <= (`CPOL) ? 1'b1 : 1'b0;
        end
        else if(start_dly) begin
            sclk <= ~sclk;
        end
        else if((state == DATA) && (cnt_max_flag) && (cnt_data < `DATA_WIDTH) ) begin
            sclk <= ~sclk;
        end
        else if((state == DATA) && (cnt_max_flag) && (cnt_data == `DATA_WIDTH) && (nx_state == EXTRA)) begin
            sclk <= ~sclk;
        end
        else if((state == EXTRA) && (cnt_max_flag) && (nx_state == FINISH)) begin
            sclk <= ~sclk;
        end
        else begin
            sclk <= sclk;
        end
    end

    always @(posedge clk or negedge rst_n) begin
        if(!rst_n) begin
            ss_n <= 1'b1;
        end
        else if(start) begin
            ss_n <= 1'b0;
        end
        else if(state == FINISH) begin
            ss_n <= 1'b1;
        end
        else begin
            ss_n <= ss_n;
        end
    end

    always @(posedge clk or negedge rst_n) begin
        if(!rst_n) begin
            cnt_data_dly <= 'd0;
        end
        else begin
            cnt_data_dly <= cnt_data;
        end
    end

    assign finish = (state == FINISH) ? 1'b1 : 1'b0;

    assign mosi  = (state == DATA) ? ((cnt_data_dly < `DATA_WIDTH) ? data_i[cnt_data_dly] : data_i[`DATA_WIDTH-1]) : data_i[0];
endmodule

module SPI_SLAVE(
    input   wire                        clk         ,
    input   wire                        rst_n       ,
    input   wire                        mosi        ,
    input   wire                        sclk        ,
    input   wire                        tx_finish   ,
    input   wire                        start       ,
    input   wire                        ss_n        ,

    output  wire    [`DATA_WIDTH-1:0]   data_o      ,
    //output  wire                        miso        ,
    output  wire                        r_finish
);
    parameter       IDLE    =   4'b0001     ,
                    RV_DATA =   4'b0010     ,
                    FINISH  =   4'b0100     ;

    wire                        sclk_posedge        ;
    wire                        sclk_negedge        ;
    wire                        dec_pos_or_neg_sample;
    //wire                        sclk_posedge        ;
    //wire                        sclk_negedge        ;


    reg                         sclk_dly            ;
    reg     [`DATA_WIDTH-1:0]   data_shift_pos      ;
    reg     [`DATA_WIDTH-1:0]   data_shift_neg      ;
    reg     [3:0]               state               ;
    reg     [3:0]               nx_state            ;
    reg     [3:0]               cnt_sclk_pos        ;
    reg     [3:0]               cnt_sclk_neg        ;
    wire    [3:0]               num_sample_data     ;

    assign  sclk_posedge = ((sclk == 1'b1) && (sclk_dly == 1'b0)) ? 1'b1 : 1'b0;
    assign  sclk_negedge = ((sclk == 1'b0) && (sclk_dly == 1'b1)) ? 1'b1 : 1'b0;
    assign  dec_pos_or_neg_sample = (`CPOL == `CPHA) ? 1'b1 : 1'b0;
    //assign  sclk_posedge = ((sclk == 1'b1) && (sclk_dly == 1'b0)) ? 1'b1 : 1'b0;
    //assign  sclk_negedge = ((sclk == 1'b0) && (sclk_dly == 1'b1)) ? 1'b1 : 1'b0;
    assign  num_sample_data = (dec_pos_or_neg_sample) ? cnt_sclk_pos : cnt_sclk_neg;

    always @(posedge clk or negedge rst_n) begin
        sclk_dly <= sclk;
    end

    always @(posedge clk or negedge rst_n) begin
        if(!rst_n) begin
            state <= IDLE;
        end
        else begin
            state <= nx_state;
        end
    end

    always @(*) begin
        nx_state <= IDLE;
        case(state)
            IDLE: nx_state <= start ? RV_DATA :IDLE;
            RV_DATA: begin
                if((num_sample_data == 7) && (dec_pos_or_neg_sample) && (sclk_posedge) && (!ss_n)) begin
                    nx_state <= FINISH;
                end
                else if((num_sample_data == 7) && (~dec_pos_or_neg_sample) && (sclk_negedge) && (!ss_n)) begin
                    nx_state <= FINISH;
                end
                else begin
                    nx_state <= RV_DATA;
                end
            end
            FINISH: nx_state <= IDLE;
        endcase
    end


    always @(posedge clk or negedge rst_n) begin
        if(!rst_n) begin
            cnt_sclk_pos <= 4'd0;
        end
        else if((state == FINISH)) begin
            cnt_sclk_pos <= 4'd0;
        end
        else if(sclk_posedge) begin
            cnt_sclk_pos <= cnt_sclk_pos + 1'b1;
        end
        else begin
            cnt_sclk_pos <= cnt_sclk_pos;
        end
    end

    always @(posedge clk or negedge rst_n) begin
        if(!rst_n) begin
            cnt_sclk_neg <= 4'd0;
        end
        else if (state == FINISH) begin
            cnt_sclk_neg <= 4'd0;
        end
        else if (sclk_negedge) begin
            cnt_sclk_neg <= cnt_sclk_neg + 1'b1;
        end
        else begin
            cnt_sclk_neg <= cnt_sclk_neg;
        end
    end

    always @(posedge clk or negedge rst_n) begin
        if(!rst_n) begin
            data_shift_pos <= {`DATA_WIDTH{1'b0}};
        end
        else if((state == RV_DATA) && (sclk_posedge)) begin
            data_shift_pos <= {mosi, data_shift_pos[`DATA_WIDTH-1:1]};
        end
        else if (state == FINISH) begin
            data_shift_pos <= {`DATA_WIDTH{1'b0}};
        end
        else begin
            data_shift_pos <= data_shift_pos;
        end
    end

    always @(posedge clk or negedge rst_n) begin
        if(!rst_n) begin
            data_shift_neg <= {`DATA_WIDTH{1'b0}};
        end
        else if((state == RV_DATA) && (sclk_negedge)) begin
            data_shift_neg <= {mosi, data_shift_neg[`DATA_WIDTH-1:1]};
        end
        else if(state == FINISH) begin
            data_shift_neg <= {`DATA_WIDTH{1'b0}};
        end
        else begin
            data_shift_neg <= data_shift_neg;
        end
    end

    //assign data_o = dec_pos_or_neg_sample ? data_shift_pos : data_shift_neg;

    assign  data_o = (state == FINISH) ? (dec_pos_or_neg_sample ? data_shift_pos : data_shift_neg): {`DATA_WIDTH{1'b0}};
    assign  r_finish = (state == FINISH);




endmodule

spi_by_IC2ICU/tb_spi.sv
`timescale  1ns/1ns
`include "defines.sv"

module tb_master_slave();

    reg                         clk         ;
    reg                         rst_n       ;
    //reg                         mosi        ;
    reg     [`DATA_WIDTH-1:0]   data_i      ;
    reg                         start       ;
    reg                         miso        ;

    wire                        mosi        ;
    wire                        sclk        ;
    wire                        finish      ;
    wire                        ss_n        ;
    wire    [`DATA_WIDTH-1:0]   data_o      ;
    wire                        r_finish    ;

    SPI_MASTER u_spi_master (
        .clk    (clk)       ,
        .rst_n  (rst_n)     ,
        .miso   (miso)      ,
        .data_i (data_i)    ,
        .start  (start)     ,

        .mosi   (mosi)      ,
        .sclk   (sclk)      ,
        .finish (finish)    ,
        .ss_n   (ss_n)
    );

    SPI_SLAVE u_spi_slave(
        .clk    (clk)       ,
        .rst_n  (rst_n)     ,
        .mosi   (mosi)      ,
        .sclk   (sclk)      ,
        .tx_finish(finish),
        .start  (start)     ,
        .ss_n   (ss_n)      ,

        .data_o (data_o)    ,
        .r_finish(r_finish)
    );

    initial begin
         clk = 1'b0;
         rst_n = 1'b0;
         start = 1'b0;
         data_i = 8'h35;
         miso = 1'b0;
         #30
         rst_n = 1'b1;
         #10;
         @(posedge clk);
         start <= 1'b1;
         @(posedge clk);
         start <= 1'b0;
         @(negedge finish);
         data_i = 8'h44;
         repeat(2) @(posedge clk);
         start = 1'b1;
         @(posedge clk);
         start = 1'b0;
    end

    always #(`CLK_CYCLE / 2) clk = ~clk;
    initial begin
        $dumpfile("wave.vcd");
        $dumpvars(0, tb_master_slave );
    #10000 $finish;
    end
endmodule

spi_by_IC2ICU/wave.vcd
$date
	Sun Jun 02 22:27:20 2024
$end
$version
	Icarus Verilog
$end
$timescale
	1ns
$end
$scope module tb_master_slave $end
$var wire 1 ! ss_n $end
$var wire 1 " sclk $end
$var wire 1 # r_finish $end
$var wire 1 $ mosi $end
$var wire 1 % finish $end
$var wire 8 & data_o [7:0] $end
$var reg 1 ' clk $end
$var reg 8 ( data_i [7:0] $end
$var reg 1 ) miso $end
$var reg 1 * rst_n $end
$var reg 1 + start $end
$scope module u_spi_master $end
$var wire 1 ' clk $end
$var wire 8 , data_i [7:0] $end
$var wire 1 - dec_pos_or_neg_sample $end
$var wire 1 ) miso $end
$var wire 1 * rst_n $end
$var wire 1 + start $end
$var wire 1 . sclk_posedge $end
$var wire 1 / sclk_negedge $end
$var wire 1 $ mosi $end
$var wire 1 % finish $end
$var wire 1 0 cnt_max_flag $end
$var wire 4 1 cnt_data [3:0] $end
$var parameter 33 2 CNT_MAX $end
$var parameter 5 3 DATA $end
$var parameter 5 4 EXTRA $end
$var parameter 5 5 FINISH $end
$var parameter 5 6 IDLE $end
$var reg 32 7 cnt [31:0] $end
$var reg 4 8 cnt_data_dly [3:0] $end
$var reg 4 9 cnt_sclk_neg [3:0] $end
$var reg 4 : cnt_sclk_pos [3:0] $end
$var reg 5 ; nx_state [4:0] $end
$var reg 1 " sclk $end
$var reg 1 < sclk_dly $end
$var reg 1 ! ss_n $end
$var reg 1 = start_dly $end
$var reg 5 > state [4:0] $end
$upscope $end
$scope module u_spi_slave $end
$var wire 1 ' clk $end
$var wire 1 ? dec_pos_or_neg_sample $end
$var wire 1 $ mosi $end
$var wire 4 @ num_sample_data [3:0] $end
$var wire 1 * rst_n $end
$var wire 1 " sclk $end
$var wire 1 ! ss_n $end
$var wire 1 + start $end
$var wire 1 % tx_finish $end
$var wire 1 A sclk_posedge $end
$var wire 1 B sclk_negedge $end
$var wire 1 # r_finish $end
$var wire 8 C data_o [7:0] $end
$var parameter 4 D FINISH $end
$var parameter 4 E IDLE $end
$var parameter 4 F RV_DATA $end
$var reg 4 G cnt_sclk_neg [3:0] $end
$var reg 4 H cnt_sclk_pos [3:0] $end
$var reg 8 I data_shift_neg [7:0] $end
$var reg 8 J data_shift_pos [7:0] $end
$var reg 4 K nx_state [3:0] $end
$var reg 1 L sclk_dly $end
$var reg 4 M state [3:0] $end
$upscope $end
$upscope $end
$enddefinitions $end
$comment Show the parameter values. $end
$dumpall
b10 F
b1 E
b100 D
b1 6
b10000 5
b1000 4
b100 3
b1001 2
$end
#0
$dumpvars
b1 M
xL
b1 K
b0 J
b0 I
b0 H
b0 G
b0 C
xB
0A
b0 @
1?
b1 >
0=
x<
b1 ;
b0 :
b0 9
b0 8
b0 7
b0 1
00
x/
0.
1-
b110101 ,
0+
0*
0)
b110101 (
0'
b0 &
0%
1$
0#
0"
1!
$end
#10
0B
0/
0L
0<
1'
#20
0'
#30
1'
1*
#40
0'
#50
b10 K
1+
1'
#60
0'
#70
b100 ;
b10 K
1=
0!
b10 M
0+
1'
#80
0'
#90
b10 K
b100 ;
1A
1.
1"
b100 >
0=
1'
#100
0'
#110
b100 ;
b10 K
0.
0A
1<
b1 1
b1 :
b1 7
1L
b1 @
b1 H
b10000000 J
1'
#120
0'
#130
0$
b1 8
b10 7
1'
#140
0'
#150
b11 7
1'
#160
0'
#170
b100 7
1'
#180
0'
#190
b101 7
1'
#200
0'
#210
b110 7
1'
#220
0'
#230
b111 7
1'
#240
0'
#250
b1000 7
1'
#260
0'
#270
b100 ;
10
b1001 7
1'
#280
0'
#290
b10 K
b100 ;
1B
1/
00
0"
b0 7
1'
#300
0'
#310
b10 K
0/
0B
0<
b1 9
b1 7
0L
b1 G
1'
#320
0'
#330
b10 7
1'
#340
0'
#350
b11 7
1'
#360
0'
#370
b100 7
1'
#380
0'
#390
b101 7
1'
#400
0'
#410
b110 7
1'
#420
0'
#430
b111 7
1'
#440
0'
#450
b1000 7
1'
#460
0'
#470
b100 ;
10
b1001 7
1'
#480
0'
#490
b10 K
b100 ;
1A
1.
00
1"
b0 7
1'
#500
0'
#510
b100 ;
b10 K
0.
0A
1<
b10 1
b10 :
b1 7
1L
b10 @
b10 H
b1000000 J
1'
#520
0'
#530
1$
b10 8
b10 7
1'
#540
0'
#550
b11 7
1'
#560
0'
#570
b100 7
1'
#580
0'
#590
b101 7
1'
#600
0'
#610
b110 7
1'
#620
0'
#630
b111 7
1'
#640
0'
#650
b1000 7
1'
#660
0'
#670
b100 ;
10
b1001 7
1'
#680
0'
#690
b10 K
b100 ;
1B
1/
00
0"
b0 7
1'
#700
0'
#710
b10 K
0/
0B
0<
b10 9
b1 7
0L
b10 G
b10000000 I
1'
#720
0'
#730
b10 7
1'
#740
0'
#750
b11 7
1'
#760
0'
#770
b100 7
1'
#780
0'
#790
b101 7
1'
#800
0'
#810
b110 7
1'
#820
0'
#830
b111 7
1'
#840
0'
#850
b1000 7
1'
#860
0'
#870
b100 ;
10
b1001 7
1'
#880
0'
#890
b10 K
b100 ;
1A
1.
00
1"
b0 7
1'
#900
0'
#910
b100 ;
b10 K
0.
0A
1<
b11 1
b11 :
b1 7
1L
b11 @
b11 H
b10100000 J
1'
#920
0'
#930
0$
b11 8
b10 7
1'
#940
0'
#950
b11 7
1'
#960
0'
#970
b100 7
1'
#980
0'
#990
b101 7
1'
#1000
0'
#1010
b110 7
1'
#1020
0'
#1030
b111 7
1'
#1040
0'
#1050
b1000 7
1'
#1060
0'
#1070
b100 ;
10
b1001 7
1'
#1080
0'
#1090
b10 K
b100 ;
1B
1/
00
0"
b0 7
1'
#1100
0'
#1110
b10 K
0/
0B
0<
b11 9
b1 7
0L
b11 G
b1000000 I
1'
#1120
0'
#1130
b10 7
1'
#1140
0'
#1150
b11 7
1'
#1160
0'
#1170
b100 7
1'
#1180
0'
#1190
b101 7
1'
#1200
0'
#1210
b110 7
1'
#1220
0'
#1230
b111 7
1'
#1240
0'
#1250
b1000 7
1'
#1260
0'
#1270
b100 ;
10
b1001 7
1'
#1280
0'
#1290
b10 K
b100 ;
1A
1.
00
1"
b0 7
1'
#1300
0'
#1310
b100 ;
b10 K
0.
0A
1<
b100 1
b100 :
b1 7
1L
b100 @
b100 H
b1010000 J
1'
#1320
0'
#1330
1$
b100 8
b10 7
1'
#1340
0'
#1350
b11 7
1'
#1360
0'
#1370
b100 7
1'
#1380
0'
#1390
b101 7
1'
#1400
0'
#1410
b110 7
1'
#1420
0'
#1430
b111 7
1'
#1440
0'
#1450
b1000 7
1'
#1460
0'
#1470
b100 ;
10
b1001 7
1'
#1480
0'
#1490
b10 K
b100 ;
1B
1/
00
0"
b0 7
1'
#1500
0'
#1510
b10 K
0/
0B
0<
b100 9
b1 7
0L
b100 G
b10100000 I
1'
#1520
0'
#1530
b10 7
1'
#1540
0'
#1550
b11 7
1'
#1560
0'
#1570
b100 7
1'
#1580
0'
#1590
b101 7
1'
#1600
0'
#1610
b110 7
1'
#1620
0'
#1630
b111 7
1'
#1640
0'
#1650
b1000 7
1'
#1660
0'
#1670
b100 ;
10
b1001 7
1'
#1680
0'
#1690
b10 K
b100 ;
1A
1.
00
1"
b0 7
1'
#1700
0'
#1710
b100 ;
b10 K
0.
0A
1<
b101 1
b101 :
b1 7
1L
b101 @
b101 H
b10101000 J
1'
#1720
0'
#1730
b101 8
b10 7
1'
#1740
0'
#1750
b11 7
1'
#1760
0'
#1770
b100 7
1'
#1780
0'
#1790
b101 7
1'
#1800
0'
#1810
b110 7
1'
#1820
0'
#1830
b111 7
1'
#1840
0'
#1850
b1000 7
1'
#1860
0'
#1870
b100 ;
10
b1001 7
1'
#1880
0'
#1890
b10 K
b100 ;
1B
1/
00
0"
b0 7
1'
#1900
0'
#1910
b10 K
0/
0B
0<
b101 9
b1 7
0L
b101 G
b11010000 I
1'
#1920
0'
#1930
b10 7
1'
#1940
0'
#1950
b11 7
1'
#1960
0'
#1970
b100 7
1'
#1980
0'
#1990
b101 7
1'
#2000
0'
#2010
b110 7
1'
#2020
0'
#2030
b111 7
1'
#2040
0'
#2050
b1000 7
1'
#2060
0'
#2070
b100 ;
10
b1001 7
1'
#2080
0'
#2090
b10 K
b100 ;
1A
1.
00
1"
b0 7
1'
#2100
0'
#2110
b100 ;
b10 K
0.
0A
1<
b110 1
b110 :
b1 7
1L
b110 @
b110 H
b11010100 J
1'
#2120
0'
#2130
0$
b110 8
b10 7
1'
#2140
0'
#2150
b11 7
1'
#2160
0'
#2170
b100 7
1'
#2180
0'
#2190
b101 7
1'
#2200
0'
#2210
b110 7
1'
#2220
0'
#2230
b111 7
1'
#2240
0'
#2250
b1000 7
1'
#2260
0'
#2270
b100 ;
10
b1001 7
1'
#2280
0'
#2290
b10 K
b100 ;
1B
1/
00
0"
b0 7
1'
#2300
0'
#2310
b10 K
0/
0B
0<
b110 9
b1 7
0L
b110 G
b1101000 I
1'
#2320
0'
#2330
b10 7
1'
#2340
0'
#2350
b11 7
1'
#2360
0'
#2370
b100 7
1'
#2380
0'
#2390
b101 7
1'
#2400
0'
#2410
b110 7
1'
#2420
0'
#2430
b111 7
1'
#2440
0'
#2450
b1000 7
1'
#2460
0'
#2470
b100 ;
10
b1001 7
1'
#2480
0'
#2490
b10 K
b100 ;
1A
1.
00
1"
b0 7
1'
#2500
0'
#2510
b100 ;
b10 K
0.
0A
1<
b111 1
b111 :
b1 7
1L
b111 @
b111 H
b1101010 J
1'
#2520
0'
#2530
b111 8
b10 7
1'
#2540
0'
#2550
b11 7
1'
#2560
0'
#2570
b100 7
1'
#2580
0'
#2590
b101 7
1'
#2600
0'
#2610
b110 7
1'
#2620
0'
#2630
b111 7
1'
#2640
0'
#2650
b1000 7
1'
#2660
0'
#2670
b100 ;
10
b1001 7
1'
#2680
0'
#2690
b10 K
b100 ;
1B
1/
00
0"
b0 7
1'
#2700
0'
#2710
b10 K
0/
0B
0<
b111 9
b1 7
0L
b111 G
b110100 I
1'
#2720
0'
#2730
b10 7
1'
#2740
0'
#2750
b11 7
1'
#2760
0'
#2770
b100 7
1'
#2780
0'
#2790
b101 7
1'
#2800
0'
#2810
b110 7
1'
#2820
0'
#2830
b111 7
1'
#2840
0'
#2850
b1000 7
1'
#2860
0'
#2870
b100 ;
10
b1001 7
1'
#2880
0'
#2890
b100 K
b100 ;
1A
1.
00
1"
b0 7
1'
#2900
0'
#2910
b1000 ;
b1 K
0.
0A
b110101 &
b110101 C
1<
b1000 1
b1000 :
b1 7
1L
1#
b100 M
b1000 @
b1000 H
b110101 J
1'
#2920
0'
#2930
b1000 ;
b0 &
b0 C
1$
b0 I
b0 J
b0 G
b0 @
b0 H
0#
b1 M
b1000 8
b10 7
b1000 >
1'
#2940
0'
#2950
b11 7
1'
#2960
0'
#2970
b100 7
1'
#2980
0'
#2990
b101 7
1'
#3000
0'
#3010
b110 7
1'
#3020
0'
#3030
b111 7
1'
#3040
0'
#3050
b1000 7
1'
#3060
0'
#3070
b10000 ;
10
b1001 7
1'
#3080
0'
#3090
b1 ;
1B
1/
00
1%
0"
b0 7
b10000 >
1'
#3100
0'
#3110
0$
0/
0B
b1000100 (
b1000100 ,
0%
0<
b0 1
b0 :
b0 9
b1 >
1!
0L
b1 G
1'
#3120
0'
#3130
b0 8
1'
#3140
0'
#3150
b100 ;
b10 K
1=
0!
1+
1'
#3160
0'
#3170
b100 ;
1A
1.
b10 K
b10 M
1"
b100 >
0=
0+
1'
#3180
0'
#3190
b100 ;
b10 K
0.
0A
1<
b1 1
b1 :
b1 7
1L
b1 @
b1 H
1'
#3200
0'
#3210
b1 8
b10 7
1'
#3220
0'
#3230
b11 7
1'
#3240
0'
#3250
b100 7
1'
#3260
0'
#3270
b101 7
1'
#3280
0'
#3290
b110 7
1'
#3300
0'
#3310
b111 7
1'
#3320
0'
#3330
b1000 7
1'
#3340
0'
#3350
b100 ;
10
b1001 7
1'
#3360
0'
#3370
b10 K
b100 ;
1B
1/
00
0"
b0 7
1'
#3380
0'
#3390
b10 K
0/
0B
0<
b1 9
b1 7
0L
b10 G
1'
#3400
0'
#3410
b10 7
1'
#3420
0'
#3430
b11 7
1'
#3440
0'
#3450
b100 7
1'
#3460
0'
#3470
b101 7
1'
#3480
0'
#3490
b110 7
1'
#3500
0'
#3510
b111 7
1'
#3520
0'
#3530
b1000 7
1'
#3540
0'
#3550
b100 ;
10
b1001 7
1'
#3560
0'
#3570
b10 K
b100 ;
1A
1.
00
1"
b0 7
1'
#3580
0'
#3590
b100 ;
b10 K
0.
0A
1<
b10 1
b10 :
b1 7
1L
b10 @
b10 H
1'
#3600
0'
#3610
1$
b10 8
b10 7
1'
#3620
0'
#3630
b11 7
1'
#3640
0'
#3650
b100 7
1'
#3660
0'
#3670
b101 7
1'
#3680
0'
#3690
b110 7
1'
#3700
0'
#3710
b111 7
1'
#3720
0'
#3730
b1000 7
1'
#3740
0'
#3750
b100 ;
10
b1001 7
1'
#3760
0'
#3770
b10 K
b100 ;
1B
1/
00
0"
b0 7
1'
#3780
0'
#3790
b10 K
0/
0B
0<
b10 9
b1 7
0L
b11 G
b10000000 I
1'
#3800
0'
#3810
b10 7
1'
#3820
0'
#3830
b11 7
1'
#3840
0'
#3850
b100 7
1'
#3860
0'
#3870
b101 7
1'
#3880
0'
#3890
b110 7
1'
#3900
0'
#3910
b111 7
1'
#3920
0'
#3930
b1000 7
1'
#3940
0'
#3950
b100 ;
10
b1001 7
1'
#3960
0'
#3970
b10 K
b100 ;
1A
1.
00
1"
b0 7
1'
#3980
0'
#3990
b100 ;
b10 K
0.
0A
1<
b11 1
b11 :
b1 7
1L
b11 @
b11 H
b10000000 J
1'
#4000
0'
#4010
0$
b11 8
b10 7
1'
#4020
0'
#4030
b11 7
1'
#4040
0'
#4050
b100 7
1'
#4060
0'
#4070
b101 7
1'
#4080
0'
#4090
b110 7
1'
#4100
0'
#4110
b111 7
1'
#4120
0'
#4130
b1000 7
1'
#4140
0'
#4150
b100 ;
10
b1001 7
1'
#4160
0'
#4170
b10 K
b100 ;
1B
1/
00
0"
b0 7
1'
#4180
0'
#4190
b10 K
0/
0B
0<
b11 9
b1 7
0L
b100 G
b1000000 I
1'
#4200
0'
#4210
b10 7
1'
#4220
0'
#4230
b11 7
1'
#4240
0'
#4250
b100 7
1'
#4260
0'
#4270
b101 7
1'
#4280
0'
#4290
b110 7
1'
#4300
0'
#4310
b111 7
1'
#4320
0'
#4330
b1000 7
1'
#4340
0'
#4350
b100 ;
10
b1001 7
1'
#4360
0'
#4370
b10 K
b100 ;
1A
1.
00
1"
b0 7
1'
#4380
0'
#4390
b100 ;
b10 K
0.
0A
1<
b100 1
b100 :
b1 7
1L
b100 @
b100 H
b1000000 J
1'
#4400
0'
#4410
b100 8
b10 7
1'
#4420
0'
#4430
b11 7
1'
#4440
0'
#4450
b100 7
1'
#4460
0'
#4470
b101 7
1'
#4480
0'
#4490
b110 7
1'
#4500
0'
#4510
b111 7
1'
#4520
0'
#4530
b1000 7
1'
#4540
0'
#4550
b100 ;
10
b1001 7
1'
#4560
0'
#4570
b10 K
b100 ;
1B
1/
00
0"
b0 7
1'
#4580
0'
#4590
b10 K
0/
0B
0<
b100 9
b1 7
0L
b101 G
b100000 I
1'
#4600
0'
#4610
b10 7
1'
#4620
0'
#4630
b11 7
1'
#4640
0'
#4650
b100 7
1'
#4660
0'
#4670
b101 7
1'
#4680
0'
#4690
b110 7
1'
#4700
0'
#4710
b111 7
1'
#4720
0'
#4730
b1000 7
1'
#4740
0'
#4750
b100 ;
10
b1001 7
1'
#4760
0'
#4770
b10 K
b100 ;
1A
1.
00
1"
b0 7
1'
#4780
0'
#4790
b100 ;
b10 K
0.
0A
1<
b101 1
b101 :
b1 7
1L
b101 @
b101 H
b100000 J
1'
#4800
0'
#4810
b101 8
b10 7
1'
#4820
0'
#4830
b11 7
1'
#4840
0'
#4850
b100 7
1'
#4860
0'
#4870
b101 7
1'
#4880
0'
#4890
b110 7
1'
#4900
0'
#4910
b111 7
1'
#4920
0'
#4930
b1000 7
1'
#4940
0'
#4950
b100 ;
10
b1001 7
1'
#4960
0'
#4970
b10 K
b100 ;
1B
1/
00
0"
b0 7
1'
#4980
0'
#4990
b10 K
0/
0B
0<
b101 9
b1 7
0L
b110 G
b10000 I
1'
#5000
0'
#5010
b10 7
1'
#5020
0'
#5030
b11 7
1'
#5040
0'
#5050
b100 7
1'
#5060
0'
#5070
b101 7
1'
#5080
0'
#5090
b110 7
1'
#5100
0'
#5110
b111 7
1'
#5120
0'
#5130
b1000 7
1'
#5140
0'
#5150
b100 ;
10
b1001 7
1'
#5160
0'
#5170
b10 K
b100 ;
1A
1.
00
1"
b0 7
1'
#5180
0'
#5190
b100 ;
b10 K
0.
0A
1<
b110 1
b110 :
b1 7
1L
b110 @
b110 H
b10000 J
1'
#5200
0'
#5210
1$
b110 8
b10 7
1'
#5220
0'
#5230
b11 7
1'
#5240
0'
#5250
b100 7
1'
#5260
0'
#5270
b101 7
1'
#5280
0'
#5290
b110 7
1'
#5300
0'
#5310
b111 7
1'
#5320
0'
#5330
b1000 7
1'
#5340
0'
#5350
b100 ;
10
b1001 7
1'
#5360
0'
#5370
b10 K
b100 ;
1B
1/
00
0"
b0 7
1'
#5380
0'
#5390
b10 K
0/
0B
0<
b110 9
b1 7
0L
b111 G
b10001000 I
1'
#5400
0'
#5410
b10 7
1'
#5420
0'
#5430
b11 7
1'
#5440
0'
#5450
b100 7
1'
#5460
0'
#5470
b101 7
1'
#5480
0'
#5490
b110 7
1'
#5500
0'
#5510
b111 7
1'
#5520
0'
#5530
b1000 7
1'
#5540
0'
#5550
b100 ;
10
b1001 7
1'
#5560
0'
#5570
b10 K
b100 ;
1A
1.
00
1"
b0 7
1'
#5580
0'
#5590
b100 ;
b10 K
0.
0A
1<
b111 1
b111 :
b1 7
1L
b111 @
b111 H
b10001000 J
1'
#5600
0'
#5610
0$
b111 8
b10 7
1'
#5620
0'
#5630
b11 7
1'
#5640
0'
#5650
b100 7
1'
#5660
0'
#5670
b101 7
1'
#5680
0'
#5690
b110 7
1'
#5700
0'
#5710
b111 7
1'
#5720
0'
#5730
b1000 7
1'
#5740
0'
#5750
b100 ;
10
b1001 7
1'
#5760
0'
#5770
b10 K
b100 ;
1B
1/
00
0"
b0 7
1'
#5780
0'
